Workbook

Sheet 参数优化说明
A1: 全行业景气度量化跟踪体系｜参数优化说明
A2: 数据口径：保留原工作簿“截至2026年5月”的数值。本版优化权重、公式和阈值口径；不把旧数值视为实时投资数据。
A4: 审计结论 | B4: 原表无公式；43个行业页权重和均大于1；细分行业原加权分可超过10；总览与行业页未链接。
A5: 本版修复 | B5: 各行业归一化为先行/同步/滞后合计100%；行业综合分、分项分数和总览均改为公式联动。
A6: 阶段模板 | B6: 复苏55/30/15；扩张45/40/15；过热35/45/20；下行50/30/20；防御30/45/25（顺序为先行/同步/滞后）。
A7: 阈值原则 | B7: 价格、库存、量、利润、政策分别采用分位、变化率、季调、TTM、确认项上限；估值与交易信号单列。
A8: 使用纪律 | B8: 景气度只用于基本面筛选与排序，不能直接生成交易仓位；每次更新数据后须在Excel中重算。

Sheet 行业核心标准库
A1: 行业 | B1: 核心增长内核 | C1: 必选先行标准（未满足不得上调） | D1: 同步确认标准 | E1: 质量/盈利验证 | F1: 不作为主评分的指标 | G1: 新标理由
A2: 农林牧渔 | B2: 供给周期与养殖价差 | C2: 母猪存栏/淘汰率、仔猪价、饲料成本 | D2: 出栏量、猪鸡价、库存 | E2: 养殖现金成本、单头利润、经营现金流 | F2: 单纯CPI、年度种植面积 | G2: 供给约束决定价格，利润需在出栏兑现后确认。
A3: 基础化工 | B3: 库存周期与价差修复 | C3: 下游订单、库存、计划新增产能 | D3: 开工率、产品价差、出口 | E3: 现金成本、ROE、自由现金流 | F3: 原油绝对价格 | G3: 化工盈利取决于供需和价差，不是单一原料价格。
A4: 钢铁 | B4: 需求/去库与利润修复 | C4: 地产施工、基建实物量、库存变化 | D4: 表观消费、开工率、钢价/原料价差 | E4: 吨钢利润、现金流、应收 | F4: 钢价绝对水平 | G4: 钢价上升若库存不去化或利润不扩张，不能确认景气。
A5: 有色金属 | B5: 库存、供给约束与需求弹性 | C5: 库存、TC/RC、美元、矿端扰动 | D5: 金属价、加工费、消费量 | E5: 单位成本、资本开支、现金流 | F5: 金属绝对价格 | G5: 资源品价格需用供需紧张与加工利润验证。
A6: 电子 | B6: 库存去化与需求/产能利用率 | C6: 订单、库存周转、存储价格、终端出货 | D6: 稼动率、出货、ASP | E6: 毛利率、资本开支回报、现金流 | F6: 行业总销售单指标 | G6: AI、存储、消费电子周期不同，需拆分确认。
A7: 家用电器 | B7: 更新需求、出口和产品结构 | C7: 地产竣工、海外订单、排产 | D7: 零售/出货、出口、ASP | E7: 毛利率、渠道库存、现金流 | F7: 商品房销售 | G7: 竣工对家电更直接，销售只作前瞻背景。
A8: 食品饮料 | B8: 动销、渠道与价格带 | C8: 经销商库存、终端动销、批价 | D8: 销量、同店、收入 | E8: 毛利率、费用率、经营现金流 | F8: CPI单项 | G8: 品牌消费的核心是量价与渠道健康，不是宏观通胀。
A9: 纺织服饰 | B9: 海外库存、订单与汇率 | C9: 海外零售库存、订单、汇率 | D9: 出口、开工、零售 | E9: 库存周转、毛利率、现金流 | F9: 棉价单项 | G9: 成本变化只有传导到订单和毛利才有意义。
A10: 轻工制造 | B10: 地产后周期/出口与价差 | C10: 竣工、海外地产、原料与产品价差 | D10: 出货、开工、出口 | E10: 库存、ROE、现金流 | F10: 纸浆绝对价格 | G10: 需求与产品价差共同决定轻工盈利。
A11: 医药生物 | B11: 创新、诊疗与政策支付 | C11: IND/注册、医保政策、研发融资 | D11: 诊疗量、收入、器械出口 | E11: 毛利率、研发效率、经营现金流 | F11: 单一原料药价格 | G11: 子行业差异大，政策和商业化必须分层。
A12: 公用事业 | B12: 利用小时、燃料传导与资本回报 | C12: 来水、燃料、电价机制、装机进度 | D12: 发电量、利用小时 | E12: ROE、负债率、经营现金流 | F12: 装机规划 | G12: 规划不产生收益，利用率和现金流才决定回报。
... A44: 创新药 | B44: 研发兑现、商业化与支付 | C44: BD、临床、获批、医保/准入 | D44: 销售、处方、出海 | E44: 现金流、销售效率、研发回报 | F44: 获批数量单项 | G44: 获批不等于商业化，需用准入、处方和现金流确认。

Sheet 打分机制标准
A1: 行业景气度新打分机制（统一底层方法，行业核心标准库决定指标选择）
A3: 环节 | B3: 新标准 | C3: 理由
A4: 1. 指标可用性 | B4: 数据发布日期不滞后于其频率周期；异常值、口径变化、单月季节性先处理 | C4: 避免旧数据或异常点直接影响行业排序。
A5: 2. 单项标准化 | B5: 方向调整后使用5年滚动历史分位：P20/P40/P60/P80对应2/4/6/8分；价格和利润率另加3个月动量确认 | C5: 消除不同行业量纲差异，避免绝对阈值随通胀、技术降本而失效。
A6: 3. 因果层级 | B6: 先行仅回答“是否会变”；同步回答“是否已发生”；滞后仅验证“盈利/现金流是否兑现” | C6: 防止政策、规划、价格等相关但非因果指标主导分数。
A7: 4. 上调门槛 | B7: 行业分数上调一档，须至少2项必选先行标准+1项同步确认同向；仅先行改善时，综合分最高上调至6.5 | C7: 降低假复苏和主题驱动的误判。
A8: 5. 过热/风险扣分 | B8: 价格或估值急升但库存、需求、利润未确认时，价格指标封顶8分；现金流/应收恶化时，行业综合分扣0.5–1.5分 | C8: 价格上涨不必然转化为盈利，回款恶化会先破坏基本面。
A9: 6. 权重限制 | B9: 单项权重≤15%；政策/规划/热度单项≤8%；任一高度相关指标组（如多种价格）合计≤25% | C9: 降低重复计分和政策/情绪放大。
A10: 7. 阶段权重 | B10: 复苏55/30/15；扩张45/40/15；过热35/45/20；下行50/30/20；防御30/45/25（先行/同步/滞后） | C10: 不同阶段的信息含量不同，固定权重会滞后或误判。
A11: 8. 输出边界 | B11: 景气度只输出：行业排序、阶段、证据缺口和风险；估值、资金面、交易时点单独建模 | C11: 避免把基本面景气直接等同为买卖信号。

Sheet 全行业景气度总览
A1: 全行业景气度量化跟踪总览表（参数优化版）
A2: 本页公式连接各行业归一化评分；需按各页N列口径更新数据并打开Excel重算后，再用于横向排序。
A3: 行业名称 | B3: 先行指标 得分 | C3: 同步指标 得分 | D3: 滞后指标 得分 | E3: 综合景气度 评分 | F3: 景气度 判断 | G3: 阶段框架 | H3: 建议使用方式 | I3: 行业分类 | J3: 核心跟踪要点
A4: 农林牧渔 | B4: =农林牧渔!$P$4 -> 7.2 | C4: =农林牧渔!$P$5 -> 6.5 | D4: =农林牧渔!$P$6 -> 6.6 | E4: =农林牧渔!$G$19 -> 6.8 | F4: =IF(E4>=8.5,"强/防过热",IF(E4>=7.5,"偏强",IF(E4>=6.5,"中性偏强",IF(E4>=5,"中性",IF(E4>=3,"偏弱","低迷"))))) -> 中性偏强 | G4: 强周期/供给出清 | H4: 基本面筛选与排序；非交易仓位指令 | I4: 一级行业 | J4: 先用库存、供给、订单确认反转；价格本身不能直接等同高景气。
A5: 基础化工 | B5: =基础化工!$P$4 -> 8 | C5: =基础化工!$P$5 -> 6.8 | D5: =基础化工!$P$6 -> 6.6 | E5: =基础化工!$G$18 -> 7.4 | F5: =IF(E5>=8.5,"强/防过热",IF(E5>=7.5,"偏强",IF(E5>=6.5,"中性偏强",IF(E5>=5,"中性",IF(E5>=3,"偏弱","低迷"))))) -> 中性偏强 | G5: 强周期/供给出清 | H5: 基本面筛选与排序；非交易仓位指令 | I5: 一级行业 | J5: 先用库存、供给、订单确认反转；价格本身不能直接等同高景气。
A6: 钢铁 | B6: =钢铁!$P$4 -> 8 | C6: =钢铁!$P$5 -> 6 | D6: =钢铁!$P$6 -> 6 | E6: =钢铁!$G$18 -> 7 | F6: =IF(E6>=8.5,"强/防过热",IF(E6>=7.5,"偏强",IF(E6>=6.5,"中性偏强",IF(E6>=5,"中性",IF(E6>=3,"偏弱","低迷"))))) -> 中性偏强 | G6: 强周期/供给出清 | H6: 基本面筛选与排序；非交易仓位指令 | I6: 一级行业 | J6: 先用库存、供给、订单确认反转；价格本身不能直接等同高景气。
A7: 有色金属 | B7: =有色金属!$P$4 -> 6.9 | C7: =有色金属!$P$5 -> 8.7 | D7: =有色金属!$P$6 -> 8.6 | E7: =有色金属!$G$18 -> 7.9 | F7: =IF(E7>=8.5,"强/防过热",IF(E7>=7.5,"偏强",IF(E7>=6.5,"中性偏强",IF(E7>=5,"中性",IF(E7>=3,"偏弱","低迷"))))) -> 偏强 | G7: 资源品/宏观供需 | H7: 基本面筛选与排序；非交易仓位指令 | I7: 一级行业 | J7: 库存、加工费、美元和价格共同确认。
A8: 电子 | B8: =电子!$P$4 -> 8.2 | C8: =电子!$P$5 -> 7.2 | D8: =电子!$P$6 -> 8 | E8: =电子!$G$19 -> 7.8 | F8: =IF(E8>=8.5,"强/防过热",IF(E8>=7.5,"偏强",IF(E8>=6.5,"中性偏强",IF(E8>=5,"中性",IF(E8>=3,"偏弱","低迷"))))) -> 偏强 | G8: 科技制造/订单库存周期 | H8: 基本面筛选与排序；非交易仓位指令 | I8: 一级行业 | J8: 订单、库存和利用率优先；不同子行业拆分后再汇总。
A9: 家用电器 | B9: =家用电器!$P$4 -> 5.3 | C9: =家用电器!$P$5 -> 7.2 | D9: =家用电器!$P$6 -> 7.4 | E9: =家用电器!$G$18 -> 6.5 | F9: =IF(E9>=8.5,"强/防过热",IF(E9>=7.5,"偏强",IF(E9>=6.5,"中性偏强",IF(E9>=5,"中性",IF(E9>=3,"偏弱","低迷"))))) -> 中性偏强 | G9: 消费/需求恢复 | H9: 基本面筛选与排序；非交易仓位指令 | I9: 一级行业 | J9: 高频需求、渠道库存和价格/利润交叉确认，使用季调数据。
A10: 食品饮料 | B10: =食品饮料!$P$4 -> 5.9 | C10: =食品饮料!$P$5 -> 6.8 | D10: =食品饮料!$P$6 -> 7.4 | E10: =食品饮料!$G$18 -> 6.7 | F10: =IF(E10>=8.5,"强/防过热",IF(E10>=7.5,"偏强",IF(E10>=6.5,"中性偏强",IF(E10>=5,"中性",IF(E10>=3,"偏弱","低迷"))))) -> 中性偏强 | G10: 防御/成熟 | H10: 基本面筛选与排序；非交易仓位指令 | I10: 一级行业 | J10: 同步经营和现金流优先；先行指标只作边际变化确认。
A11: 纺织服饰 | B11: =纺织服饰!$P$4 -> 7.6 | C11: =纺织服饰!$P$5 -> 6.7 | D11: =纺织服饰!$P$6 -> 6 | E11: =纺织服饰!$G$18 -> 6.9 | F11: =IF(E11>=8.5,"强/防过热",IF(E11>=7.5,"偏强",IF(E11>=6.5,"中性偏强",IF(E11>=5,"中性",IF(E11>=3,"偏弱","低迷"))))) -> 中性偏强 | G11: 消费/需求恢复 | H11: 基本面筛选与排序；非交易仓位指令 | I11: 一级行业 | J11: 高频需求、渠道库存和价格/利润交叉确认，使用季调数据。
A12: 轻工制造 | B12: =轻工制造!$P$4 -> 6.6 | C12: =轻工制造!$P$5 -> 5 | D12: =轻工制造!$P$6 -> 6 | E12: =轻工制造!$G$18 -> 5.8 | F12: =IF(E12>=8.5,"强/防过热",IF(E12>=7.5,"偏强",IF(E12>=6.5,"中性偏强",IF(E12>=5,"中性",IF(E12>=3,"偏弱","低迷"))))) -> 中性 | G12: 消费/需求恢复 | H12: 基本面筛选与排序；非交易仓位指令 | I12: 一级行业 | J12: 高频需求、渠道库存和价格/利润交叉确认，使用季调数据。
A13: 医药生物 | B13: =医药生物!$P$4 -> 8 | C13: =医药生物!$P$5 -> 7.2 | D13: =医药生物!$P$6 -> 8 | E13: =医药生物!$G$18 -> 7.7 | F13: =IF(E13>=8.5,"强/防过热",IF(E13>=7.5,"偏强",IF(E13>=6.5,"中性偏强",IF(E13>=5,"中性",IF(E13>=3,"偏弱","低迷"))))) -> 偏强 | G13: 科技制造/订单库存周期 | H13: 基本面筛选与排序；非交易仓位指令 | I13: 一级行业 | J13: 订单、库存和利用率优先；不同子行业拆分后再汇总。
A14: 公用事业 | B14: =公用事业!$P$4 -> 9 | C14: =公用事业!$P$5 -> 7.1 | D14: =公用事业!$P$6 -> 8 | E14: =公用事业!$G$18 -> 7.9 | F14: =IF(E14>=8.5,"强/防过热",IF(E14>=7.5,"偏强",IF(E14>=6.5,"中性偏强",IF(E14>=5,"中性",IF(E14>=3,"偏弱","低迷"))))) -> 偏强 | G14: 防御/成熟 | H14: 基本面筛选与排序；非交易仓位指令 | I14: 一级行业 | J14: 同步经营和现金流优先；先行指标只作边际变化确认。
A15: 交通运输 | B15: =交通运输!$P$4 -> 8 | C15: =交通运输!$P$5 -> 8 | D15: =交通运输!$P$6 -> 8 | E15: =交通运输!$G$18 -> 8 | F15: =IF(E15>=8.5,"强/防过热",IF(E15>=7.5,"偏强",IF(E15>=6.5,"中性偏强",IF(E15>=5,"中性",IF(E15>=3,"偏弱","低迷"))))) -> 偏强 | G15: 消费/需求恢复 | H15: 基本面筛选与排序；非交易仓位指令 | I15: 一级行业 | J15: 高频需求、渠道库存和价格/利润交叉确认，使用季调数据。
A16: 房地产 | B16: =房地产!$P$4 -> 4.9 | C16: =房地产!$P$5 -> 4 | D16: =房地产!$P$6 -> 3.4 | E16: =房地产!$G$18 -> 4.3 | F16: =IF(E16>=8.5,"强/防过热",IF(E16>=7.5,"偏强",IF(E16>=6.5,"中性偏强",IF(E16>=5,"中性",IF(E16>=3,"偏弱","低迷"))))) -> 偏弱 | G16: 强周期/供给出清 | H16: 基本面筛选与排序；非交易仓位指令 | I16: 一级行业 | J16: 先用库存、供给、订单确认反转；价格本身不能直接等同高景气。
A17: 商贸零售 | B17: =商贸零售!$P$4 -> 5.5 | C17: =商贸零售!$P$5 -> 7.4 | D17: =商贸零售!$P$6 -> 6.6 | E17: =商贸零售!$G$18 -> 6.5 | F17: =IF(E17>=8.5,"强/防过热",IF(E17>=7.5,"偏强",IF(E17>=6.5,"中性偏强",IF(E17>=5,"中性",IF(E17>=3,"偏弱","低迷"))))) -> 中性偏强 | G17: 消费/需求恢复 | H17: 基本面筛选与排序；非交易仓位指令 | I17: 一级行业 | J17: 高频需求、渠道库存和价格/利润交叉确认，使用季调数据。
A18: 社会服务 | B18: =社会服务!$P$4 -> 7.2 | C18: =社会服务!$P$5 -> 7.6 | D18: =社会服务!$P$6 -> 5.4 | E18: =社会服务!$G$18 -> 7 | F18: =IF(E18>=8.5,"强/防过热",IF(E18>=7.5,"偏强",IF(E18>=6.5,"中性偏强",IF(E18>=5,"中性",IF(E18>=3,"偏弱","低迷"))))) -> 中性偏强 | G18: 消费/需求恢复 | H18: 基本面筛选与排序；非交易仓位指令 | I18: 一级行业 | J18: 高频需求、渠道库存和价格/利润交叉确认，使用季调数据。
A19: 综合 | B19: =综合!$P$4 -> 6.4 | C19: =综合!$P$5 -> 6.7 | D19: =综合!$P$6 -> 7.2 | E19: =综合!$G$15 -> 6.6 | F19: =IF(E19>=8.5,"强/防过热",IF(E19>=7.5,"偏强",IF(E19>=6.5,"中性偏强",IF(E19>=5,"中性",IF(E19>=3,"偏弱","低迷"))))) -> 中性偏强 | G19: 扩张/订单周期 | H19: 基本面筛选与排序；非交易仓位指令 | I19: 一级行业 | J19: 订单、需求和利润三段式确认，避免单一宏观指标主导。
A20: 建筑材料 | B20: =建筑材料!$P$4 -> 4.8 | C20: =建筑材料!$P$5 -> 4.9 | D20: =建筑材料!$P$6 -> 4 | E20: =建筑材料!$G$18 -> 4.7 | F20: =IF(E20>=8.5,"强/防过热",IF(E20>=7.5,"偏强",IF(E20>=6.5,"中性偏强",IF(E20>=5,"中性",IF(E20>=3,"偏弱","低迷"))))) -> 偏弱 | G20: 强周期/供给出清 | H20: 基本面筛选与排序；非交易仓位指令 | I20: 一级行业 | J20: 先用库存、供给、订单确认反转；价格本身不能直接等同高景气。
A21: 建筑装饰 | B21: =建筑装饰!$P$4 -> 7.1 | C21: =建筑装饰!$P$5 -> 5.3 | D21: =建筑装饰!$P$6 -> 6 | E21: =建筑装饰!$G$18 -> 6.3 | F21: =IF(E21>=8.5,"强/防过热",IF(E21>=7.5,"偏强",IF(E21>=6.5,"中性偏强",IF(E21>=5,"中性",IF(E21>=3,"偏弱","低迷"))))) -> 中性 | G21: 政策资本开支/交付 | H21: 基本面筛选与排序；非交易仓位指令 | I21: 一级行业 | J21: 政策与规划只作确认项，必须由招标、交付、回款和利润验证。
A22: 电力设备 | B22: =电力设备!$P$4 -> 8.8 | C22: =电力设备!$P$5 -> 6.4 | D22: =电力设备!$P$6 -> 5.9 | E22: =电力设备!$G$19 -> 7.4 | F22: =IF(E22>=8.5,"强/防过热",IF(E22>=7.5,"偏强",IF(E22>=6.5,"中性偏强",IF(E22>=5,"中性",IF(E22>=3,"偏弱","低迷"))))) -> 中性偏强 | G22: 政策资本开支/交付 | H22: 基本面筛选与排序；非交易仓位指令 | I22: 一级行业 | J22: 政策与规划只作确认项，必须由招标、交付、回款和利润验证。
A23: 国防军工 | B23: =国防军工!$P$4 -> 7.2 | C23: =国防军工!$P$5 -> 7.7 | D23: =国防军工!$P$6 -> 7.2 | E23: =国防军工!$G$18 -> 7.4 | F23: =IF(E23>=8.5,"强/防过热",IF(E23>=7.5,"偏强",IF(E23>=6.5,"中性偏强",IF(E23>=5,"中性",IF(E23>=3,"偏弱","低迷"))))) -> 中性偏强 | G23: 政策资本开支/交付 | H23: 基本面筛选与排序；非交易仓位指令 | I23: 一级行业 | J23: 政策与规划只作确认项，必须由招标、交付、回款和利润验证。
A24: 计算机 | B24: =计算机!$P$4 -> 8.5 | C24: =计算机!$P$5 -> 7.6 | D24: =计算机!$P$6 -> 6.6 | E24: =计算机!$G$18 -> 7.9 | F24: =IF(E24>=8.5,"强/防过热",IF(E24>=7.5,"偏强",IF(E24>=6.5,"中性偏强",IF(E24>=5,"中性",IF(E24>=3,"偏弱","低迷"))))) -> 偏强 | G24: 科技制造/订单库存周期 | H24: 基本面筛选与排序；非交易仓位指令 | I24: 一级行业 | J24: 订单、库存和利用率优先；不同子行业拆分后再汇总。
A25: 传媒 | B25: =传媒!$P$4 -> 7.2 | C25: =传媒!$P$5 -> 7 | D25: =传媒!$P$6 -> 6.6 | E25: =传媒!$G$18 -> 7 | F25: =IF(E25>=8.5,"强/防过热",IF(E25>=7.5,"偏强",IF(E25>=6.5,"中性偏强",IF(E25>=5,"中性",IF(E25>=3,"偏弱","低迷"))))) -> 中性偏强 | G25: 消费/需求恢复 | H25: 基本面筛选与排序；非交易仓位指令 | I25: 一级行业 | J25: 高频需求、渠道库存和价格/利润交叉确认，使用季调数据。
A26: 通信 | B26: =通信!$P$4 -> 9.5 | C26: =通信!$P$5 -> 8.5 | D26: =通信!$P$6 -> 8 | E26: =通信!$G$18 -> 8.9 | F26: =IF(E26>=8.5,"强/防过热",IF(E26>=7.5,"偏强",IF(E26>=6.5,"中性偏强",IF(E26>=5,"中性",IF(E26>=3,"偏弱","低迷"))))) -> 强/防过热 | G26: 科技制造/订单库存周期 | H26: 基本面筛选与排序；非交易仓位指令 | I26: 一级行业 | J26: 订单、库存和利用率优先；不同子行业拆分后再汇总。
A27: 银行 | B27: =银行!$P$4 -> 8 | C27: =银行!$P$5 -> 6.5 | D27: =银行!$P$6 -> 6.6 | E27: =银行!$G$18 -> 7 | F27: =IF(E27>=8.5,"强/防过热",IF(E27>=7.5,"偏强",IF(E27>=6.5,"中性偏强",IF(E27>=5,"中性",IF(E27>=3,"偏弱","低迷"))))) -> 中性偏强 | G27: 防御/成熟 | H27: 基本面筛选与排序；非交易仓位指令 | I27: 一级行业 | J27: 同步经营和现金流优先；先行指标只作边际变化确认。
A28: 非银金融 | B28: =非银金融!$P$4 -> 7.1 | C28: =非银金融!$P$5 -> 7.1 | D28: =非银金融!$P$6 -> 7.4 | E28: =非银金融!$G$18 -> 7.2 | F28: =IF(E28>=8.5,"强/防过热",IF(E28>=7.5,"偏强",IF(E28>=6.5,"中性偏强",IF(E28>=5,"中性",IF(E28>=3,"偏弱","低迷"))))) -> 中性偏强 | G28: 信用/风险偏好周期 | H28: 基本面筛选与排序；非交易仓位指令 | I28: 一级行业 | J28: 信用与资产质量优先；券商、保险、银行不宜混算。
A29: 汽车 | B29: =汽车!$P$4 -> 7.3 | C29: =汽车!$P$5 -> 8 | D29: =汽车!$P$6 -> 7.4 | E29: =汽车!$G$18 -> 7.6 | F29: =IF(E29>=8.5,"强/防过热",IF(E29>=7.5,"偏强",IF(E29>=6.5,"中性偏强",IF(E29>=5,"中性",IF(E29>=3,"偏弱","低迷"))))) -> 偏强 | G29: 消费/需求恢复 | H29: 基本面筛选与排序；非交易仓位指令 | I29: 一级行业 | J29: 高频需求、渠道库存和价格/利润交叉确认，使用季调数据。
A30: 机械设备 | B30: =机械设备!$P$4 -> 7.5 | C30: =机械设备!$P$5 -> 7.5 | D30: =机械设备!$P$6 -> 6 | E30: =机械设备!$G$18 -> 7.2 | F30: =IF(E30>=8.5,"强/防过热",IF(E30>=7.5,"偏强",IF(E30>=6.5,"中性偏强",IF(E30>=5,"中性",IF(E30>=3,"偏弱","低迷"))))) -> 中性偏强 | G30: 科技制造/订单库存周期 | H30: 基本面筛选与排序；非交易仓位指令 | I30: 一级行业 | J30: 订单、库存和利用率优先；不同子行业拆分后再汇总。
A31: 煤炭 | B31: =煤炭!$P$4 -> 7.6 | C31: =煤炭!$P$5 -> 7.6 | D31: =煤炭!$P$6 -> 6.6 | E31: =煤炭!$G$18 -> 7.5 | F31: =IF(E31>=8.5,"强/防过热",IF(E31>=7.5,"偏强",IF(E31>=6.5,"中性偏强",IF(E31>=5,"中性",IF(E31>=3,"偏弱","低迷"))))) -> 偏强 | G31: 强周期/供给出清 | H31: 基本面筛选与排序；非交易仓位指令 | I31: 一级行业 | J31: 先用库存、供给、订单确认反转；价格本身不能直接等同高景气。
A32: 石油石化 | B32: =石油石化!$P$4 -> 7.6 | C32: =石油石化!$P$5 -> 6 | D32: =石油石化!$P$6 -> 6.6 | E32: =石油石化!$G$18 -> 6.9 | F32: =IF(E32>=8.5,"强/防过热",IF(E32>=7.5,"偏强",IF(E32>=6.5,"中性偏强",IF(E32>=5,"中性",IF(E32>=3,"偏弱","低迷"))))) -> 中性偏强 | G32: 强周期/供给出清 | H32: 基本面筛选与排序；非交易仓位指令 | I32: 一级行业 | J32: 先用库存、供给、订单确认反转；价格本身不能直接等同高景气。
A33: 环保 | B33: =环保!$P$4 -> 8 | C33: =环保!$P$5 -> 6.5 | D33: =环保!$P$6 -> 6 | E33: =环保!$G$18 -> 7.1 | F33: =IF(E33>=8.5,"强/防过热",IF(E33>=7.5,"偏强",IF(E33>=6.5,"中性偏强",IF(E33>=5,"中性",IF(E33>=3,"偏弱","低迷"))))) -> 中性偏强 | G33: 政策资本开支/交付 | H33: 基本面筛选与排序；非交易仓位指令 | I33: 一级行业 | J33: 政策与规划只作确认项，必须由招标、交付、回款和利润验证。
A34: 美容护理 | B34: =美容护理!$P$4 -> 5.8 | C34: =美容护理!$P$5 -> 7.6 | D34: =美容护理!$P$6 -> 7.2 | E34: =美容护理!$G$18 -> 6.8 | F34: =IF(E34>=8.5,"强/防过热",IF(E34>=7.5,"偏强",IF(E34>=6.5,"中性偏强",IF(E34>=5,"中性",IF(E34>=3,"偏弱","低迷"))))) -> 中性偏强 | G34: 消费/需求恢复 | H34: 基本面筛选与排序；非交易仓位指令 | I34: 一级行业 | J34: 高频需求、渠道库存和价格/利润交叉确认，使用季调数据。
A35: 半导体 | B35: =半导体!$P$4 -> 8 | C35: =半导体!$P$5 -> 7.6 | D35: =半导体!$P$6 -> 8.6 | E35: =半导体!$G$22 -> 8 | F35: =IF(E35>=8.5,"强/防过热",IF(E35>=7.5,"偏强",IF(E35>=6.5,"中性偏强",IF(E35>=5,"中性",IF(E35>=3,"偏弱","低迷"))))) -> 偏强 | G35: 科技制造/订单库存周期 | H35: 基本面筛选与排序；非交易仓位指令 | I35: 重点细分行业 | J35: 订单、库存和利用率优先；不同子行业拆分后再汇总。
A36: 新能源 | B36: =新能源!$P$4 -> 8.6 | C36: =新能源!$P$5 -> 6.5 | D36: =新能源!$P$6 -> 5.4 | E36: =新能源!$G$22 -> 7.3 | F36: =IF(E36>=8.5,"强/防过热",IF(E36>=7.5,"偏强",IF(E36>=6.5,"中性偏强",IF(E36>=5,"中性",IF(E36>=3,"偏弱","低迷"))))) -> 中性偏强 | G36: 强周期/供给出清 | H36: 基本面筛选与排序；非交易仓位指令 | I36: 重点细分行业 | J36: 先用库存、供给、订单确认反转；价格本身不能直接等同高景气。
A37: 医药医疗 | B37: =医药医疗!$P$4 -> 8 | C37: =医药医疗!$P$5 -> 7.2 | D37: =医药医疗!$P$6 -> 8 | E37: =医药医疗!$G$22 -> 7.7 | F37: =IF(E37>=8.5,"强/防过热",IF(E37>=7.5,"偏强",IF(E37>=6.5,"中性偏强",IF(E37>=5,"中性",IF(E37>=3,"偏弱","低迷"))))) -> 偏强 | G37: 科技制造/订单库存周期 | H37: 基本面筛选与排序；非交易仓位指令 | I37: 重点细分行业 | J37: 订单、库存和利用率优先；不同子行业拆分后再汇总。
A38: 高端制造 | B38: =高端制造!$P$4 -> 7.6 | C38: =高端制造!$P$5 -> 7 | D38: =高端制造!$P$6 -> 6 | E38: =高端制造!$G$19 -> 7.2 | F38: =IF(E38>=8.5,"强/防过热",IF(E38>=7.5,"偏强",IF(E38>=6.5,"中性偏强",IF(E38>=5,"中性",IF(E38>=3,"偏弱","低迷"))))) -> 中性偏强 | G38: 科技制造/订单库存周期 | H38: 基本面筛选与排序；非交易仓位指令 | I38: 重点细分行业 | J38: 订单、库存和利用率优先；不同子行业拆分后再汇总。
A39: 人形机器人 | B39: =人形机器人!$P$4 -> 8.4 | C39: =人形机器人!$P$5 -> 7.6 | D39: =人形机器人!$P$6 -> 5.8 | E39: =人形机器人!$G$19 -> 7.8 | F39: =IF(E39>=8.5,"强/防过热",IF(E39>=7.5,"偏强",IF(E39>=6.5,"中性偏强",IF(E39>=5,"中性",IF(E39>=3,"偏弱","低迷"))))) -> 偏强 | G39: 早期产业化/兑现 | H39: 基本面筛选与排序；非交易仓位指令 | I39: 重点细分行业 | J39: 量产、订单、交付优先；热度与规划指标不得主导评分。
A40: AI算力 | B40: =AI算力!$P$4 -> 9.4 | C40: =AI算力!$P$5 -> 8.5 | D40: =AI算力!$P$6 -> 8 | E40: =AI算力!$G$19 -> 8.9 | F40: =IF(E40>=8.5,"强/防过热",IF(E40>=7.5,"偏强",IF(E40>=6.5,"中性偏强",IF(E40>=5,"中性",IF(E40>=3,"偏弱","低迷"))))) -> 强/防过热 | G40: 早期产业化/兑现 | H40: 基本面筛选与排序；非交易仓位指令 | I40: 重点细分行业 | J40: 量产、订单、交付优先；热度与规划指标不得主导评分。
A41: 锂电 | B41: =锂电!$P$4 -> 7.8 | C41: =锂电!$P$5 -> 8 | D41: =锂电!$P$6 -> 5.5 | E41: =锂电!$G$24 -> 7.5 | F41: =IF(E41>=8.5,"强/防过热",IF(E41>=7.5,"偏强",IF(E41>=6.5,"中性偏强",IF(E41>=5,"中性",IF(E41>=3,"偏弱","低迷"))))) -> 偏强 | G41: 强周期/供给出清 | H41: 基本面筛选与排序；非交易仓位指令 | I41: 重点细分行业 | J41: 先用库存、供给、订单确认反转；价格本身不能直接等同高景气。
A42: 光伏 | B42: =光伏!$P$4 -> 7.7 | C42: =光伏!$P$5 -> 7.5 | D42: =光伏!$P$6 -> 4.4 | E42: =光伏!$G$24 -> 7.1 | F42: =IF(E42>=8.5,"强/防过热",IF(E42>=7.5,"偏强",IF(E42>=6.5,"中性偏强",IF(E42>=5,"中性",IF(E42>=3,"偏弱","低迷"))))) -> 中性偏强 | G42: 强周期/供给出清 | H42: 基本面筛选与排序；非交易仓位指令 | I42: 重点细分行业 | J42: 先用库存、供给、订单确认反转；价格本身不能直接等同高景气。
A43: 风电 | B43: =风电!$P$4 -> 9.1 | C43: =风电!$P$5 -> 7.2 | D43: =风电!$P$6 -> 6.6 | E43: =风电!$G$24 -> 7.9 | F43: =IF(E43>=8.5,"强/防过热",IF(E43>=7.5,"偏强",IF(E43>=6.5,"中性偏强",IF(E43>=5,"中性",IF(E43>=3,"偏弱","低迷"))))) -> 偏强 | G43: 政策资本开支/交付 | H43: 基本面筛选与排序；非交易仓位指令 | I43: 重点细分行业 | J43: 政策与规划只作确认项，必须由招标、交付、回款和利润验证。
A44: 储能 | B44: =储能!$P$4 -> 9.2 | C44: =储能!$P$5 -> 7.1 | D44: =储能!$P$6 -> 7.1 | E44: =储能!$G$24 -> 8 | F44: =IF(E44>=8.5,"强/防过热",IF(E44>=7.5,"偏强",IF(E44>=6.5,"中性偏强",IF(E44>=5,"中性",IF(E44>=3,"偏弱","低迷"))))) -> 偏强 | G44: 政策资本开支/交付 | H44: 基本面筛选与排序；非交易仓位指令 | I44: 重点细分行业 | J44: 政策与规划只作确认项，必须由招标、交付、回款和利润验证。
A45: CXO | B45: =CXO!$P$4 -> 7.8 | C45: =CXO!$P$5 -> 7.4 | D45: =CXO!$P$6 -> 7.1 | E45: =CXO!$G$24 -> 7.6 | F45: =IF(E45>=8.5,"强/防过热",IF(E45>=7.5,"偏强",IF(E45>=6.5,"中性偏强",IF(E45>=5,"中性",IF(E45>=3,"偏弱","低迷"))))) -> 偏强 | G45: 早期产业化/兑现 | H45: 基本面筛选与排序；非交易仓位指令 | I45: 重点细分行业 | J45: 量产、订单、交付优先；热度与规划指标不得主导评分。
A46: 创新药 | B46: =创新药!$P$4 -> 8 | C46: =创新药!$P$5 -> 8 | D46: =创新药!$P$6 -> 8.1 | E46: =创新药!$G$25 -> 8 | F46: =IF(E46>=8.5,"强/防过热",IF(E46>=7.5,"偏强",IF(E46>=6.5,"中性偏强",IF(E46>=5,"中性",IF(E46>=3,"偏弱","低迷"))))) -> 偏强 | G46: 早期产业化/兑现 | H46: 基本面筛选与排序；非交易仓位指令 | I46: 重点细分行业 | J46: 量产、订单、交付优先；热度与规划指标不得主导评分。

Sheet 农林牧渔
A1: 行业景气度量化跟踪体系（参数优化版）— 农林牧渔
A2: 默认阶段框架：强周期/供给出清｜先行/同步/滞后=50%/35%/15%。先用库存、供给、订单确认反转；价格本身不能直接等同高景气。｜核心验证：供给周期与养殖价差；必选：母猪存栏/淘汰率、仔猪价、饲料成本
A3: 指标名称 | B3: 数据来源 | C3: 最新数值 | D3: 单位 | E3: 趋势 | F3: 权重 | G3: 评分 (1-10) | H3: 评分阈值说明 | I3: 历史分位 | J3: 对景气度影响 | K3: 跟踪频率 | L3: 原权重 | M3: 参数优化建议 | N3: 评分口径（更新时采用） | O3: 阶段分项 | P3: 公式分数
A4: 【第一部分：先行指标（Leading Indicators）——提前1-2个季度预示景气变化】 | O4: 先行 | P4: =ROUND(SUMPRODUCT(F5:F9,G5:G9)/SUM(F5:F9),1) -> 7.2
A5: 1-能繁母猪存栏量变化 | B5: 农业农村部 | C5: +1.2 | D5: %YoY | E5: 企稳 | F5: 0.125 | G5: 6 | H5: >5%=10分,2-5%=8分,0-2%=6分,-2-0%=4分,<-2%=2分 | I5: 45% | J5: 产能温和回升，供给端压力可控 | K5: 月度 | L5: 0.15 | M5: 目标组权重 50%；按同组相对重要性归一化。 | N5: 采用5年滚动分位+同比/环比双阈值；数据滞后超过一个频率周期时自动降权。 | O5: 同步 | P5: =ROUND(SUMPRODUCT(F11:F14,G11:G14)/SUM(F11:F14),1) -> 6.5
A6: 2-仔猪价格变化 | B6: 农业农村部/博亚和讯 | C6: +35 | D6: %YoY | E6: 大涨 | F6: 0.125 | G6: 9 | H6: >30%=10分,10-30%=8分,0-10%=6分,-10-0%=4分,<-10%=2分 | I6: 78% | J6: 补栏积极性高，预示6个月后出栏增加 | K6: 周度 | L6: 0.15 | M6: 目标组权重 50%；按同组相对重要性归一化。 | N6: 改为5年滚动分位(P20/P40/P60/P80)+3个月动量；须与库存、价差或利润交叉确认。 | O6: 滞后 | P6: =ROUND(SUMPRODUCT(F16:F18,G16:G18)/SUM(F16:F18),1) -> 6.6
A7: 3-饲料价格变化 | B7: 中国饲料工业协会 | C7: -3.5 | D7: %YoY | E7: 下行 | F7: 0.1 | G7: 8 | H7: <-10%=10分,-10-0%=8分,0-5%=6分,5-10%=4分,>10%=2分 | I7: 35% | J7: 成本端改善，养殖利润修复 | K7: 月度 | L7: 0.12 | M7: 目标组权重 50%；按同组相对重要性归一化。 | N7: 改为5年滚动分位(P20/P40/P60/P80)+3个月动量；须与库存、价差或利润交叉确认。
A8: 4-农产品进口量增速 | B8: 海关总署 | C8: +2.1 | D8: %YoY | E8: 上行 | F8: 0.0833 | G8: 6 | H8: <-5%=10分,-5-0%=8分,0-5%=6分,5-10%=4分,>10%=2分 | I8: 52% | J8: 进口平稳，国内供给基本自足 | K8: 月度 | L8: 0.1 | M8: 目标组权重 50%；按同组相对重要性归一化。 | N8: 采用5年滚动分位+同比/环比双阈值；数据滞后超过一个频率周期时自动降权。
A9: 5-种植面积变化 | B9: 国家统计局 | C9: +0.8 | D9: %YoY | E9: 企稳 | F9: 0.0667 | G9: 6 | H9: >2%=10分,0-2%=8分,-2-0%=6分,-5--2%=4分,<-5%=2分 | I9: 48% | J9: 种植面积稳定，产量预期平稳 | K9: 年度 | L9: 0.08 | M9: 目标组权重 50%；按同组相对重要性归一化。 | N9: 采用5年滚动分位+同比/环比双阈值；数据滞后超过一个频率周期时自动降权。
A10: 【第二部分：同步指标（Coincident Indicators）——与当前景气同步变动】
A11: 6-生猪出栏均价 | B11: 农业农村部 | C11: 15.8 | D11: 元/公斤 | E11: 上行 | F11: 0.1312 | G11: 6 | H11: >20=10分,16-20=8分,14-16=6分,12-14=4分,<12=2分 | I11: 55% | J11: 猪价温和回升，养殖盈利改善 | K11: 周度 | L11: 0.15 | M11: 目标组权重 35%；按同组相对重要性归一化。 | N11: 改为5年滚动分位(P20/P40/P60/P80)+3个月动量；须与库存、价差或利润交叉确认。
A12: 7-白羽肉鸡价格 | B12: 博亚和讯 | C12: 8.2 | D12: 元/公斤 | E12: 上行 | F12: 0.0875 | G12: 8 | H12: >10=10分,8-10=8分,7-8=6分,6-7=4分,<6=2分 | I12: 62% | J12: 禽价处于较好水平，养殖利润可观 | K12: 周度 | L12: 0.1 | M12: 目标组权重 35%；按同组相对重要性归一化。 | N12: 改为5年滚动分位(P20/P40/P60/P80)+3个月动量；须与库存、价差或利润交叉确认。
A13: 8-水产批发价格指数 | B13: 农业农村部 | C13: 112 | D13: 点 | E13: 上行 | F13: 0.07 | G13: 6 | H13: >120=10分,110-120=8分,100-110=6分,90-100=4分,<90=2分 | I13: 58% | J13: 水产价格温和上涨，消费旺季来临 | K13: 周度 | L13: 0.08 | M13: 目标组权重 35%；按同组相对重要性归一化。 | N13: 改为5年滚动分位(P20/P40/P60/P80)+3个月动量；须与库存、价差或利润交叉确认。
A14: 9-农产品批发价格200指数 | B14: 农业农村部 | C14: 118 | D14: 点 | E14: 上行 | F14: 0.0612 | G14: 6 | H14: >130=10分,120-130=8分,110-120=6分,100-110=4分,<100=2分 | I14: 54% | J14: 农产品价格整体平稳略升 | K14: 日度 | L14: 0.07 | M14: 目标组权重 35%；按同组相对重要性归一化。 | N14: 改为5年滚动分位(P20/P40/P60/P80)+3个月动量；须与库存、价差或利润交叉确认。
A15: 【第三部分：滞后指标（Lagging Indicators）——滞后1-2个季度反映景气变化】
A16: 10-养殖企业季度净利润率 | B16: 上市公司财报 | C16: 6.5 | D16: % | E16: 上行 | F16: 0.06 | G16: 6 | H16: >15%=10分,5-15%=8分,0-5%=6分,-5-0%=4分,<-5%=2分 | I16: 48% | J16: Q1养殖利润转正，景气度回升 | K16: 季度 | L16: 0.1 | M16: 目标组权重 15%；按同组相对重要性归一化。 | N16: 采用TTM/滚动4季同比+历史分位；剔除一次性损益，IRR按项目现金流复核。
A17: 11-农林牧渔固定资产投资增速 | B17: 国家统计局 | C17: +8.2 | D17: %YoY | E17: 上行 | F17: 0.048 | G17: 8 | H17: >15%=10分,5-15%=8分,0-5%=6分,-5-0%=4分,<-5%=2分 | I17: 60% | J17: 投资回暖，产能扩张意愿增强 | K17: 季度 | L17: 0.08 | M17: 目标组权重 15%；按同组相对重要性归一化。 | N17: 采用5年滚动分位+同比/环比双阈值；数据滞后超过一个频率周期时自动降权。
A18: 12-CPI食品项同比 | B18: 国家统计局 | C18: +1.2 | D18: % | E18: 上行 | F18: 0.042 | G18: 6 | H18: >5%=10分,2-5%=8分,0-2%=6分,-2-0%=4分,<-2%=2分 | I18: 42% | J18: 食品通胀温和，终端需求平稳 | K18: 月度 | L18: 0.07 | M18: 目标组权重 15%；按同组相对重要性归一化。 | N18: 采用5年滚动分位+同比/环比双阈值；数据滞后超过一个频率周期时自动降权。
A19: 行业综合景气度加权得分 | G19: =ROUND(SUMPRODUCT(F5:F18,G5:G18),1) -> 6.8 | H19: 综合分=Σ(建议权重×单项评分)，建议权重和=100%。

Sheet 基础化工
A1: 行业景气度量化跟踪体系（参数优化版）— 基础化工
A2: 默认阶段框架：强周期/供给出清｜先行/同步/滞后=50%/35%/15%。先用库存、供给、订单确认反转；价格本身不能直接等同高景气。｜核心验证：库存周期与价差修复；必选：下游订单、库存、计划新增产能
A3: 指标名称 | B3: 数据来源 | C3: 最新数值 | D3: 单位 | E3: 趋势 | F3: 权重 | G3: 评分 (1-10) | H3: 评分阈值说明 | I3: 历史分位 | J3: 对景气度影响 | K3: 跟踪频率 | L3: 原权重 | M3: 参数优化建议 | N3: 评分口径（更新时采用） | O3: 阶段分项 | P3: 公式分数
A4: 【第一部分：先行指标（Leading Indicators）——提前1-2个季度预示景气变化】 | O4: 先行 | P4: =ROUND(SUMPRODUCT(F5:F8,G5:G8)/SUM(F5:F8),1) -> 8
A5: 1-原油价格变化 | B5: WTI/布伦特 | C5: 72 | D5: 美元/桶 | E5: 下行 | F5: 0.15 | G5: 8 | H5: 60-80=10分,50-60或80-90=8分,40-50或90-100=6分,<40或>100=4分 | I5: 55% | J5: 油价中枢回落，成本压力缓解 | K5: 日度 | L5: 0.15 | M5: 目标组权重 50%；按同组相对重要性归一化。 | N5: 改为5年滚动分位(P20/P40/P60/P80)+3个月动量；须与库存、价差或利润交叉确认。 | O5: 同步 | P5: =ROUND(SUMPRODUCT(F10:F13,G10:G13)/SUM(F10:F13),1) -> 6.8
A6: 2-煤化工原料煤价格 | B6: 秦皇岛动力煤 | C6: 680 | D6: 元/吨 | E6: 下行 | F6: 0.12 | G6: 10 | H6: <700=10分,700-800=8分,800-900=6分,900-1000=4分,>1000=2分 | I6: 30% | J6: 煤价处于低位，煤化工成本优势明显 | K6: 周度 | L6: 0.12 | M6: 目标组权重 50%；按同组相对重要性归一化。 | N6: 改为5年滚动分位(P20/P40/P60/P80)+3个月动量；须与库存、价差或利润交叉确认。 | O6: 滞后 | P6: =ROUND(SUMPRODUCT(F15:F17,G15:G17)/SUM(F15:F17),1) -> 6.6
A7: 3-化工品产能利用率 | B7: 卓创资讯 | C7: 74 | D7: % | E7: 上行 | F7: 0.13 | G7: 6 | H7: >80%=10分,75-80%=8分,70-75%=6分,65-70%=4分,<65%=2分 | I7: 52% | J7: 产能利用率回升，供需格局改善 | K7: 月度 | L7: 0.13 | M7: 目标组权重 50%；按同组相对重要性归一化。 | N7: 采用TTM/滚动4季同比+历史分位；剔除一次性损益，IRR按项目现金流复核。
A8: 4-新增产能投放计划 | B8: 公司公告/行业协会 | C8: +3.5 | D8: % | E8: 放缓 | F8: 0.1 | G8: 8 | H8: <2%=10分,2-5%=8分,5-8%=6分,8-12%=4分,>12%=2分 | I8: 45% | J8: 产能投放放缓，供给压力减轻 | K8: 季度 | L8: 0.1 | M8: 目标组权重 50%；按同组相对重要性归一化。 | N8: 采用5年滚动分位+同比/环比双阈值；数据滞后超过一个频率周期时自动降权。
A9: 【第二部分：同步指标（Coincident Indicators）——与当前景气同步变动】
A10: 5-中国化工产品价格指数(CCPI) | B10: 卓创资讯 | C10: 4850 | D10: 点 | E10: 上行 | F10: 0.1167 | G10: 6 | H10: >5500=10分,5000-5500=8分,4500-5000=6分,4000-4500=4分,<4000=2分 | I10: 48% | J10: 化工品价格温和上涨，价差修复 | K10: 周度 | L10: 0.15 | M10: 目标组权重 35%；按同组相对重要性归一化。 | N10: 改为5年滚动分位(P20/P40/P60/P80)+3个月动量；须与库存、价差或利润交叉确认。
A11: 6-主要化工品价差 | B11: 百川盈孚 | C11: +5 | D11: %vs均值 | E11: 上行 | F11: 0.0933 | G11: 6 | H11: >历史均值20%=10分,0-20%=8分,-10-0%=6分,-20--10%=4分,<-20%=2分 | I11: 55% | J11: 价差改善，企业盈利空间扩大 | K11: 周度 | L11: 0.12 | M11: 目标组权重 35%；按同组相对重要性归一化。 | N11: 改为5年滚动分位(P20/P40/P60/P80)+3个月动量；须与库存、价差或利润交叉确认。
A12: 7-化工品库存天数 | B12: 卓创资讯 | C12: 18 | D12: 天 | E12: 下行 | F12: 0.0778 | G12: 8 | H12: <15天=10分,15-20天=8分,20-25天=6分,25-30天=4分,>30天=2分 | I12: 40% | J12: 库存健康，去库接近尾声 | K12: 月度 | L12: 0.1 | M12: 目标组权重 35%；按同组相对重要性归一化。 | N12: 采用同比、环比、历史分位三维评分；按去库/改善方向计分。
A13: 8-化工品出口增速 | B13: 海关总署 | C13: +12.5 | D13: %YoY | E13: 上行 | F13: 0.0622 | G13: 8 | H13: >15%=10分,5-15%=8分,0-5%=6分,-5-0%=4分,<-5%=2分 | I13: 65% | J13: 出口强劲，外需支撑景气度 | K13: 月度 | L13: 0.08 | M13: 目标组权重 35%；按同组相对重要性归一化。 | N13: 采用5年滚动分位+同比/环比双阈值；数据滞后超过一个频率周期时自动降权。
A14: 【第三部分：滞后指标（Lagging Indicators）——滞后1-2个季度反映景气变化】
A15: 9-化工企业季度ROE | B15: 上市公司财报 | C15: 7.5 | D15: % | E15: 上行 | F15: 0.06 | G15: 6 | H15: >12%=10分,8-12%=8分,4-8%=6分,0-4%=4分,<0%=2分 | I15: 50% | J15: Q1盈利修复，ROE回升 | K15: 季度 | L15: 0.1 | M15: 目标组权重 15%；按同组相对重要性归一化。 | N15: 采用TTM/滚动4季同比+历史分位；剔除一次性损益，IRR按项目现金流复核。
A16: 10-化工行业固定资产投资增速 | B16: 国家统计局 | C16: +8.5 | D16: %YoY | E16: 上行 | F16: 0.048 | G16: 8 | H16: >10%=10分,5-10%=8分,0-5%=6分,-5-0%=4分,<-5%=2分 | I16: 58% | J16: 投资回暖，扩产意愿增强 | K16: 季度 | L16: 0.08 | M16: 目标组权重 15%；按同组相对重要性归一化。 | N16: 采用5年滚动分位+同比/环比双阈值；数据滞后超过一个频率周期时自动降权。
A17: 11-PPI化工原料同比 | B17: 国家统计局 | C17: +2.5 | D17: % | E17: 上行 | F17: 0.042 | G17: 6 | H17: >5%=10分,0-5%=8分,-3-0%=6分,-6--3%=4分,<-6%=2分 | I17: 55% | J17: 价格同比转正，通缩压力缓解 | K17: 月度 | L17: 0.07 | M17: 目标组权重 15%；按同组相对重要性归一化。 | N17: 采用5年滚动分位+同比/环比双阈值；数据滞后超过一个频率周期时自动降权。
A18: 行业综合景气度加权得分 | G18: =ROUND(SUMPRODUCT(F5:F17,G5:G17),1) -> 7.4 | H18: 综合分=Σ(建议权重×单项评分)，建议权重和=100%。

Sheet 钢铁
A1: 行业景气度量化跟踪体系（参数优化版）— 钢铁
A2: 默认阶段框架：强周期/供给出清｜先行/同步/滞后=50%/35%/15%。先用库存、供给、订单确认反转；价格本身不能直接等同高景气。｜核心验证：需求/去库与利润修复；必选：地产施工、基建实物量、库存变化
A3: 指标名称 | B3: 数据来源 | C3: 最新数值 | D3: 单位 | E3: 趋势 | F3: 权重 | G3: 评分 (1-10) | H3: 评分阈值说明 | I3: 历史分位 | J3: 对景气度影响 | K3: 跟踪频率 | L3: 原权重 | M3: 参数优化建议 | N3: 评分口径（更新时采用） | O3: 阶段分项 | P3: 公式分数
A4: 【第一部分：先行指标（Leading Indicators）——提前1-2个季度预示景气变化】 | O4: 先行 | P4: =ROUND(SUMPRODUCT(F5:F8,G5:G8)/SUM(F5:F8),1) -> 8
A5: 1-铁矿石价格变化 | B5: 普氏62%指数 | C5: 105 | D5: 美元/吨 | E5: 下行 | F5: 0.15 | G5: 8 | H5: 80-100=10分,70-80或100-120=8分,60-70或120-140=6分,<60或>140=4分 | I5: 62% | J5: 矿价回落，成本压力减轻 | K5: 日度 | L5: 0.15 | M5: 目标组权重 50%；按同组相对重要性归一化。 | N5: 改为5年滚动分位(P20/P40/P60/P80)+3个月动量；须与库存、价差或利润交叉确认。 | O5: 同步 | P5: =ROUND(SUMPRODUCT(F10:F13,G10:G13)/SUM(F10:F13),1) -> 6
A6: 2-焦煤价格变化 | B6: CCI指数 | C6: 1650 | D6: 元/吨 | E6: 下行 | F6: 0.12 | G6: 8 | H6: <1500=10分,1500-1800=8分,1800-2200=6分,2200-2600=4分,>2600=2分 | I6: 45% | J6: 焦煤价格回落，焦炭成本下降 | K6: 周度 | L6: 0.12 | M6: 目标组权重 50%；按同组相对重要性归一化。 | N6: 改为5年滚动分位(P20/P40/P60/P80)+3个月动量；须与库存、价差或利润交叉确认。 | O6: 滞后 | P6: =ROUND(SUMPRODUCT(F15:F17,G15:G17)/SUM(F15:F17),1) -> 6
A7: 3-高炉开工率 | B7: Mysteel | C7: 82 | D7: % | E7: 上行 | F7: 0.13 | G7: 8 | H7: >85%=10分,80-85%=8分,75-80%=6分,70-75%=4分,<70%=2分 | I7: 58% | J7: 开工率回升，生产积极性改善 | K7: 周度 | L7: 0.13 | M7: 目标组权重 50%；按同组相对重要性归一化。 | N7: 采用5年滚动分位+同比/环比双阈值；数据滞后超过一个频率周期时自动降权。
A8: 4-钢材社会库存变化 | B8: Mysteel | C8: -4.2 | D8: %MoM | E8: 去库 | F8: 0.1 | G8: 8 | H8: <-5%=10分,-5-0%=8分,0-5%=6分,5-10%=4分,>10%=2分 | I8: 38% | J8: 库存去化顺利，供需格局改善 | K8: 周度 | L8: 0.1 | M8: 目标组权重 50%；按同组相对重要性归一化。 | N8: 采用同比、环比、历史分位三维评分；按去库/改善方向计分。
A9: 【第二部分：同步指标（Coincident Indicators）——与当前景气同步变动】
A10: 5-螺纹钢现货价格 | B10: 上海钢联 | C10: 3450 | D10: 元/吨 | E10: 上行 | F10: 0.1167 | G10: 6 | H10: >4000=10分,3500-4000=8分,3000-3500=6分,2500-3000=4分,<2500=2分 | I10: 48% | J10: 钢价温和回升，盈利边际改善 | K10: 日度 | L10: 0.15 | M10: 目标组权重 35%；按同组相对重要性归一化。 | N10: 改为5年滚动分位(P20/P40/P60/P80)+3个月动量；须与库存、价差或利润交叉确认。
A11: 6-热轧板卷价格 | B11: 上海钢联 | C11: 3650 | D11: 元/吨 | E11: 上行 | F11: 0.0778 | G11: 6 | H11: >4200=10分,3800-4200=8分,3400-3800=6分,3000-3400=4分,<3000=2分 | I11: 45% | J11: 板材价格回升，制造业需求支撑 | K11: 日度 | L11: 0.1 | M11: 目标组权重 35%；按同组相对重要性归一化。 | N11: 改为5年滚动分位(P20/P40/P60/P80)+3个月动量；须与库存、价差或利润交叉确认。
A12: 7-钢厂盈利面 | B12: Mysteel | C12: 55 | D12: % | E12: 上行 | F12: 0.0933 | G12: 6 | H12: >70%=10分,50-70%=8分,30-50%=6分,10-30%=4分,<10%=2分 | I12: 48% | J12: 盈利面扩大，过半钢厂实现盈利 | K12: 周度 | L12: 0.12 | M12: 目标组权重 35%；按同组相对重要性归一化。 | N12: 采用5年滚动分位+同比/环比双阈值；数据滞后超过一个频率周期时自动降权。
A13: 8-钢材表观消费量 | B13: 国家统计局 | C13: 1.05 | D13: 亿吨/年化 | E13: 上行 | F13: 0.0622 | G13: 6 | H13: >1.1亿年化=10分,1.0-1.1亿=8分,0.9-1.0亿=6分,0.8-0.9亿=4分,<0.8亿=2分 | I13: 52% | J13: 表观消费回升，需求端改善 | K13: 月度 | L13: 0.08 | M13: 目标组权重 35%；按同组相对重要性归一化。 | N13: 采用季调同比+3个月环比；单月值用3个月移动均值过滤。
A14: 【第三部分：滞后指标（Lagging Indicators）——滞后1-2个季度反映景气变化】
A15: 9-钢铁企业季度净利润 | B15: 上市公司财报 | C15: 35 | D15: 亿元 | E15: 上行 | F15: 0.06 | G15: 6 | H15: >50亿=10分,20-50亿=8分,0-20亿=6分,-20-0亿=4分,<-20亿=2分 | I15: 45% | J15: Q1扭亏为盈，利润端改善 | K15: 季度 | L15: 0.1 | M15: 目标组权重 15%；按同组相对重要性归一化。 | N15: 采用TTM/滚动4季同比+历史分位；剔除一次性损益，IRR按项目现金流复核。
A16: 10-钢铁行业产能利用率 | B16: 国家统计局 | C16: 77 | D16: % | E16: 上行 | F16: 0.048 | G16: 6 | H16: >80%=10分,75-80%=8分,70-75%=6分,65-70%=4分,<65%=2分 | I16: 52% | J16: 产能利用率回升，供需趋于平衡 | K16: 季度 | L16: 0.08 | M16: 目标组权重 15%；按同组相对重要性归一化。 | N16: 采用TTM/滚动4季同比+历史分位；剔除一次性损益，IRR按项目现金流复核。
A17: 11-PPI黑色金属冶炼同比 | B17: 国家统计局 | C17: +1.8 | D17: % | E17: 上行 | F17: 0.042 | G17: 6 | H17: >5%=10分,0-5%=8分,-5-0%=6分,-10--5%=4分,<-10%=2分 | I17: 48% | J17: 价格同比转正，通缩压力缓解 | K17: 月度 | L17: 0.07 | M17: 目标组权重 15%；按同组相对重要性归一化。 | N17: 采用5年滚动分位+同比/环比双阈值；数据滞后超过一个频率周期时自动降权。
A18: 行业综合景气度加权得分 | G18: =ROUND(SUMPRODUCT(F5:F17,G5:G17),1) -> 7 | H18: 综合分=Σ(建议权重×单项评分)，建议权重和=100%。

Sheet 有色金属
A1: 行业景气度量化跟踪体系（参数优化版）— 有色金属
A2: 默认阶段框架：资源品/宏观供需｜先行/同步/滞后=45%/40%/15%。库存、加工费、美元和价格共同确认。｜核心验证：库存、供给约束与需求弹性；必选：库存、TC/RC、美元、矿端扰动
A3: 指标名称 | B3: 数据来源 | C3: 最新数值 | D3: 单位 | E3: 趋势 | F3: 权重 | G3: 评分 (1-10) | H3: 评分阈值说明 | I3: 历史分位 | J3: 对景气度影响 | K3: 跟踪频率 | L3: 原权重 | M3: 参数优化建议 | N3: 评分口径（更新时采用） | O3: 阶段分项 | P3: 公式分数
A4: 【第一部分：先行指标（Leading Indicators）——提前1-2个季度预示景气变化】 | O4: 先行 | P4: =ROUND(SUMPRODUCT(F5:F8,G5:G8)/SUM(F5:F8),1) -> 6.9
A5: 1-LME铜库存变化 | B5: LME | C5: -12 | D5: %YoY | E5: 去库 | F5: 0.15 | G5: 8 | H5: <-10%=10分,-10-0%=8分,0-10%=6分,10-20%=4分,>20%=2分 | I5: 35% | J5: 全球库存去化，供给偏紧 | K5: 周度 | L5: 0.15 | M5: 目标组权重 45%；按同组相对重要性归一化。 | N5: 采用同比、环比、历史分位三维评分；按去库/改善方向计分。 | O5: 同步 | P5: =ROUND(SUMPRODUCT(F10:F13,G10:G13)/SUM(F10:F13),1) -> 8.7
A6: 2-铜精矿TC/RC | B6: SMM | C6: 25 | D6: 美元/吨 | E6: 下行 | F6: 0.12 | G6: 4 | H6: >80=10分,60-80=8分,40-60=6分,20-40=4分,<20=2分 | I6: 15% | J6: 加工费极低，铜矿供给紧张 | K6: 月度 | L6: 0.12 | M6: 目标组权重 45%；按同组相对重要性归一化。 | N6: 改为5年滚动分位(P20/P40/P60/P80)+3个月动量；须与库存、价差或利润交叉确认。 | O6: 滞后 | P6: =ROUND(SUMPRODUCT(F15:F17,G15:G17)/SUM(F15:F17),1) -> 8.6
A7: 3-美元指数 | B7: 美联储 | C7: 99.5 | D7: 点 | E7: 下行 | F7: 0.1 | G7: 8 | H7: <100=10分,100-103=8分,103-106=6分,106-110=4分,>110=2分 | I7: 35% | J7: 美元走弱，利好大宗商品定价 | K7: 日度 | L7: 0.1 | M7: 目标组权重 45%；按同组相对重要性归一化。 | N7: 采用5年滚动分位+同比/环比双阈值；数据滞后超过一个频率周期时自动降权。
A8: 4-全球矿山资本开支增速 | B8: Wood Mackenzie | C8: +18 | D8: %YoY | E8: 上行 | F8: 0.08 | G8: 8 | H8: >15%=10分,5-15%=8分,0-5%=6分,-5-0%=4分,<-5%=2分 | I8: 65% | J8: 资本开支增加，远期供给有望改善 | K8: 年度 | L8: 0.08 | M8: 目标组权重 45%；按同组相对重要性归一化。 | N8: 采用5年滚动分位+同比/环比双阈值；数据滞后超过一个频率周期时自动降权。
A9: 【第二部分：同步指标（Coincident Indicators）——与当前景气同步变动】
A10: 5-LME铜现货价格 | B10: LME | C10: 9800 | D10: 美元/吨 | E10: 上行 | F10: 0.1395 | G10: 10 | H10: >9500=10分,8500-9500=8分,7500-8500=6分,6500-7500=4分,<6500=2分 | I10: 85% | J10: 铜价处于历史高位，新能源+AI需求强劲 | K10: 日度 | L10: 0.15 | M10: 目标组权重 40%；按同组相对重要性归一化。 | N10: 改为5年滚动分位(P20/P40/P60/P80)+3个月动量；须与库存、价差或利润交叉确认。
A11: 6-铝现货价格 | B11: SMM | C11: 20500 | D11: 元/吨 | E11: 上行 | F11: 0.093 | G11: 10 | H11: >20000=10分,18000-20000=8分,16000-18000=6分,14000-16000=4分,<14000=2分 | I11: 78% | J11: 铝价高位运行，氧化铝成本支撑 | K11: 日度 | L11: 0.1 | M11: 目标组权重 40%；按同组相对重要性归一化。 | N11: 改为5年滚动分位(P20/P40/P60/P80)+3个月动量；须与库存、价差或利润交叉确认。
A12: 7-有色金属冶炼加工费 | B12: SMM | C12: +8 | D12: %vs均值 | E12: 上行 | F12: 0.093 | G12: 6 | H12: >均值20%=10分,0-20%=8分,-10-0%=6分,-20--10%=4分,<-20%=2分 | I12: 55% | J12: 加工费改善，冶炼端利润修复 | K12: 月度 | L12: 0.1 | M12: 目标组权重 40%；按同组相对重要性归一化。 | N12: 采用5年滚动分位+同比/环比双阈值；数据滞后超过一个频率周期时自动降权。
A13: 8-中国有色金属消费量 | B13: 中国有色金属工业协会 | C13: +7.5 | D13: %YoY | E13: 上行 | F13: 0.0744 | G13: 8 | H13: >8%=10分,5-8%=8分,2-5%=6分,0-2%=4分,<0%=2分 | I13: 62% | J13: 消费量稳健增长，新能源需求拉动 | K13: 月度 | L13: 0.08 | M13: 目标组权重 40%；按同组相对重要性归一化。 | N13: 采用季调同比+3个月环比；单月值用3个月移动均值过滤。
A14: 【第三部分：滞后指标（Lagging Indicators）——滞后1-2个季度反映景气变化】
A15: 9-有色企业季度净利润 | B15: 上市公司财报 | C15: 180 | D15: 亿元 | E15: 上行 | F15: 0.06 | G15: 8 | H15: >100亿=10分,50-100亿=8分,10-50亿=6分,0-10亿=4分,<0亿=2分 | I15: 72% | J15: Q1业绩爆发，小金属板块净利增93% | K15: 季度 | L15: 0.1 | M15: 目标组权重 15%；按同组相对重要性归一化。 | N15: 采用TTM/滚动4季同比+历史分位；剔除一次性损益，IRR按项目现金流复核。
A16: 10-有色金属库存周转天数 | B16: 上市公司财报 | C16: 38 | D16: 天 | E16: 下行 | F16: 0.048 | G16: 8 | H16: <30天=10分,30-45天=8分,45-60天=6分,60-75天=4分,>75天=2分 | I16: 42% | J16: 库存周转加快，运营效率提升 | K16: 季度 | L16: 0.08 | M16: 目标组权重 15%；按同组相对重要性归一化。 | N16: 采用同比、环比、历史分位三维评分；按去库/改善方向计分。
A17: 11-PPI有色金属冶炼同比 | B17: 国家统计局 | C17: +12.5 | D17: % | E17: 上行 | F17: 0.042 | G17: 10 | H17: >10%=10分,5-10%=8分,0-5%=6分,-5-0%=4分,<-5%=2分 | I17: 75% | J17: 价格同比大涨，行业景气度高企 | K17: 月度 | L17: 0.07 | M17: 目标组权重 15%；按同组相对重要性归一化。 | N17: 采用5年滚动分位+同比/环比双阈值；数据滞后超过一个频率周期时自动降权。
A18: 行业综合景气度加权得分 | G18: =ROUND(SUMPRODUCT(F5:F17,G5:G17),1) -> 7.9 | H18: 综合分=Σ(建议权重×单项评分)，建议权重和=100%。

Sheet 电子
A1: 行业景气度量化跟踪体系（参数优化版）— 电子
A2: 默认阶段框架：科技制造/订单库存周期｜先行/同步/滞后=50%/35%/15%。订单、库存和利用率优先；不同子行业拆分后再汇总。｜核心验证：库存去化与需求/产能利用率；必选：订单、库存周转、存储价格、终端出货
A3: 指标名称 | B3: 数据来源 | C3: 最新数值 | D3: 单位 | E3: 趋势 | F3: 权重 | G3: 评分 (1-10) | H3: 评分阈值说明 | I3: 历史分位 | J3: 对景气度影响 | K3: 跟踪频率 | L3: 原权重 | M3: 参数优化建议 | N3: 评分口径（更新时采用） | O3: 阶段分项 | P3: 公式分数
A4: 【第一部分：先行指标（Leading Indicators）——提前1-2个季度预示景气变化】 | O4: 先行 | P4: =ROUND(SUMPRODUCT(F5:F9,G5:G9)/SUM(F5:F9),1) -> 8.2
A5: 1-全球半导体销售额增速 | B5: SIA/WSTS | C5: +18.5 | D5: %YoY | E5: 上行 | F5: 0.1364 | G5: 8 | H5: >20%=10分,10-20%=8分,5-10%=6分,0-5%=4分,<0%=2分 | I5: 75% | J5: 半导体周期强劲复苏，AI需求驱动 | K5: 月度 | L5: 0.15 | M5: 目标组权重 50%；按同组相对重要性归一化。 | N5: 采用5年滚动分位+同比/环比双阈值；数据滞后超过一个频率周期时自动降权。 | O5: 同步 | P5: =ROUND(SUMPRODUCT(F11:F14,G11:G14)/SUM(F11:F14),1) -> 7.2
A6: 2-存储芯片价格变化 | B6: DRAMeXchange | C6: +22 | D6: %MoM | E6: 大涨 | F6: 0.1091 | G6: 9 | H6: 涨价>10%=10分,涨价5-10%=8分,持平=5分,跌价5-10%=3分,跌价>10%=1分 | I6: 82% | J6: 存储超级周期，HBM需求爆发 | K6: 周度 | L6: 0.12 | M6: 目标组权重 50%；按同组相对重要性归一化。 | N6: 改为5年滚动分位(P20/P40/P60/P80)+3个月动量；须与库存、价差或利润交叉确认。 | O6: 滞后 | P6: =ROUND(SUMPRODUCT(F16:F18,G16:G18)/SUM(F16:F18),1) -> 8
A7: 3-硅片出货量增速 | B7: SEMI | C7: +15.2 | D7: %YoY | E7: 上行 | F7: 0.0909 | G7: 7 | H7: >30%=10分,20-30%=8分,10-20%=6分,0-10%=4分,<0%=2分 | I7: 68% | J7: 硅片需求回暖，晶圆厂扩产 | K7: 季度 | L7: 0.1 | M7: 目标组权重 50%；按同组相对重要性归一化。 | N7: 采用季调同比+3个月环比；单月值用3个月移动均值过滤。
A8: 4-设备商订单增速 | B8: 应用材料/ASML财报 | C8: +28 | D8: %YoY | E8: 上行 | F8: 0.0909 | G8: 8 | H8: >40%=10分,20-40%=8分,10-20%=6分,0-10%=4分,<0%=2分 | I8: 72% | J8: 设备订单高增，扩产周期确认 | K8: 季度 | L8: 0.1 | M8: 目标组权重 50%；按同组相对重要性归一化。 | N8: 滚动3M/4Q同比；以交付、收入或现金流确认，政策/规划单项权重≤8%。
A9: 5-下游客户库存周转天数 | B9: 下游公司财报 | C9: 58 | D9: 天 | E9: 去库完成 | F9: 0.0727 | G9: 9 | H9: 去库完成<60天=10分,去库中60-80天=7分,高位80-100天=4分,补库初期100-120天=6分,补库后期>120天=3分 | I9: 35% | J9: 库存去化完成，补库周期即将启动 | K9: 季度 | L9: 0.08 | M9: 目标组权重 50%；按同组相对重要性归一化。 | N9: 采用同比、环比、历史分位三维评分；按去库/改善方向计分。
A10: 【第二部分：同步指标（Coincident Indicators）——与当前景气同步变动】
A11: 6-晶圆厂产能利用率 | B11: 台积电/中芯国际 | C11: 88 | D11: % | E11: 上行 | F11: 0.1105 | G11: 8 | H11: >90%=10分,80-90%=8分,70-80%=6分,60-70%=4分,<60%=2分 | I11: 72% | J11: 产能利用率高位，供需偏紧 | K11: 月度 | L11: 0.12 | M11: 目标组权重 35%；按同组相对重要性归一化。 | N11: 采用TTM/滚动4季同比+历史分位；剔除一次性损益，IRR按项目现金流复核。
A12: 7-智能手机出货量增速 | B12: IDC/Counterpoint | C12: +8.5 | D12: %YoY | E12: 上行 | F12: 0.0921 | G12: 8 | H12: >10%=10分,5-10%=8分,0-5%=6分,-5-0%=4分,<-5%=2分 | I12: 60% | J12: 手机出货回暖，AI手机换机潮 | K12: 季度 | L12: 0.1 | M12: 目标组权重 35%；按同组相对重要性归一化。 | N12: 采用季调同比+3个月环比；单月值用3个月移动均值过滤。
A13: 8-PC出货量增速 | B13: IDC/Gartner | C13: +3.2 | D13: %YoY | E13: 上行 | F13: 0.0737 | G13: 6 | H13: >5%=10分,0-5%=8分,-5-0%=6分,-10--5%=4分,<-10%=2分 | I13: 55% | J13: PC出货温和复苏，AI PC渗透 | K13: 季度 | L13: 0.08 | M13: 目标组权重 35%；按同组相对重要性归一化。 | N13: 采用季调同比+3个月环比；单月值用3个月移动均值过滤。
A14: 9-MLCC出货量 | B14: 村田/TDK | C14: 480 | D14: 亿颗/月 | E14: 上行 | F14: 0.0737 | G14: 6 | H14: >500=10分,450-500=8分,400-450=6分,350-400=4分,<350=2分 | I14: 58% | J14: 被动元件出货回升，消费电子复苏 | K14: 月度 | L14: 0.08 | M14: 目标组权重 35%；按同组相对重要性归一化。 | N14: 采用季调同比+3个月环比；单月值用3个月移动均值过滤。
A15: 【第三部分：滞后指标（Lagging Indicators）——滞后1-2个季度反映景气变化】
A16: 10-电子企业季度毛利率 | B16: 上市公司财报 | C16: 28 | D16: % | E16: 上行 | F16: 0.0625 | G16: 8 | H16: >30%=10分,25-30%=8分,20-25%=6分,15-20%=4分,<15%=2分 | I16: 62% | J16: Q1毛利率改善，产品结构优化 | K16: 季度 | L16: 0.1 | M16: 目标组权重 15%；按同组相对重要性归一化。 | N16: 改为5年滚动分位(P20/P40/P60/P80)+3个月动量；须与库存、价差或利润交叉确认。
A17: 11-电子行业固定资产投资增速 | B17: 国家统计局 | C17: +12 | D17: %YoY | E17: 上行 | F17: 0.0437 | G17: 8 | H17: >15%=10分,5-15%=8分,0-5%=6分,-5-0%=4分,<-5%=2分 | I17: 65% | J17: 投资高增，产能扩张积极 | K17: 季度 | L17: 0.07 | M17: 目标组权重 15%；按同组相对重要性归一化。 | N17: 采用5年滚动分位+同比/环比双阈值；数据滞后超过一个频率周期时自动降权。
A18: 12-电子元器件进口金额增速 | B18: 海关总署 | C18: +15 | D18: %YoY | E18: 上行 | F18: 0.0437 | G18: 8 | H18: >10%=10分,5-10%=8分,0-5%=6分,-5-0%=4分,<-5%=2分 | I18: 68% | J18: 进口高增，国内需求旺盛 | K18: 月度 | L18: 0.07 | M18: 目标组权重 15%；按同组相对重要性归一化。 | N18: 采用5年滚动分位+同比/环比双阈值；数据滞后超过一个频率周期时自动降权。
A19: 行业综合景气度加权得分 | G19: =ROUND(SUMPRODUCT(F5:F18,G5:G18),1) -> 7.8 | H19: 综合分=Σ(建议权重×单项评分)，建议权重和=100%。

Sheet 家用电器
A1: 行业景气度量化跟踪体系（参数优化版）— 家用电器
A2: 默认阶段框架：消费/需求恢复｜先行/同步/滞后=40%/40%/20%。高频需求、渠道库存和价格/利润交叉确认，使用季调数据。｜核心验证：更新需求、出口和产品结构；必选：地产竣工、海外订单、排产
A3: 指标名称 | B3: 数据来源 | C3: 最新数值 | D3: 单位 | E3: 趋势 | F3: 权重 | G3: 评分 (1-10) | H3: 评分阈值说明 | I3: 历史分位 | J3: 对景气度影响 | K3: 跟踪频率 | L3: 原权重 | M3: 参数优化建议 | N3: 评分口径（更新时采用） | O3: 阶段分项 | P3: 公式分数
A4: 【第一部分：先行指标（Leading Indicators）——提前1-2个季度预示景气变化】 | O4: 先行 | P4: =ROUND(SUMPRODUCT(F5:F8,G5:G8)/SUM(F5:F8),1) -> 5.3
A5: 1-房地产竣工面积增速 | B5: 国家统计局 | C5: -8.5 | D5: %YoY | E5: 下行 | F5: 0.1277 | G5: 4 | H5: >10%=10分,5-10%=8分,0-5%=6分,-5-0%=4分,<-5%=2分 | I5: 25% | J5: 竣工下滑，后周期需求承压 | K5: 月度 | L5: 0.15 | M5: 目标组权重 40%；按同组相对重要性归一化。 | N5: 采用5年滚动分位+同比/环比双阈值；数据滞后超过一个频率周期时自动降权。 | O5: 同步 | P5: =ROUND(SUMPRODUCT(F10:F13,G10:G13)/SUM(F10:F13),1) -> 7.2
A6: 2-商品房销售面积增速 | B6: 国家统计局 | C6: -5.2 | D6: %YoY | E6: 下行 | F6: 0.1021 | G6: 4 | H6: >5%=10分,0-5%=8分,-5-0%=6分,-10--5%=4分,<-10%=2分 | I6: 30% | J6: 销售低迷，新增需求不足 | K6: 月度 | L6: 0.12 | M6: 目标组权重 40%；按同组相对重要性归一化。 | N6: 采用5年滚动分位+同比/环比双阈值；数据滞后超过一个频率周期时自动降权。 | O6: 滞后 | P6: =ROUND(SUMPRODUCT(F15:F17,G15:G17)/SUM(F15:F17),1) -> 7.4
A7: 3-铜/钢等原材料价格 | B7: LME/上海期货 | C7: -2.5 | D7: %YoY | E7: 下行 | F7: 0.0851 | G7: 8 | H7: <-5%=10分,-5-0%=8分,0-5%=6分,5-10%=4分,>10%=2分 | I7: 45% | J7: 原材料成本下降，利润端改善 | K7: 日度 | L7: 0.1 | M7: 目标组权重 40%；按同组相对重要性归一化。 | N7: 改为5年滚动分位(P20/P40/P60/P80)+3个月动量；须与库存、价差或利润交叉确认。
A8: 4-家电企业排产计划 | B8: 产业在线 | C8: +8 | D8: %YoY | E8: 上行 | F8: 0.0851 | G8: 6 | H8: >15%=10分,5-15%=8分,0-5%=6分,-5-0%=4分,<-5%=2分 | I8: 55% | J8: 排产温和增长，出口订单支撑 | K8: 月度 | L8: 0.1 | M8: 目标组权重 40%；按同组相对重要性归一化。 | N8: 采用5年滚动分位+同比/环比双阈值；数据滞后超过一个频率周期时自动降权。
A9: 【第二部分：同步指标（Coincident Indicators）——与当前景气同步变动】
A10: 5-空调销量增速 | B10: 产业在线 | C10: +12 | D10: %YoY | E10: 上行 | F10: 0.1395 | G10: 8 | H10: >15%=10分,5-15%=8分,0-5%=6分,-5-0%=4分,<-5%=2分 | I10: 62% | J10: 空调销售旺季，出口强劲 | K10: 月度 | L10: 0.15 | M10: 目标组权重 40%；按同组相对重要性归一化。 | N10: 采用季调同比+3个月环比；单月值用3个月移动均值过滤。
A11: 6-冰箱销量增速 | B11: 产业在线 | C11: +6.5 | D11: %YoY | E11: 上行 | F11: 0.093 | G11: 6 | H11: >10%=10分,5-10%=8分,0-5%=6分,-5-0%=4分,<-5%=2分 | I11: 55% | J11: 冰箱销售平稳，更新需求为主 | K11: 月度 | L11: 0.1 | M11: 目标组权重 40%；按同组相对重要性归一化。 | N11: 采用季调同比+3个月环比；单月值用3个月移动均值过滤。
A12: 7-洗衣机销量增速 | B12: 产业在线 | C12: +4.2 | D12: %YoY | E12: 上行 | F12: 0.0744 | G12: 6 | H12: >10%=10分,5-10%=8分,0-5%=6分,-5-0%=4分,<-5%=2分 | I12: 52% | J12: 洗衣机销售温和增长 | K12: 月度 | L12: 0.08 | M12: 目标组权重 40%；按同组相对重要性归一化。 | N12: 采用季调同比+3个月环比；单月值用3个月移动均值过滤。
A13: 8-家电出口金额增速 | B13: 海关总署 | C13: +18.5 | D13: %YoY | E13: 上行 | F13: 0.093 | G13: 8 | H13: >15%=10分,5-15%=8分,0-5%=6分,-5-0%=4分,<-5%=2分 | I13: 70% | J13: 出口高增，海外需求旺盛 | K13: 月度 | L13: 0.1 | M13: 目标组权重 40%；按同组相对重要性归一化。 | N13: 采用5年滚动分位+同比/环比双阈值；数据滞后超过一个频率周期时自动降权。
A14: 【第三部分：滞后指标（Lagging Indicators）——滞后1-2个季度反映景气变化】
A15: 9-家电企业季度净利润率 | B15: 上市公司财报 | C15: 8.5 | D15: % | E15: 上行 | F15: 0.08 | G15: 8 | H15: >10%=10分,7-10%=8分,4-7%=6分,1-4%=4分,<1%=2分 | I15: 60% | J15: Q1净利率改善，成本红利释放 | K15: 季度 | L15: 0.1 | M15: 目标组权重 20%；按同组相对重要性归一化。 | N15: 采用TTM/滚动4季同比+历史分位；剔除一次性损益，IRR按项目现金流复核。
A16: 10-家电行业库存周转天数 | B16: 上市公司财报 | C16: 42 | D16: 天 | E16: 下行 | F16: 0.064 | G16: 8 | H16: <40天=10分,40-50天=8分,50-60天=6分,60-70天=4分,>70天=2分 | I16: 45% | J16: 库存周转加快，运营效率提升 | K16: 季度 | L16: 0.08 | M16: 目标组权重 20%；按同组相对重要性归一化。 | N16: 采用同比、环比、历史分位三维评分；按去库/改善方向计分。
A17: 11-家电零售均价变化 | B17: 奥维云网 | C17: +2.5 | D17: %YoY | E17: 上行 | F17: 0.056 | G17: 6 | H17: >5%=10分,0-5%=8分,-3-0%=6分,-6--3%=4分,<-6%=2分 | I17: 55% | J17: 均价温和上涨，产品结构升级 | K17: 月度 | L17: 0.07 | M17: 目标组权重 20%；按同组相对重要性归一化。 | N17: 改为5年滚动分位(P20/P40/P60/P80)+3个月动量；须与库存、价差或利润交叉确认。
A18: 行业综合景气度加权得分 | G18: =ROUND(SUMPRODUCT(F5:F17,G5:G17),1) -> 6.5 | H18: 综合分=Σ(建议权重×单项评分)，建议权重和=100%。

Sheet 食品饮料
A1: 行业景气度量化跟踪体系（参数优化版）— 食品饮料
A2: 默认阶段框架：防御/成熟｜先行/同步/滞后=30%/45%/25%。同步经营和现金流优先；先行指标只作边际变化确认。｜核心验证：动销、渠道与价格带；必选：经销商库存、终端动销、批价
A3: 指标名称 | B3: 数据来源 | C3: 最新数值 | D3: 单位 | E3: 趋势 | F3: 权重 | G3: 评分 (1-10) | H3: 评分阈值说明 | I3: 历史分位 | J3: 对景气度影响 | K3: 跟踪频率 | L3: 原权重 | M3: 参数优化建议 | N3: 评分口径（更新时采用） | O3: 阶段分项 | P3: 公式分数
A4: 【第一部分：先行指标（Leading Indicators）——提前1-2个季度预示景气变化】 | O4: 先行 | P4: =ROUND(SUMPRODUCT(F5:F8,G5:G8)/SUM(F5:F8),1) -> 5.9
A5: 1-粮食价格变化 | B5: 农业农村部 | C5: +2.8 | D5: %YoY | E5: 上行 | F5: 0.08 | G5: 6 | H5: <3%=10分,3-5%=8分,5-8%=6分,8-10%=4分,>10%=2分 | I5: 55% | J5: 粮价温和上涨，成本端可控 | K5: 月度 | L5: 0.12 | M5: 目标组权重 30%；按同组相对重要性归一化。 | N5: 改为5年滚动分位(P20/P40/P60/P80)+3个月动量；须与库存、价差或利润交叉确认。 | O5: 同步 | P5: =ROUND(SUMPRODUCT(F10:F13,G10:G13)/SUM(F10:F13),1) -> 6.8
A6: 2-包材价格变化 | B6: 生意社 | C6: -4.5 | D6: %YoY | E6: 下行 | F6: 0.0667 | G6: 8 | H6: <-5%=10分,-5-0%=8分,0-5%=6分,5-10%=4分,>10%=2分 | I6: 38% | J6: 包材成本下降，利润端改善 | K6: 月度 | L6: 0.1 | M6: 目标组权重 30%；按同组相对重要性归一化。 | N6: 改为5年滚动分位(P20/P40/P60/P80)+3个月动量；须与库存、价差或利润交叉确认。 | O6: 滞后 | P6: =ROUND(SUMPRODUCT(F15:F17,G15:G17)/SUM(F15:F17),1) -> 7.4
A7: 3-消费者信心指数 | B7: 国家统计局 | C7: 88 | D7: 点 | E7: 下行 | F7: 0.0867 | G7: 4 | H7: >120=10分,110-120=8分,100-110=6分,90-100=4分,<90=2分 | I7: 25% | J7: 信心指数低迷，消费意愿偏弱 | K7: 月度 | L7: 0.13 | M7: 目标组权重 30%；按同组相对重要性归一化。 | N7: 采用5年滚动分位+同比/环比双阈值；数据滞后超过一个频率周期时自动降权。
A8: 4-社会消费品零售总额增速 | B8: 国家统计局 | C8: +5.2 | D8: %YoY | E8: 上行 | F8: 0.0667 | G8: 6 | H8: >8%=10分,5-8%=8分,3-5%=6分,0-3%=4分,<0%=2分 | I8: 48% | J8: 社零温和增长，消费复苏缓慢 | K8: 月度 | L8: 0.1 | M8: 目标组权重 30%；按同组相对重要性归一化。 | N8: 采用季调同比+3个月环比；单月值用3个月移动均值过滤。
A9: 【第二部分：同步指标（Coincident Indicators）——与当前景气同步变动】
A10: 5-白酒批价 | B10: 今日酒价 | C10: 2650 | D10: 元/瓶 | E10: 下行 | F10: 0.1776 | G10: 8 | H10: >2800=10分,2500-2800=8分,2200-2500=6分,2000-2200=4分,<2000=2分 | I10: 65% | J10: 茅台批价坚挺，高端酒需求稳定 | K10: 周度 | L10: 0.15 | M10: 目标组权重 45%；按同组相对重要性归一化。 | N10: 改为5年滚动分位(P20/P40/P60/P80)+3个月动量；须与库存、价差或利润交叉确认。
A11: 6-乳制品产量增速 | B11: 国家统计局 | C11: +3.5 | D11: %YoY | E11: 上行 | F11: 0.0947 | G11: 6 | H11: >5%=10分,2-5%=8分,0-2%=6分,-3-0%=4分,<-3%=2分 | I11: 52% | J11: 乳制品产量温和增长 | K11: 月度 | L11: 0.08 | M11: 目标组权重 45%；按同组相对重要性归一化。 | N11: 采用季调同比+3个月环比；单月值用3个月移动均值过滤。
A12: 7-啤酒产量增速 | B12: 国家统计局 | C12: +1.8 | D12: %YoY | E12: 上行 | F12: 0.0947 | G12: 6 | H12: >5%=10分,2-5%=8分,0-2%=6分,-3-0%=4分,<-3%=2分 | I12: 48% | J12: 啤酒产量平稳，旺季来临 | K12: 月度 | L12: 0.08 | M12: 目标组权重 45%；按同组相对重要性归一化。 | N12: 采用季调同比+3个月环比；单月值用3个月移动均值过滤。
A13: 8-调味品产量增速 | B13: 中国调味品协会 | C13: +2.5 | D13: %YoY | E13: 上行 | F13: 0.0829 | G13: 6 | H13: >5%=10分,2-5%=8分,0-2%=6分,-3-0%=4分,<-3%=2分 | I13: 50% | J13: 调味品产量温和增长 | K13: 月度 | L13: 0.07 | M13: 目标组权重 45%；按同组相对重要性归一化。 | N13: 采用季调同比+3个月环比；单月值用3个月移动均值过滤。
A14: 【第三部分：滞后指标（Lagging Indicators）——滞后1-2个季度反映景气变化】
A15: 9-食品饮料企业季度ROE | B15: 上市公司财报 | C15: 16 | D15: % | E15: 上行 | F15: 0.1 | G15: 8 | H15: >20%=10分,15-20%=8分,10-15%=6分,5-10%=4分,<5%=2分 | I15: 65% | J15: Q1 ROE稳健，盈利能力维持高位 | K15: 季度 | L15: 0.1 | M15: 目标组权重 25%；按同组相对重要性归一化。 | N15: 采用TTM/滚动4季同比+历史分位；剔除一次性损益，IRR按项目现金流复核。
A16: 10-食品饮料行业毛利率 | B16: 上市公司财报 | C16: 48 | D16: % | E16: 上行 | F16: 0.08 | G16: 8 | H16: >50%=10分,40-50%=8分,30-40%=6分,20-30%=4分,<20%=2分 | I16: 62% | J16: 毛利率改善，成本红利释放 | K16: 季度 | L16: 0.08 | M16: 目标组权重 25%；按同组相对重要性归一化。 | N16: 改为5年滚动分位(P20/P40/P60/P80)+3个月动量；须与库存、价差或利润交叉确认。
A17: 11-CPI非食品项同比 | B17: 国家统计局 | C17: +0.8 | D17: % | E17: 上行 | F17: 0.07 | G17: 6 | H17: >2%=10分,1-2%=8分,0-1%=6分,-1-0%=4分,<-1%=2分 | I17: 42% | J17: 非食品通胀温和，终端价格稳定 | K17: 月度 | L17: 0.07 | M17: 目标组权重 25%；按同组相对重要性归一化。 | N17: 采用5年滚动分位+同比/环比双阈值；数据滞后超过一个频率周期时自动降权。
A18: 行业综合景气度加权得分 | G18: =ROUND(SUMPRODUCT(F5:F17,G5:G17),1) -> 6.7 | H18: 综合分=Σ(建议权重×单项评分)，建议权重和=100%。

Sheet 纺织服饰
A1: 行业景气度量化跟踪体系（参数优化版）— 纺织服饰
A2: 默认阶段框架：消费/需求恢复｜先行/同步/滞后=40%/40%/20%。高频需求、渠道库存和价格/利润交叉确认，使用季调数据。｜核心验证：海外库存、订单与汇率；必选：海外零售库存、订单、汇率
A3: 指标名称 | B3: 数据来源 | C3: 最新数值 | D3: 单位 | E3: 趋势 | F3: 权重 | G3: 评分 (1-10) | H3: 评分阈值说明 | I3: 历史分位 | J3: 对景气度影响 | K3: 跟踪频率 | L3: 原权重 | M3: 参数优化建议 | N3: 评分口径（更新时采用） | O3: 阶段分项 | P3: 公式分数
A4: 【第一部分：先行指标（Leading Indicators）——提前1-2个季度预示景气变化】 | O4: 先行 | P4: =ROUND(SUMPRODUCT(F5:F8,G5:G8)/SUM(F5:F8),1) -> 7.6
A5: 1-棉花价格变化 | B5: 郑商所/ICE | C5: -5.2 | D5: %YoY | E5: 下行 | F5: 0.1333 | G5: 8 | H5: <-10%=10分,-10-0%=8分,0-5%=6分,5-10%=4分,>10%=2分 | I5: 42% | J5: 棉价回落，纺企成本压力缓解 | K5: 日度 | L5: 0.15 | M5: 目标组权重 40%；按同组相对重要性归一化。 | N5: 改为5年滚动分位(P20/P40/P60/P80)+3个月动量；须与库存、价差或利润交叉确认。 | O5: 同步 | P5: =ROUND(SUMPRODUCT(F10:F13,G10:G13)/SUM(F10:F13),1) -> 6.7
A6: 2-化纤价格变化 | B6: CCFEI | C6: -3.8 | D6: %YoY | E6: 下行 | F6: 0.1067 | G6: 8 | H6: <-5%=10分,-5-0%=8分,0-5%=6分,5-10%=4分,>10%=2分 | I6: 45% | J6: 化纤价格下行，成本端改善 | K6: 周度 | L6: 0.12 | M6: 目标组权重 40%；按同组相对重要性归一化。 | N6: 改为5年滚动分位(P20/P40/P60/P80)+3个月动量；须与库存、价差或利润交叉确认。 | O6: 滞后 | P6: =ROUND(SUMPRODUCT(F15:F17,G15:G17)/SUM(F15:F17),1) -> 6
A7: 3-美国服装零售库存 | B7: 美国商务部 | C7: -3.5 | D7: %YoY | E7: 去库 | F7: 0.0889 | G7: 8 | H7: <-5%=10分,-5-0%=8分,0-5%=6分,5-10%=4分,>10%=2分 | I7: 38% | J7: 海外去库顺利，订单有望回流 | K7: 月度 | L7: 0.1 | M7: 目标组权重 40%；按同组相对重要性归一化。 | N7: 采用同比、环比、历史分位三维评分；按去库/改善方向计分。
A8: 4-人民币汇率 | B8: 中国外汇交易中心 | C8: 7.18 | E8: 贬值 | F8: 0.0711 | G8: 6 | H8: 升值>3%=10分,升值0-3%=8分,持平=6分,贬值0-3%=4分,贬值>3%=2分 | I8: 55% | J8: 汇率小幅贬值，利好出口竞争力 | K8: 日度 | L8: 0.08 | M8: 目标组权重 40%；按同组相对重要性归一化。 | N8: 采用5年滚动分位+同比/环比双阈值；数据滞后超过一个频率周期时自动降权。
A9: 【第二部分：同步指标（Coincident Indicators）——与当前景气同步变动】
A10: 5-纺织品出口金额增速 | B10: 海关总署 | C10: +8.5 | D10: %YoY | E10: 上行 | F10: 0.1333 | G10: 8 | H10: >10%=10分,5-10%=8分,0-5%=6分,-5-0%=4分,<-5%=2分 | I10: 58% | J10: 纺织品出口回暖，外需改善 | K10: 月度 | L10: 0.15 | M10: 目标组权重 40%；按同组相对重要性归一化。 | N10: 采用5年滚动分位+同比/环比双阈值；数据滞后超过一个频率周期时自动降权。
A11: 6-服装出口金额增速 | B11: 海关总署 | C11: +6.2 | D11: %YoY | E11: 上行 | F11: 0.1067 | G11: 6 | H11: >10%=10分,5-10%=8分,0-5%=6分,-5-0%=4分,<-5%=2分 | I11: 55% | J11: 服装出口温和增长 | K11: 月度 | L11: 0.12 | M11: 目标组权重 40%；按同组相对重要性归一化。 | N11: 采用5年滚动分位+同比/环比双阈值；数据滞后超过一个频率周期时自动降权。
A12: 7-柯桥纺织价格指数 | B12: 柯桥指数 | C12: 104 | D12: 点 | E12: 上行 | F12: 0.0889 | G12: 6 | H12: >105=10分,102-105=8分,100-102=6分,98-100=4分,<98=2分 | I12: 58% | J12: 价格指数温和回升 | K12: 周度 | L12: 0.1 | M12: 目标组权重 40%；按同组相对重要性归一化。 | N12: 改为5年滚动分位(P20/P40/P60/P80)+3个月动量；须与库存、价差或利润交叉确认。
A13: 8-纺服企业开工率 | B13: 中国纺织工业联合会 | C13: 78 | D13: % | E13: 上行 | F13: 0.0711 | G13: 6 | H13: >85%=10分,80-85%=8分,75-80%=6分,70-75%=4分,<70%=2分 | I13: 52% | J13: 开工率回升，订单边际改善 | K13: 月度 | L13: 0.08 | M13: 目标组权重 40%；按同组相对重要性归一化。 | N13: 采用5年滚动分位+同比/环比双阈值；数据滞后超过一个频率周期时自动降权。
A14: 【第三部分：滞后指标（Lagging Indicators）——滞后1-2个季度反映景气变化】
A15: 9-纺服企业季度净利润率 | B15: 上市公司财报 | C15: 5.5 | D15: % | E15: 上行 | F15: 0.08 | G15: 6 | H15: >8%=10分,5-8%=8分,3-5%=6分,0-3%=4分,<0%=2分 | I15: 50% | J15: Q1利润率改善，成本红利释放 | K15: 季度 | L15: 0.1 | M15: 目标组权重 20%；按同组相对重要性归一化。 | N15: 采用TTM/滚动4季同比+历史分位；剔除一次性损益，IRR按项目现金流复核。
A16: 10-纺服行业库存周转天数 | B16: 上市公司财报 | C16: 68 | D16: 天 | E16: 下行 | F16: 0.064 | G16: 6 | H16: <60天=10分,60-75天=8分,75-90天=6分,90-105天=4分,>105天=2分 | I16: 48% | J16: 库存周转加快，运营效率提升 | K16: 季度 | L16: 0.08 | M16: 目标组权重 20%；按同组相对重要性归一化。 | N16: 采用同比、环比、历史分位三维评分；按去库/改善方向计分。
A17: 11-社会消费品零售-服装类 | B17: 国家统计局 | C17: +3.8 | D17: %YoY | E17: 上行 | F17: 0.056 | G17: 6 | H17: >10%=10分,5-10%=8分,0-5%=6分,-5-0%=4分,<-5%=2分 | I17: 48% | J17: 服装零售温和增长 | K17: 月度 | L17: 0.07 | M17: 目标组权重 20%；按同组相对重要性归一化。 | N17: 采用季调同比+3个月环比；单月值用3个月移动均值过滤。
A18: 行业综合景气度加权得分 | G18: =ROUND(SUMPRODUCT(F5:F17,G5:G17),1) -> 6.9 | H18: 综合分=Σ(建议权重×单项评分)，建议权重和=100%。

Sheet 轻工制造
A1: 行业景气度量化跟踪体系（参数优化版）— 轻工制造
A2: 默认阶段框架：消费/需求恢复｜先行/同步/滞后=40%/40%/20%。高频需求、渠道库存和价格/利润交叉确认，使用季调数据。｜核心验证：地产后周期/出口与价差；必选：竣工、海外地产、原料与产品价差
A3: 指标名称 | B3: 数据来源 | C3: 最新数值 | D3: 单位 | E3: 趋势 | F3: 权重 | G3: 评分 (1-10) | H3: 评分阈值说明 | I3: 历史分位 | J3: 对景气度影响 | K3: 跟踪频率 | L3: 原权重 | M3: 参数优化建议 | N3: 评分口径（更新时采用） | O3: 阶段分项 | P3: 公式分数
A4: 【第一部分：先行指标（Leading Indicators）——提前1-2个季度预示景气变化】 | O4: 先行 | P4: =ROUND(SUMPRODUCT(F5:F8,G5:G8)/SUM(F5:F8),1) -> 6.6
A5: 1-纸浆价格变化 | B5: 针叶浆/阔叶浆 | C5: -8.5 | D5: %YoY | E5: 下行 | F5: 0.1333 | G5: 8 | H5: <-10%=10分,-10-0%=8分,0-5%=6分,5-10%=4分,>10%=2分 | I5: 35% | J5: 纸浆价格回落，造纸成本改善 | K5: 周度 | L5: 0.15 | M5: 目标组权重 40%；按同组相对重要性归一化。 | N5: 改为5年滚动分位(P20/P40/P60/P80)+3个月动量；须与库存、价差或利润交叉确认。 | O5: 同步 | P5: =ROUND(SUMPRODUCT(F10:F13,G10:G13)/SUM(F10:F13),1) -> 5
A6: 2-木材价格变化 | B6: 木材指数 | C6: -2.5 | D6: %YoY | E6: 下行 | F6: 0.0889 | G6: 8 | H6: <-5%=10分,-5-0%=8分,0-5%=6分,5-10%=4分,>10%=2分 | I6: 42% | J6: 木材价格下行，家具成本下降 | K6: 月度 | L6: 0.1 | M6: 目标组权重 40%；按同组相对重要性归一化。 | N6: 改为5年滚动分位(P20/P40/P60/P80)+3个月动量；须与库存、价差或利润交叉确认。 | O6: 滞后 | P6: =ROUND(SUMPRODUCT(F15:F17,G15:G17)/SUM(F15:F17),1) -> 6
A7: 3-房地产竣工面积增速 | B7: 国家统计局 | C7: -8.5 | D7: %YoY | E7: 下行 | F7: 0.1067 | G7: 4 | H7: >10%=10分,5-10%=8分,0-5%=6分,-5-0%=4分,<-5%=2分 | I7: 25% | J7: 竣工下滑，后周期需求承压 | K7: 月度 | L7: 0.12 | M7: 目标组权重 40%；按同组相对重要性归一化。 | N7: 采用5年滚动分位+同比/环比双阈值；数据滞后超过一个频率周期时自动降权。
A8: 4-美国新房销售 | B8: 美国商务部 | C8: +2.5 | D8: %YoY | E8: 上行 | F8: 0.0711 | G8: 6 | H8: >5%=10分,0-5%=8分,-5-0%=6分,-10--5%=4分,<-10%=2分 | I8: 52% | J8: 美国房市回暖，出口订单有望改善 | K8: 月度 | L8: 0.08 | M8: 目标组权重 40%；按同组相对重要性归一化。 | N8: 采用5年滚动分位+同比/环比双阈值；数据滞后超过一个频率周期时自动降权。
A9: 【第二部分：同步指标（Coincident Indicators）——与当前景气同步变动】
A10: 5-瓦楞纸价格 | B10: 卓创资讯 | C10: 2800 | D10: 元/吨 | E10: 下行 | F10: 0.1143 | G10: 4 | H10: >3500=10分,3200-3500=8分,2900-3200=6分,2600-2900=4分,<2600=2分 | I10: 32% | J10: 瓦楞纸价格低迷，包装需求偏弱 | K10: 周度 | L10: 0.12 | M10: 目标组权重 40%；按同组相对重要性归一化。 | N10: 改为5年滚动分位(P20/P40/P60/P80)+3个月动量；须与库存、价差或利润交叉确认。
A11: 6-双胶纸价格 | B11: 卓创资讯 | C11: 5200 | D11: 元/吨 | E11: 下行 | F11: 0.0952 | G11: 4 | H11: >6000=10分,5500-6000=8分,5000-5500=6分,4500-5000=4分,<4500=2分 | I11: 38% | J11: 文化纸价格承压，出版需求平淡 | K11: 周度 | L11: 0.1 | M11: 目标组权重 40%；按同组相对重要性归一化。 | N11: 改为5年滚动分位(P20/P40/P60/P80)+3个月动量；须与库存、价差或利润交叉确认。
A12: 7-家具零售额增速 | B12: 国家统计局 | C12: +1.5 | D12: %YoY | E12: 上行 | F12: 0.1143 | G12: 6 | H12: >10%=10分,5-10%=8分,0-5%=6分,-5-0%=4分,<-5%=2分 | I12: 45% | J12: 家具零售温和增长，更新需求为主 | K12: 月度 | L12: 0.12 | M12: 目标组权重 40%；按同组相对重要性归一化。 | N12: 采用季调同比+3个月环比；单月值用3个月移动均值过滤。
A13: 8-造纸企业开工率 | B13: 卓创资讯 | C13: 72 | D13: % | E13: 上行 | F13: 0.0762 | G13: 6 | H13: >80%=10分,75-80%=8分,70-75%=6分,65-70%=4分,<65%=2分 | I13: 48% | J13: 开工率回升，供需边际改善 | K13: 月度 | L13: 0.08 | M13: 目标组权重 40%；按同组相对重要性归一化。 | N13: 采用5年滚动分位+同比/环比双阈值；数据滞后超过一个频率周期时自动降权。
A14: 【第三部分：滞后指标（Lagging Indicators）——滞后1-2个季度反映景气变化】
A15: 9-轻工企业季度ROE | B15: 上市公司财报 | C15: 7.5 | D15: % | E15: 上行 | F15: 0.08 | G15: 6 | H15: >12%=10分,8-12%=8分,4-8%=6分,0-4%=4分,<0%=2分 | I15: 48% | J15: Q1 ROE改善，盈利能力修复 | K15: 季度 | L15: 0.1 | M15: 目标组权重 20%；按同组相对重要性归一化。 | N15: 采用TTM/滚动4季同比+历史分位；剔除一次性损益，IRR按项目现金流复核。
A16: 10-轻工行业库存周转天数 | B16: 上市公司财报 | C16: 58 | D16: 天 | E16: 下行 | F16: 0.064 | G16: 6 | H16: <50天=10分,50-65天=8分,65-80天=6分,80-95天=4分,>95天=2分 | I16: 45% | J16: 库存周转加快，运营效率提升 | K16: 季度 | L16: 0.08 | M16: 目标组权重 20%；按同组相对重要性归一化。 | N16: 采用同比、环比、历史分位三维评分；按去库/改善方向计分。
A17: 11-轻工行业固定资产投资 | B17: 国家统计局 | C17: +6.5 | D17: %YoY | E17: 上行 | F17: 0.056 | G17: 6 | H17: >10%=10分,5-10%=8分,0-5%=6分,-5-0%=4分,<-5%=2分 | I17: 52% | J17: 投资温和增长，产能扩张谨慎 | K17: 季度 | L17: 0.07 | M17: 目标组权重 20%；按同组相对重要性归一化。 | N17: 采用5年滚动分位+同比/环比双阈值；数据滞后超过一个频率周期时自动降权。
A18: 行业综合景气度加权得分 | G18: =ROUND(SUMPRODUCT(F5:F17,G5:G17),1) -> 5.8 | H18: 综合分=Σ(建议权重×单项评分)，建议权重和=100%。

Sheet 医药生物
A1: 行业景气度量化跟踪体系（参数优化版）— 医药生物
A2: 默认阶段框架：科技制造/订单库存周期｜先行/同步/滞后=50%/35%/15%。订单、库存和利用率优先；不同子行业拆分后再汇总。｜核心验证：创新、诊疗与政策支付；必选：IND/注册、医保政策、研发融资
A3: 指标名称 | B3: 数据来源 | C3: 最新数值 | D3: 单位 | E3: 趋势 | F3: 权重 | G3: 评分 (1-10) | H3: 评分阈值说明 | I3: 历史分位 | J3: 对景气度影响 | K3: 跟踪频率 | L3: 原权重 | M3: 参数优化建议 | N3: 评分口径（更新时采用） | O3: 阶段分项 | P3: 公式分数
A4: 【第一部分：先行指标（Leading Indicators）——提前1-2个季度预示景气变化】 | O4: 先行 | P4: =ROUND(SUMPRODUCT(F5:F8,G5:G8)/SUM(F5:F8),1) -> 8
A5: 1-创新药IND数量 | B5: CDE | C5: 185 | D5: 个/月 | E5: 上行 | F5: 0.1667 | G5: 8 | H5: >200=10分,150-200=8分,100-150=6分,50-100=4分,<50=2分 | I5: 72% | J5: 创新药申报活跃，研发管线丰富 | K5: 月度 | L5: 0.15 | M5: 目标组权重 50%；按同组相对重要性归一化。 | N5: 采用5年滚动分位+同比/环比双阈值；数据滞后超过一个频率周期时自动降权。 | O5: 同步 | P5: =ROUND(SUMPRODUCT(F10:F13,G10:G13)/SUM(F10:F13),1) -> 7.2
A6: 2-医保谈判降价幅度 | B6: 国家医保局 | C6: 45 | D6: % | E6: 温和 | F6: 0.1111 | G6: 8 | H6: <40%=10分,40-50%=8分,50-60%=6分,60-70%=4分,>70%=2分 | I6: 55% | J6: 降价幅度可控，创新药定价环境改善 | K6: 年度 | L6: 0.1 | M6: 目标组权重 50%；按同组相对重要性归一化。 | N6: 采用5年滚动分位+同比/环比双阈值；数据滞后超过一个频率周期时自动降权。 | O6: 滞后 | P6: =ROUND(SUMPRODUCT(F15:F17,G15:G17)/SUM(F15:F17),1) -> 8
A7: 3-原料药价格变化 | B7: 健康网 | C7: -2.5 | D7: %YoY | E7: 下行 | F7: 0.1111 | G7: 8 | H7: <-5%=10分,-5-0%=8分,0-5%=6分,5-10%=4分,>10%=2分 | I7: 42% | J7: 原料药价格回落，制剂成本改善 | K7: 月度 | L7: 0.1 | M7: 目标组权重 50%；按同组相对重要性归一化。 | N7: 改为5年滚动分位(P20/P40/P60/P80)+3个月动量；须与库存、价差或利润交叉确认。
A8: 4-全球生物医药融资额 | B8: PitchBook | C8: +15 | D8: %YoY | E8: 上行 | F8: 0.1111 | G8: 8 | H8: >20%=10分,10-20%=8分,0-10%=6分,-10-0%=4分,<-10%=2分 | I8: 60% | J8: 融资回暖，创新药估值修复 | K8: 季度 | L8: 0.1 | M8: 目标组权重 50%；按同组相对重要性归一化。 | N8: 滚动3M/4Q同比；以交付、收入或现金流确认，政策/规划单项权重≤8%。
A9: 【第二部分：同步指标（Coincident Indicators）——与当前景气同步变动】
A10: 5-医药制造业收入增速 | B10: 国家统计局 | C10: +8.5 | D10: %YoY | E10: 上行 | F10: 0.1105 | G10: 8 | H10: >10%=10分,5-10%=8分,0-5%=6分,-5-0%=4分,<-5%=2分 | I10: 62% | J10: 制造业收入稳健增长 | K10: 月度 | L10: 0.12 | M10: 目标组权重 35%；按同组相对重要性归一化。 | N10: 采用季调同比+3个月环比；单月值用3个月移动均值过滤。
A11: 6-化学药品原药产量 | B11: 国家统计局 | C11: +4.2 | D11: %YoY | E11: 上行 | F11: 0.0737 | G11: 6 | H11: >5%=10分,2-5%=8分,0-2%=6分,-3-0%=4分,<-3%=2分 | I11: 55% | J11: 原料药产量温和增长 | K11: 月度 | L11: 0.08 | M11: 目标组权重 35%；按同组相对重要性归一化。 | N11: 采用季调同比+3个月环比；单月值用3个月移动均值过滤。
A12: 7-医疗器械出口增速 | B12: 海关总署 | C12: +18.5 | D12: %YoY | E12: 上行 | F12: 0.0921 | G12: 8 | H12: >15%=10分,5-15%=8分,0-5%=6分,-5-0%=4分,<-5%=2分 | I12: 70% | J12: 器械出口强劲，海外需求旺盛 | K12: 月度 | L12: 0.1 | M12: 目标组权重 35%；按同组相对重要性归一化。 | N12: 采用5年滚动分位+同比/环比双阈值；数据滞后超过一个频率周期时自动降权。
A13: 8-医院诊疗人次增速 | B13: 国家卫健委 | C13: +6.5 | D13: %YoY | E13: 上行 | F13: 0.0737 | G13: 6 | H13: >10%=10分,5-10%=8分,0-5%=6分,-5-0%=4分,<-5%=2分 | I13: 58% | J13: 诊疗人次恢复，院内需求回暖 | K13: 月度 | L13: 0.08 | M13: 目标组权重 35%；按同组相对重要性归一化。 | N13: 采用5年滚动分位+同比/环比双阈值；数据滞后超过一个频率周期时自动降权。
A14: 【第三部分：滞后指标（Lagging Indicators）——滞后1-2个季度反映景气变化】
A15: 9-医药企业季度毛利率 | B15: 上市公司财报 | C15: 55 | D15: % | E15: 上行 | F15: 0.06 | G15: 8 | H15: >60%=10分,50-60%=8分,40-50%=6分,30-40%=4分,<30%=2分 | I15: 65% | J15: Q1毛利率稳健，产品结构优化 | K15: 季度 | L15: 0.1 | M15: 目标组权重 15%；按同组相对重要性归一化。 | N15: 改为5年滚动分位(P20/P40/P60/P80)+3个月动量；须与库存、价差或利润交叉确认。
A16: 10-医药企业研发费用率 | B16: 上市公司财报 | C16: 12 | D16: % | E16: 上行 | F16: 0.048 | G16: 8 | H16: >15%=10分,10-15%=8分,5-10%=6分,2-5%=4分,<2%=2分 | I16: 60% | J16: 研发投入维持高位，创新转型加速 | K16: 季度 | L16: 0.08 | M16: 目标组权重 15%；按同组相对重要性归一化。 | N16: 采用5年滚动分位+同比/环比双阈值；数据滞后超过一个频率周期时自动降权。
A17: 11-医药制造业利润增速 | B17: 国家统计局 | C17: +12 | D17: %YoY | E17: 上行 | F17: 0.042 | G17: 8 | H17: >15%=10分,5-15%=8分,0-5%=6分,-5-0%=4分,<-5%=2分 | I17: 65% | J17: 利润增速回升，盈利能力改善 | K17: 月度 | L17: 0.07 | M17: 目标组权重 15%；按同组相对重要性归一化。 | N17: 采用TTM/滚动4季同比+历史分位；剔除一次性损益，IRR按项目现金流复核。
A18: 行业综合景气度加权得分 | G18: =ROUND(SUMPRODUCT(F5:F17,G5:G17),1) -> 7.7 | H18: 综合分=Σ(建议权重×单项评分)，建议权重和=100%。

Sheet 公用事业
A1: 行业景气度量化跟踪体系（参数优化版）— 公用事业
A2: 默认阶段框架：防御/成熟｜先行/同步/滞后=30%/45%/25%。同步经营和现金流优先；先行指标只作边际变化确认。｜核心验证：利用小时、燃料传导与资本回报；必选：来水、燃料、电价机制、装机进度
A3: 指标名称 | B3: 数据来源 | C3: 最新数值 | D3: 单位 | E3: 趋势 | F3: 权重 | G3: 评分 (1-10) | H3: 评分阈值说明 | I3: 历史分位 | J3: 对景气度影响 | K3: 跟踪频率 | L3: 原权重 | M3: 参数优化建议 | N3: 评分口径（更新时采用） | O3: 阶段分项 | P3: 公式分数
A4: 【第一部分：先行指标（Leading Indicators）——提前1-2个季度预示景气变化】 | O4: 先行 | P4: =ROUND(SUMPRODUCT(F5:F8,G5:G8)/SUM(F5:F8),1) -> 9
A5: 1-动力煤价格变化 | B5: 秦皇岛动力煤 | C5: -12 | D5: %YoY | E5: 下行 | F5: 0.1 | G5: 10 | H5: <-10%=10分,-10-0%=8分,0-5%=6分,5-10%=4分,>10%=2分 | I5: 28% | J5: 煤价大幅回落，火电成本显著改善 | K5: 周度 | L5: 0.15 | M5: 目标组权重 30%；按同组相对重要性归一化。 | N5: 改为5年滚动分位(P20/P40/P60/P80)+3个月动量；须与库存、价差或利润交叉确认。 | O5: 同步 | P5: =ROUND(SUMPRODUCT(F10:F13,G10:G13)/SUM(F10:F13),1) -> 7.1
A6: 2-天然气进口价格 | B6: 海关总署 | C6: -5.5 | D6: %YoY | E6: 下行 | F6: 0.08 | G6: 8 | H6: <-5%=10分,-5-0%=8分,0-5%=6分,5-10%=4分,>10%=2分 | I6: 38% | J6: 气价回落，燃气发电成本下降 | K6: 月度 | L6: 0.12 | M6: 目标组权重 30%；按同组相对重要性归一化。 | N6: 改为5年滚动分位(P20/P40/P60/P80)+3个月动量；须与库存、价差或利润交叉确认。 | O6: 滞后 | P6: =ROUND(SUMPRODUCT(F15:F17,G15:G17)/SUM(F15:F17),1) -> 8
A7: 3-来水情况(三峡出库流量) | B7: 长江水利委员会 | C7: 18500 | D7: m³/s | E7: 充沛 | F7: 0.0667 | G7: 8 | H7: >20000=10分,15000-20000=8分,10000-15000=6分,5000-10000=4分,<5000=2分 | I7: 72% | J7: 来水充沛，水电出力提升 | K7: 日度 | L7: 0.1 | M7: 目标组权重 30%；按同组相对重要性归一化。 | N7: 采用5年滚动分位+同比/环比双阈值；数据滞后超过一个频率周期时自动降权。
A8: 4-新能源装机规划 | B8: 国家能源局 | C8: 120 | D8: GW | E8: 高增 | F8: 0.0533 | G8: 10 | H8: >100=10分,70-100=8分,50-70=6分,30-50%=4分,<30=2分 | I8: 85% | J8: 新能源装机规划创新高，绿电转型加速 | K8: 年度 | L8: 0.08 | M8: 目标组权重 30%；按同组相对重要性归一化。 | N8: 滚动3M/4Q同比；以交付、收入或现金流确认，政策/规划单项权重≤8%。
A9: 【第二部分：同步指标（Coincident Indicators）——与当前景气同步变动】
A10: 5-全社会用电量增速 | B10: 国家能源局 | C10: +7.5 | D10: %YoY | E10: 上行 | F10: 0.1646 | G10: 8 | H10: >8%=10分,5-8%=8分,3-5%=6分,0-3%=4分,<0%=2分 | I10: 62% | J10: 用电量稳健增长，经济活力回升 | K10: 月度 | L10: 0.15 | M10: 目标组权重 45%；按同组相对重要性归一化。 | N10: 采用5年滚动分位+同比/环比双阈值；数据滞后超过一个频率周期时自动降权。
A11: 6-火电利用小时数 | B11: 国家能源局 | C11: 1180 | D11: 小时(累计) | E11: 上行 | F11: 0.1098 | G11: 6 | H11: >4200年化=10分,4000-4200=8分,3800-4000=6分,3600-3800=4分,<3600=2分 | I11: 55% | J11: 火电利用小时回升，煤电需求改善 | K11: 月度 | L11: 0.1 | M11: 目标组权重 45%；按同组相对重要性归一化。 | N11: 采用5年滚动分位+同比/环比双阈值；数据滞后超过一个频率周期时自动降权。
A12: 7-水电利用小时数 | B12: 国家能源局 | C12: 980 | D12: 小时(累计) | E12: 上行 | F12: 0.0878 | G12: 8 | H12: >3800年化=10分,3500-3800=8分,3200-3500=6分,2900-3200=4分,<2900=2分 | I12: 70% | J12: 水电利用小时高增，来水偏丰 | K12: 月度 | L12: 0.08 | M12: 目标组权重 45%；按同组相对重要性归一化。 | N12: 采用5年滚动分位+同比/环比双阈值；数据滞后超过一个频率周期时自动降权。
A13: 8-风电/光伏利用小时数 | B13: 国家能源局 | C13: +5 | D13: %vs均值 | E13: 上行 | F13: 0.0878 | G13: 6 | H13: >均值10%=10分,0-10%=8分,-10-0%=6分,-20--10%=4分,<-20%=2分 | I13: 58% | J13: 新能源利用小时改善，消纳好转 | K13: 月度 | L13: 0.08 | M13: 目标组权重 45%；按同组相对重要性归一化。 | N13: 采用5年滚动分位+同比/环比双阈值；数据滞后超过一个频率周期时自动降权。
A14: 【第三部分：滞后指标（Lagging Indicators）——滞后1-2个季度反映景气变化】
A15: 9-电力企业季度ROE | B15: 上市公司财报 | C15: 8.5 | D15: % | E15: 上行 | F15: 0.1 | G15: 8 | H15: >10%=10分,7-10%=8分,4-7%=6分,1-4%=4分,<1%=2分 | I15: 60% | J15: Q1 ROE改善，煤价红利释放 | K15: 季度 | L15: 0.1 | M15: 目标组权重 25%；按同组相对重要性归一化。 | N15: 采用TTM/滚动4季同比+历史分位；剔除一次性损益，IRR按项目现金流复核。
A16: 10-电力行业资产负债率 | B16: 上市公司财报 | C16: 62 | D16: % | E16: 下行 | F16: 0.08 | G16: 8 | H16: <60%=10分,60-65%=8分,65-70%=6分,70-75%=4分,>75%=2分 | I16: 45% | J16: 负债率下降，财务结构优化 | K16: 季度 | L16: 0.08 | M16: 目标组权重 25%；按同组相对重要性归一化。 | N16: 采用同比、环比、历史分位三维评分；按去库/改善方向计分。
A17: 11-电力行业固定资产投资 | B17: 国家统计局 | C17: +18 | D17: %YoY | E17: 上行 | F17: 0.07 | G17: 8 | H17: >15%=10分,5-15%=8分,0-5%=6分,-5-0%=4分,<-5%=2分 | I17: 72% | J17: 投资高增，电网/新能源建设加速 | K17: 季度 | L17: 0.07 | M17: 目标组权重 25%；按同组相对重要性归一化。 | N17: 采用5年滚动分位+同比/环比双阈值；数据滞后超过一个频率周期时自动降权。
A18: 行业综合景气度加权得分 | G18: =ROUND(SUMPRODUCT(F5:F17,G5:G17),1) -> 7.9 | H18: 综合分=Σ(建议权重×单项评分)，建议权重和=100%。

Sheet 交通运输
A1: 行业景气度量化跟踪体系（参数优化版）— 交通运输
A2: 默认阶段框架：消费/需求恢复｜先行/同步/滞后=40%/40%/20%。高频需求、渠道库存和价格/利润交叉确认，使用季调数据。｜核心验证：运价、运量与供给；必选：运力投放、运价、油价
A3: 指标名称 | B3: 数据来源 | C3: 最新数值 | D3: 单位 | E3: 趋势 | F3: 权重 | G3: 评分 (1-10) | H3: 评分阈值说明 | I3: 历史分位 | J3: 对景气度影响 | K3: 跟踪频率 | L3: 原权重 | M3: 参数优化建议 | N3: 评分口径（更新时采用） | O3: 阶段分项 | P3: 公式分数
A4: 【第一部分：先行指标（Leading Indicators）——提前1-2个季度预示景气变化】 | O4: 先行 | P4: =ROUND(SUMPRODUCT(F5:F8,G5:G8)/SUM(F5:F8),1) -> 8
A5: 1-BDI指数 | B5: 波罗的海交易所 | C5: 1850 | D5: 点 | E5: 上行 | F5: 0.1333 | G5: 8 | H5: >2000=10分,1500-2000=8分,1000-1500=6分,500-1000=4分,<500=2分 | I5: 68% | J5: 干散货运价回升，大宗商品贸易活跃 | K5: 日度 | L5: 0.15 | M5: 目标组权重 40%；按同组相对重要性归一化。 | N5: 采用5年滚动分位+同比/环比双阈值；数据滞后超过一个频率周期时自动降权。 | O5: 同步 | P5: =ROUND(SUMPRODUCT(F10:F13,G10:G13)/SUM(F10:F13),1) -> 8
A6: 2-原油运输指数(BDTI) | B6: 波罗的海交易所 | C6: 1150 | D6: 点 | E6: 上行 | F6: 0.0889 | G6: 8 | H6: >1200=10分,900-1200=8分,600-900=6分,400-600=4分,<400=2分 | I6: 65% | J6: 油运运价高位，红海绕行支撑 | K6: 日度 | L6: 0.1 | M6: 目标组权重 40%；按同组相对重要性归一化。 | N6: 采用5年滚动分位+同比/环比双阈值；数据滞后超过一个频率周期时自动降权。 | O6: 滞后 | P6: =ROUND(SUMPRODUCT(F15:F17,G15:G17)/SUM(F15:F17),1) -> 8
A7: 3-集装箱运价指数(CCFI) | B7: 上海航运交易所 | C7: 1250 | D7: 点 | E7: 上行 | F7: 0.1067 | G7: 8 | H7: >1200=10分,1000-1200=8分,800-1000=6分,600-800=4分,<600=2分 | I7: 62% | J7: 集运运价回升，出口需求强劲 | K7: 周度 | L7: 0.12 | M7: 目标组权重 40%；按同组相对重要性归一化。 | N7: 采用5年滚动分位+同比/环比双阈值；数据滞后超过一个频率周期时自动降权。
A8: 4-航空煤油价格 | B8: IATA | C8: -8.5 | D8: %YoY | E8: 下行 | F8: 0.0711 | G8: 8 | H8: <-10%=10分,-10-0%=8分,0-5%=6分,5-10%=4分,>10%=2分 | I8: 35% | J8: 航油价格回落，航空成本改善 | K8: 月度 | L8: 0.08 | M8: 目标组权重 40%；按同组相对重要性归一化。 | N8: 改为5年滚动分位(P20/P40/P60/P80)+3个月动量；须与库存、价差或利润交叉确认。
A9: 【第二部分：同步指标（Coincident Indicators）——与当前景气同步变动】
A10: 5-港口货物吞吐量增速 | B10: 交通运输部 | C10: +5.5 | D10: %YoY | E10: 上行 | F10: 0.12 | G10: 8 | H10: >5%=10分,3-5%=8分,0-3%=6分,-3-0%=4分,<-3%=2分 | I10: 58% | J10: 港口吞吐量增长，贸易活动活跃 | K10: 月度 | L10: 0.12 | M10: 目标组权重 40%；按同组相对重要性归一化。 | N10: 采用季调同比+3个月环比；单月值用3个月移动均值过滤。
A11: 6-民航客运量增速 | B11: 民航局 | C11: +16.5 | D11: %YoY | E11: 上行 | F11: 0.12 | G11: 8 | H11: >15%=10分,10-15%=8分,5-10%=6分,0-5%=4分,<0%=2分 | I11: 70% | J11: 民航客运强劲恢复，出行需求旺盛 | K11: 月度 | L11: 0.12 | M11: 目标组权重 40%；按同组相对重要性归一化。 | N11: 采用季调同比+3个月环比；单月值用3个月移动均值过滤。
A12: 7-铁路货运量增速 | B12: 国铁集团 | C12: +4.5 | D12: %YoY | E12: 上行 | F12: 0.08 | G12: 6 | H12: >5%=10分,3-5%=8分,0-3%=6分,-3-0%=4分,<-3%=2分 | I12: 55% | J12: 铁路货运平稳增长 | K12: 月度 | L12: 0.08 | M12: 目标组权重 40%；按同组相对重要性归一化。 | N12: 采用季调同比+3个月环比；单月值用3个月移动均值过滤。
A13: 8-快递业务量增速 | B13: 国家邮政局 | C13: +22 | D13: %YoY | E13: 上行 | F13: 0.08 | G13: 10 | H13: >20%=10分,15-20%=8分,10-15%=6分,5-10%=4分,<5%=2分 | I13: 75% | J13: 快递业务量高增，电商消费活跃 | K13: 月度 | L13: 0.08 | M13: 目标组权重 40%；按同组相对重要性归一化。 | N13: 采用季调同比+3个月环比；单月值用3个月移动均值过滤。
A14: 【第三部分：滞后指标（Lagging Indicators）——滞后1-2个季度反映景气变化】
A15: 9-交运企业季度净利润 | B15: 上市公司财报 | C15: 85 | D15: 亿元 | E15: 上行 | F15: 0.08 | G15: 8 | H15: >50亿=10分,20-50亿=8分,0-20亿=6分,-20-0亿=4分,<-20亿=2分 | I15: 68% | J15: Q1净利润改善，油运/航空贡献 | K15: 季度 | L15: 0.1 | M15: 目标组权重 20%；按同组相对重要性归一化。 | N15: 采用TTM/滚动4季同比+历史分位；剔除一次性损益，IRR按项目现金流复核。
A16: 10-交运行业资产负债率 | B16: 上市公司财报 | C16: 58 | D16: % | E16: 下行 | F16: 0.064 | G16: 8 | H16: <55%=10分,55-60%=8分,60-65%=6分,65-70%=4分,>70%=2分 | I16: 48% | J16: 负债率下降，财务结构优化 | K16: 季度 | L16: 0.08 | M16: 目标组权重 20%；按同组相对重要性归一化。 | N16: 采用同比、环比、历史分位三维评分；按去库/改善方向计分。
A17: 11-交运行业固定资产投资 | B17: 国家统计局 | C17: +8.5 | D17: %YoY | E17: 上行 | F17: 0.056 | G17: 8 | H17: >10%=10分,5-10%=8分,0-5%=6分,-5-0%=4分,<-5%=2分 | I17: 58% | J17: 投资温和增长，基础设施完善 | K17: 季度 | L17: 0.07 | M17: 目标组权重 20%；按同组相对重要性归一化。 | N17: 采用5年滚动分位+同比/环比双阈值；数据滞后超过一个频率周期时自动降权。
A18: 行业综合景气度加权得分 | G18: =ROUND(SUMPRODUCT(F5:F17,G5:G17),1) -> 8 | H18: 综合分=Σ(建议权重×单项评分)，建议权重和=100%。

Sheet 房地产
A1: 行业景气度量化跟踪体系（参数优化版）— 房地产
A2: 默认阶段框架：强周期/供给出清｜先行/同步/滞后=50%/35%/15%。先用库存、供给、订单确认反转；价格本身不能直接等同高景气。｜核心验证：融资、销售与库存去化；必选：按揭利率、融资、限购/供给、城市库存
A3: 指标名称 | B3: 数据来源 | C3: 最新数值 | D3: 单位 | E3: 趋势 | F3: 权重 | G3: 评分 (1-10) | H3: 评分阈值说明 | I3: 历史分位 | J3: 对景气度影响 | K3: 跟踪频率 | L3: 原权重 | M3: 参数优化建议 | N3: 评分口径（更新时采用） | O3: 阶段分项 | P3: 公式分数
A4: 【第一部分：先行指标（Leading Indicators）——提前1-2个季度预示景气变化】 | O4: 先行 | P4: =ROUND(SUMPRODUCT(F5:F8,G5:G8)/SUM(F5:F8),1) -> 4.9
A5: 1-百城土地成交面积增速 | B5: 中指院 | C5: -15 | D5: %YoY | E5: 下行 | F5: 0.1667 | G5: 4 | H5: >10%=10分,0-10%=8分,-10-0%=6分,-20--10%=4分,<-20%=2分 | I5: 22% | J5: 土地成交低迷，房企拿地谨慎 | K5: 月度 | L5: 0.15 | M5: 目标组权重 50%；按同组相对重要性归一化。 | N5: 采用5年滚动分位+同比/环比双阈值；数据滞后超过一个频率周期时自动降权。 | O5: 同步 | P5: =ROUND(SUMPRODUCT(F10:F13,G10:G13)/SUM(F10:F13),1) -> 4
A6: 2-房企拿地金额增速 | B6: 中指院 | C6: -18 | D6: %YoY | E6: 下行 | F6: 0.1333 | G6: 4 | H6: >5%=10分,0-5%=8分,-10-0%=6分,-20--10%=4分,<-20%=2分 | I6: 20% | J6: 拿地金额大幅下滑，投资意愿弱 | K6: 月度 | L6: 0.12 | M6: 目标组权重 50%；按同组相对重要性归一化。 | N6: 采用5年滚动分位+同比/环比双阈值；数据滞后超过一个频率周期时自动降权。 | O6: 滞后 | P6: =ROUND(SUMPRODUCT(F15:F17,G15:G17)/SUM(F15:F17),1) -> 3.4
A7: 3-房贷利率 | B7: 央行 | C7: 3.45 | D7: % | E7: 下行 | F7: 0.1111 | G7: 8 | H7: <3.5%=10分,3.5-4.0%=8分,4.0-4.5%=6分,4.5-5.0%=4分,>5.0%=2分 | I7: 35% | J7: 利率处于历史低位，但刺激效果有限 | K7: 月度 | L7: 0.1 | M7: 目标组权重 50%；按同组相对重要性归一化。 | N7: 改为5年滚动分位(P20/P40/P60/P80)+3个月动量；须与库存、价差或利润交叉确认。
A8: 4-房地产信托发行规模 | B8: 用益信托 | C8: -25 | D8: %YoY | E8: 下行 | F8: 0.0889 | G8: 4 | H8: >10%=10分,0-10%=8分,-10-0%=6分,-20--10%=4分,<-20%=2分 | I8: 18% | J8: 信托融资萎缩，房企资金链紧张 | K8: 季度 | L8: 0.08 | M8: 目标组权重 50%；按同组相对重要性归一化。 | N8: 采用5年滚动分位+同比/环比双阈值；数据滞后超过一个频率周期时自动降权。
A9: 【第二部分：同步指标（Coincident Indicators）——与当前景气同步变动】
A10: 5-商品房销售面积增速 | B10: 国家统计局 | C10: -8.5 | D10: %YoY | E10: 下行 | F10: 0.1167 | G10: 4 | H10: >5%=10分,0-5%=8分,-5-0%=6分,-10--5%=4分,<-10%=2分 | I10: 25% | J10: 销售持续低迷，市场信心不足 | K10: 月度 | L10: 0.15 | M10: 目标组权重 35%；按同组相对重要性归一化。 | N10: 采用5年滚动分位+同比/环比双阈值；数据滞后超过一个频率周期时自动降权。
A11: 6-70城新建商品住宅价格指数 | B11: 国家统计局 | C11: -0.8 | D11: %MoM | E11: 下行 | F11: 0.0933 | G11: 4 | H11: >0.5%=10分,0-0.5%=8分,-0.5-0%=6分,-1--0.5%=4分,<-1%=2分 | I11: 22% | J11: 房价环比下跌，市场调整持续 | K11: 月度 | L11: 0.12 | M11: 目标组权重 35%；按同组相对重要性归一化。 | N11: 改为5年滚动分位(P20/P40/P60/P80)+3个月动量；须与库存、价差或利润交叉确认。
A12: 7-二手房挂牌量变化 | B12: 贝壳研究院 | C12: +8.5 | D12: %MoM | E12: 上行 | F12: 0.0622 | G12: 4 | H12: <-5%=10分,-5-0%=8分,0-5%=6分,5-10%=4分,>10%=2分 | I12: 68% | J12: 挂牌量增加，供给压力加大 | K12: 月度 | L12: 0.08 | M12: 目标组权重 35%；按同组相对重要性归一化。 | N12: 采用同比、环比、历史分位三维评分；按去库/改善方向计分。
A13: 8-房地产新开工面积增速 | B13: 国家统计局 | C13: -22 | D13: %YoY | E13: 下行 | F13: 0.0778 | G13: 4 | H13: >5%=10分,0-5%=8分,-10-0%=6分,-20--10%=4分,<-20%=2分 | I13: 18% | J13: 新开工大幅下滑，供给端收缩 | K13: 月度 | L13: 0.1 | M13: 目标组权重 35%；按同组相对重要性归一化。 | N13: 采用5年滚动分位+同比/环比双阈值；数据滞后超过一个频率周期时自动降权。
A14: 【第三部分：滞后指标（Lagging Indicators）——滞后1-2个季度反映景气变化】
A15: 9-房地产竣工面积增速 | B15: 国家统计局 | C15: -12 | D15: %YoY | E15: 下行 | F15: 0.06 | G15: 4 | H15: >10%=10分,5-10%=8分,0-5%=6分,-5-0%=4分,<-5%=2分 | I15: 28% | J15: 竣工下滑，后周期产业承压 | K15: 月度 | L15: 0.1 | M15: 目标组权重 15%；按同组相对重要性归一化。 | N15: 采用5年滚动分位+同比/环比双阈值；数据滞后超过一个频率周期时自动降权。
A16: 10-房企季度净利润 | B16: 上市公司财报 | C16: -35 | D16: 亿元 | E16: 亏损 | F16: 0.048 | G16: 2 | H16: >100亿=10分,50-100亿=8分,0-50亿=6分,-50-0亿=4分,<-50亿=2分 | I16: 15% | J16: Q1多数房企亏损，盈利能力恶化 | K16: 季度 | L16: 0.08 | M16: 目标组权重 15%；按同组相对重要性归一化。 | N16: 采用TTM/滚动4季同比+历史分位；剔除一次性损益，IRR按项目现金流复核。
A17: 11-房地产投资增速 | B17: 国家统计局 | C17: -10.5 | D17: %YoY | E17: 下行 | F17: 0.042 | G17: 4 | H17: >5%=10分,0-5%=8分,-5-0%=6分,-10--5%=4分,<-10%=2分 | I17: 20% | J17: 投资持续下滑，拖累经济增长 | K17: 月度 | L17: 0.07 | M17: 目标组权重 15%；按同组相对重要性归一化。 | N17: 采用5年滚动分位+同比/环比双阈值；数据滞后超过一个频率周期时自动降权。
A18: 行业综合景气度加权得分 | G18: =ROUND(SUMPRODUCT(F5:F17,G5:G17),1) -> 4.3 | H18: 综合分=Σ(建议权重×单项评分)，建议权重和=100%。

Sheet 商贸零售
A1: 行业景气度量化跟踪体系（参数优化版）— 商贸零售
A2: 默认阶段框架：消费/需求恢复｜先行/同步/滞后=40%/40%/20%。高频需求、渠道库存和价格/利润交叉确认，使用季调数据。｜核心验证：客流、同店和渠道效率；必选：消费者信心、可支配收入、流量
A3: 指标名称 | B3: 数据来源 | C3: 最新数值 | D3: 单位 | E3: 趋势 | F3: 权重 | G3: 评分 (1-10) | H3: 评分阈值说明 | I3: 历史分位 | J3: 对景气度影响 | K3: 跟踪频率 | L3: 原权重 | M3: 参数优化建议 | N3: 评分口径（更新时采用） | O3: 阶段分项 | P3: 公式分数
A4: 【第一部分：先行指标（Leading Indicators）——提前1-2个季度预示景气变化】 | O4: 先行 | P4: =ROUND(SUMPRODUCT(F5:F8,G5:G8)/SUM(F5:F8),1) -> 5.5
A5: 1-社会消费品零售总额增速 | B5: 国家统计局 | C5: +5.2 | D5: %YoY | E5: 上行 | F5: 0.1333 | G5: 6 | H5: >8%=10分,5-8%=8分,3-5%=6分,0-3%=4分,<0%=2分 | I5: 48% | J5: 社零温和增长，消费复苏缓慢 | K5: 月度 | L5: 0.15 | M5: 目标组权重 40%；按同组相对重要性归一化。 | N5: 采用季调同比+3个月环比；单月值用3个月移动均值过滤。 | O5: 同步 | P5: =ROUND(SUMPRODUCT(F10:F13,G10:G13)/SUM(F10:F13),1) -> 7.4
A6: 2-消费者信心指数 | B6: 国家统计局 | C6: 88 | D6: 点 | E6: 下行 | F6: 0.1067 | G6: 4 | H6: >120=10分,110-120=8分,100-110=6分,90-100=4分,<90=2分 | I6: 25% | J6: 信心指数低迷，消费意愿不足 | K6: 月度 | L6: 0.12 | M6: 目标组权重 40%；按同组相对重要性归一化。 | N6: 采用5年滚动分位+同比/环比双阈值；数据滞后超过一个频率周期时自动降权。 | O6: 滞后 | P6: =ROUND(SUMPRODUCT(F15:F17,G15:G17)/SUM(F15:F17),1) -> 6.6
A7: 3-人均可支配收入增速 | B7: 国家统计局 | C7: +5.8 | D7: %YoY | E7: 上行 | F7: 0.0889 | G7: 6 | H7: >8%=10分,6-8%=8分,4-6%=6分,2-4%=4分,<2%=2分 | I7: 48% | J7: 收入增速放缓，消费能力受限 | K7: 季度 | L7: 0.1 | M7: 目标组权重 40%；按同组相对重要性归一化。 | N7: 采用季调同比+3个月环比；单月值用3个月移动均值过滤。
A8: 4-网购渗透率 | B8: 商务部 | C8: 28.5 | D8: % | E8: 上行 | F8: 0.0711 | G8: 6 | H8: >30%=10分,27-30%=8分,24-27%=6分,21-24%=4分,<21%=2分 | I8: 55% | J8: 线上渗透率提升，渠道结构优化 | K8: 季度 | L8: 0.08 | M8: 目标组权重 40%；按同组相对重要性归一化。 | N8: 采用5年滚动分位+同比/环比双阈值；数据滞后超过一个频率周期时自动降权。
A9: 【第二部分：同步指标（Coincident Indicators）——与当前景气同步变动】
A10: 5-网上零售额增速 | B10: 国家统计局 | C10: +12.5 | D10: %YoY | E10: 上行 | F10: 0.12 | G10: 8 | H10: >15%=10分,10-15%=8分,5-10%=6分,0-5%=4分,<0%=2分 | I10: 62% | J10: 线上零售强劲，电商活力充沛 | K10: 月度 | L10: 0.12 | M10: 目标组权重 40%；按同组相对重要性归一化。 | N10: 采用季调同比+3个月环比；单月值用3个月移动均值过滤。
A11: 6-限额以上零售企业收入 | B11: 国家统计局 | C11: +4.8 | D11: %YoY | E11: 上行 | F11: 0.1 | G11: 6 | H11: >10%=10分,5-10%=8分,0-5%=6分,-5-0%=4分,<-5%=2分 | I11: 50% | J11: 限额以上零售温和增长 | K11: 月度 | L11: 0.1 | M11: 目标组权重 40%；按同组相对重要性归一化。 | N11: 采用季调同比+3个月环比；单月值用3个月移动均值过滤。
A12: 7-超市/百货销售额增速 | B12: 商务部 | C12: +2.5 | D12: %YoY | E12: 上行 | F12: 0.1 | G12: 6 | H12: >5%=10分,2-5%=8分,0-2%=6分,-3-0%=4分,<-3%=2分 | I12: 48% | J12: 线下零售缓慢复苏 | K12: 月度 | L12: 0.1 | M12: 目标组权重 40%；按同组相对重要性归一化。 | N12: 采用5年滚动分位+同比/环比双阈值；数据滞后超过一个频率周期时自动降权。
A13: 8-快递业务量增速 | B13: 国家邮政局 | C13: +22 | D13: %YoY | E13: 上行 | F13: 0.08 | G13: 10 | H13: >20%=10分,15-20%=8分,10-15%=6分,5-10%=4分,<5%=2分 | I13: 75% | J13: 快递高增，电商消费活跃 | K13: 月度 | L13: 0.08 | M13: 目标组权重 40%；按同组相对重要性归一化。 | N13: 采用季调同比+3个月环比；单月值用3个月移动均值过滤。
A14: 【第三部分：滞后指标（Lagging Indicators）——滞后1-2个季度反映景气变化】
A15: 9-零售企业季度净利润率 | B15: 上市公司财报 | C15: 3.5 | D15: % | E15: 上行 | F15: 0.08 | G15: 6 | H15: >5%=10分,3-5%=8分,1-3%=6分,0-1%=4分,<0%=2分 | I15: 50% | J15: Q1利润率改善，但仍处低位 | K15: 季度 | L15: 0.1 | M15: 目标组权重 20%；按同组相对重要性归一化。 | N15: 采用TTM/滚动4季同比+历史分位；剔除一次性损益，IRR按项目现金流复核。
A16: 10-零售行业库存周转天数 | B16: 上市公司财报 | C16: 45 | D16: 天 | E16: 下行 | F16: 0.064 | G16: 8 | H16: <40天=10分,40-50天=8分,50-60天=6分,60-70天=4分,>70天=2分 | I16: 48% | J16: 库存周转加快，运营效率提升 | K16: 季度 | L16: 0.08 | M16: 目标组权重 20%；按同组相对重要性归一化。 | N16: 采用同比、环比、历史分位三维评分；按去库/改善方向计分。
A17: 11-CPI同比 | B17: 国家统计局 | C17: +0.3 | D17: % | E17: 上行 | F17: 0.056 | G17: 6 | H17: >2%=10分,1-2%=8分,0-1%=6分,-1-0%=4分,<-1%=2分 | I17: 35% | J17: 通胀温和，终端价格稳定 | K17: 月度 | L17: 0.07 | M17: 目标组权重 20%；按同组相对重要性归一化。 | N17: 采用5年滚动分位+同比/环比双阈值；数据滞后超过一个频率周期时自动降权。
A18: 行业综合景气度加权得分 | G18: =ROUND(SUMPRODUCT(F5:F17,G5:G17),1) -> 6.5 | H18: 综合分=Σ(建议权重×单项评分)，建议权重和=100%。

Sheet 社会服务
A1: 行业景气度量化跟踪体系（参数优化版）— 社会服务
A2: 默认阶段框架：消费/需求恢复｜先行/同步/滞后=40%/40%/20%。高频需求、渠道库存和价格/利润交叉确认，使用季调数据。｜核心验证：预订、客流与价格；必选：预订、客座率、出行意愿
A3: 指标名称 | B3: 数据来源 | C3: 最新数值 | D3: 单位 | E3: 趋势 | F3: 权重 | G3: 评分 (1-10) | H3: 评分阈值说明 | I3: 历史分位 | J3: 对景气度影响 | K3: 跟踪频率 | L3: 原权重 | M3: 参数优化建议 | N3: 评分口径（更新时采用） | O3: 阶段分项 | P3: 公式分数
A4: 【第一部分：先行指标（Leading Indicators）——提前1-2个季度预示景气变化】 | O4: 先行 | P4: =ROUND(SUMPRODUCT(F5:F8,G5:G8)/SUM(F5:F8),1) -> 7.2
A5: 1-居民可支配收入增速 | B5: 国家统计局 | C5: +5.8 | D5: %YoY | E5: 上行 | F5: 0.1333 | G5: 6 | H5: >8%=10分,6-8%=8分,4-6%=6分,2-4%=4分,<2%=2分 | I5: 48% | J5: 收入增速放缓，消费能力受限 | K5: 季度 | L5: 0.15 | M5: 目标组权重 40%；按同组相对重要性归一化。 | N5: 采用季调同比+3个月环比；单月值用3个月移动均值过滤。 | O5: 同步 | P5: =ROUND(SUMPRODUCT(F10:F13,G10:G13)/SUM(F10:F13),1) -> 7.6
A6: 2-节假日旅游预订量 | B6: 携程/去哪儿 | C6: +35 | D6: %YoY | E6: 上行 | F6: 0.1067 | G6: 9 | H6: >30%=10分,20-30%=8分,10-20%=6分,0-10%=4分,<0%=2分 | I6: 78% | J6: 旅游预订火爆，出行需求旺盛 | K6: 节假日 | L6: 0.12 | M6: 目标组权重 40%；按同组相对重要性归一化。 | N6: 采用5年滚动分位+同比/环比双阈值；数据滞后超过一个频率周期时自动降权。 | O6: 滞后 | P6: =ROUND(SUMPRODUCT(F15:F17,G15:G17)/SUM(F15:F17),1) -> 5.4
A7: 3-航空客座率 | B7: 民航局 | C7: 82 | D7: % | E7: 上行 | F7: 0.0889 | G7: 6 | H7: >85%=10分,80-85%=8分,75-80%=6分,70-75%=4分,<70%=2分 | I7: 62% | J7: 客座率回升，航空运力恢复 | K7: 月度 | L7: 0.1 | M7: 目标组权重 40%；按同组相对重要性归一化。 | N7: 采用5年滚动分位+同比/环比双阈值；数据滞后超过一个频率周期时自动降权。
A8: 4-酒店RevPAR | B8: STR | C8: 380 | D8: 元 | E8: 上行 | F8: 0.0711 | G8: 8 | H8: >400=10分,350-400=8分,300-350=6分,250-300=4分,<250=2分 | I8: 68% | J8: RevPAR回升，酒店经营改善 | K8: 月度 | L8: 0.08 | M8: 目标组权重 40%；按同组相对重要性归一化。 | N8: 采用5年滚动分位+同比/环比双阈值；数据滞后超过一个频率周期时自动降权。
A9: 【第二部分：同步指标（Coincident Indicators）——与当前景气同步变动】
A10: 5-国内旅游人次 | B10: 文旅部 | C10: +22 | D10: %YoY | E10: 上行 | F10: 0.1395 | G10: 8 | H10: >20%=10分,10-20%=8分,5-10%=6分,0-5%=4分,<0%=2分 | I10: 72% | J10: 旅游人次高增，消费场景恢复 | K10: 季度 | L10: 0.15 | M10: 目标组权重 40%；按同组相对重要性归一化。 | N10: 采用5年滚动分位+同比/环比双阈值；数据滞后超过一个频率周期时自动降权。
A11: 6-国内旅游收入 | B11: 文旅部 | C11: +25 | D11: %YoY | E11: 上行 | F11: 0.093 | G11: 8 | H11: >20%=10分,10-20%=8分,5-10%=6分,0-5%=4分,<0%=2分 | I11: 75% | J11: 旅游收入增长，消费升级 | K11: 季度 | L11: 0.1 | M11: 目标组权重 40%；按同组相对重要性归一化。 | N11: 采用季调同比+3个月环比；单月值用3个月移动均值过滤。
A12: 7-餐饮收入增速 | B12: 国家统计局 | C12: +8.5 | D12: %YoY | E12: 上行 | F12: 0.093 | G12: 8 | H12: >10%=10分,5-10%=8分,0-5%=6分,-5-0%=4分,<-5%=2分 | I12: 62% | J12: 餐饮收入回暖，线下消费活跃 | K12: 月度 | L12: 0.1 | M12: 目标组权重 40%；按同组相对重要性归一化。 | N12: 采用季调同比+3个月环比；单月值用3个月移动均值过滤。
A13: 8-电影票房收入 | B13: 猫眼/灯塔 | C13: 42 | D13: 亿元/月 | E13: 上行 | F13: 0.0744 | G13: 6 | H13: >50=10分,40-50=8分,30-40=6分,20-30=4分,<20=2分 | I13: 55% | J13: 票房温和增长，内容供给恢复 | K13: 月度 | L13: 0.08 | M13: 目标组权重 40%；按同组相对重要性归一化。 | N13: 采用季调同比+3个月环比；单月值用3个月移动均值过滤。
A14: 【第三部分：滞后指标（Lagging Indicators）——滞后1-2个季度反映景气变化】
A15: 9-社会服务企业季度净利润 | B15: 上市公司财报 | C15: 15 | D15: 亿元 | E15: 上行 | F15: 0.08 | G15: 6 | H15: >20亿=10分,10-20亿=8分,0-10亿=6分,-10-0亿=4分,<-10亿=2分 | I15: 55% | J15: Q1利润改善，旅游/酒店贡献 | K15: 季度 | L15: 0.1 | M15: 目标组权重 20%；按同组相对重要性归一化。 | N15: 采用TTM/滚动4季同比+历史分位；剔除一次性损益，IRR按项目现金流复核。
A16: 10-社会服务行业毛利率 | B16: 上市公司财报 | C16: 38 | D16: % | E16: 上行 | F16: 0.064 | G16: 6 | H16: >40%=10分,30-40%=8分,20-30%=6分,10-20%=4分,<10%=2分 | I16: 58% | J16: 毛利率改善，成本管控见效 | K16: 季度 | L16: 0.08 | M16: 目标组权重 20%；按同组相对重要性归一化。 | N16: 改为5年滚动分位(P20/P40/P60/P80)+3个月动量；须与库存、价差或利润交叉确认。
A17: 11-服务业PMI | B17: 国家统计局 | C17: 49.6 | D17: 点 | E17: 下行 | F17: 0.056 | G17: 4 | H17: >55=10分,52-55=8分,50-52=6分,48-50=4分,<48=2分 | I17: 35% | J17: 服务业PMI跌破荣枯线，景气回落 | K17: 月度 | L17: 0.07 | M17: 目标组权重 20%；按同组相对重要性归一化。 | N17: 采用5年滚动分位+同比/环比双阈值；数据滞后超过一个频率周期时自动降权。
A18: 行业综合景气度加权得分 | G18: =ROUND(SUMPRODUCT(F5:F17,G5:G17),1) -> 7 | H18: 综合分=Σ(建议权重×单项评分)，建议权重和=100%。

Sheet 综合
A1: 行业景气度量化跟踪体系（参数优化版）— 综合
A2: 默认阶段框架：扩张/订单周期｜先行/同步/滞后=45%/40%/15%。订单、需求和利润三段式确认，避免单一宏观指标主导。｜核心验证：宏观扩散与企业盈利；必选：PMI新订单、社融、政策脉冲
A3: 指标名称 | B3: 数据来源 | C3: 最新数值 | D3: 单位 | E3: 趋势 | F3: 权重 | G3: 评分 (1-10) | H3: 评分阈值说明 | I3: 历史分位 | J3: 对景气度影响 | K3: 跟踪频率 | L3: 原权重 | M3: 参数优化建议 | N3: 评分口径（更新时采用） | O3: 阶段分项 | P3: 公式分数
A4: 【第一部分：先行指标（Leading Indicators）——提前1-2个季度预示景气变化】 | O4: 先行 | P4: =ROUND(SUMPRODUCT(F5:F7,G5:G7)/SUM(F5:F7),1) -> 6.4
A5: 1-宏观经济景气指数 | B5: 国家统计局 | C5: 102 | D5: 点 | E5: 上行 | F5: 0.2 | G5: 6 | H5: >120=10分,110-120=8分,100-110=6分,90-100=4分,<90=2分 | I5: 52% | J5: 景气指数略高于临界，经济温和扩张 | K5: 月度 | L5: 0.2 | M5: 目标组权重 45%；按同组相对重要性归一化。 | N5: 采用5年滚动分位+同比/环比双阈值；数据滞后超过一个频率周期时自动降权。 | O5: 同步 | P5: =ROUND(SUMPRODUCT(F9:F11,G9:G11)/SUM(F9:F11),1) -> 6.7
A6: 2-制造业PMI | B6: 国家统计局 | C6: 50.3 | D6: 点 | E6: 上行 | F6: 0.15 | G6: 6 | H6: >52=10分,50-52=8分,48-50=6分,45-48=4分,<45=2分 | I6: 52% | J6: PMI连续扩张，制造业韧性显现 | K6: 月度 | L6: 0.15 | M6: 目标组权重 45%；按同组相对重要性归一化。 | N6: 采用5年滚动分位+同比/环比双阈值；数据滞后超过一个频率周期时自动降权。 | O6: 滞后 | P6: =ROUND(SUMPRODUCT(F13:F14,G13:G14)/SUM(F13:F14),1) -> 7.2
A7: 3-新增社融规模 | B7: 央行 | C7: 3.8 | D7: 万亿元(累计) | E7: 上行 | F7: 0.1 | G7: 8 | H7: >4=10分,3-4=8分,2-3=6分,1-2=4分,<1=2分 | I7: 58% | J7: 社融稳健增长，信用环境宽松 | K7: 月度 | L7: 0.1 | M7: 目标组权重 45%；按同组相对重要性归一化。 | N7: 采用5年滚动分位+同比/环比双阈值；数据滞后超过一个频率周期时自动降权。
A8: 【第二部分：同步指标（Coincident Indicators）——与当前景气同步变动】
A9: 4-GDP增速 | B9: 国家统计局 | C9: +5.2 | D9: %YoY | E9: 上行 | F9: 0.1778 | G9: 6 | H9: >6%=10分,5-6%=8分,4-5%=6分,3-4%=4分,<3%=2分 | I9: 48% | J9: GDP增速稳健，经济韧性较强 | K9: 季度 | L9: 0.2 | M9: 目标组权重 40%；按同组相对重要性归一化。 | N9: 采用5年滚动分位+同比/环比双阈值；数据滞后超过一个频率周期时自动降权。
A10: 5-工业增加值增速 | B10: 国家统计局 | C10: +6.5 | D10: %YoY | E10: 上行 | F10: 0.1333 | G10: 8 | H10: >6%=10分,5-6%=8分,4-5%=6分,3-4%=4分,<3%=2分 | I10: 58% | J10: 工业生产加快，制造业复苏 | K10: 月度 | L10: 0.15 | M10: 目标组权重 40%；按同组相对重要性归一化。 | N10: 采用5年滚动分位+同比/环比双阈值；数据滞后超过一个频率周期时自动降权。
A11: 6-固定资产投资增速 | B11: 国家统计局 | C11: +4.8 | D11: %YoY | E11: 上行 | F11: 0.0889 | G11: 6 | H11: >8%=10分,5-8%=8分,3-5%=6分,0-3%=4分,<0%=2分 | I11: 48% | J11: 投资增速温和，基建支撑明显 | K11: 月度 | L11: 0.1 | M11: 目标组权重 40%；按同组相对重要性归一化。 | N11: 采用5年滚动分位+同比/环比双阈值；数据滞后超过一个频率周期时自动降权。
A12: 【第三部分：滞后指标（Lagging Indicators）——滞后1-2个季度反映景气变化】
A13: 7-企业盈利增速 | B13: 国家统计局 | C13: +8.5 | D13: %YoY | E13: 上行 | F13: 0.09 | G13: 8 | H13: >10%=10分,5-10%=8分,0-5%=6分,-5-0%=4分,<-5%=2分 | I13: 58% | J13: 企业盈利改善，利润端修复 | K13: 月度 | L13: 0.15 | M13: 目标组权重 15%；按同组相对重要性归一化。 | N13: 采用5年滚动分位+同比/环比双阈值；数据滞后超过一个频率周期时自动降权。
A14: 8-失业率 | B14: 国家统计局 | C14: 5.1 | D14: % | E14: 下行 | F14: 0.06 | G14: 6 | H14: <4.5%=10分,4.5-5.0%=8分,5.0-5.5%=6分,5.5-6.0%=4分,>6.0%=2分 | I14: 55% | J14: 失业率略高，就业压力仍存 | K14: 月度 | L14: 0.1 | M14: 目标组权重 15%；按同组相对重要性归一化。 | N14: 采用5年滚动分位+同比/环比双阈值；数据滞后超过一个频率周期时自动降权。
A15: 行业综合景气度加权得分 | G15: =ROUND(SUMPRODUCT(F5:F14,G5:G14),1) -> 6.6 | H15: 综合分=Σ(建议权重×单项评分)，建议权重和=100%。

Sheet 建筑材料
A1: 行业景气度量化跟踪体系（参数优化版）— 建筑材料
A2: 默认阶段框架：强周期/供给出清｜先行/同步/滞后=50%/35%/15%。先用库存、供给、订单确认反转；价格本身不能直接等同高景气。｜核心验证：地产基建实物量与库存；必选：新开工、基建项目、库存
A3: 指标名称 | B3: 数据来源 | C3: 最新数值 | D3: 单位 | E3: 趋势 | F3: 权重 | G3: 评分 (1-10) | H3: 评分阈值说明 | I3: 历史分位 | J3: 对景气度影响 | K3: 跟踪频率 | L3: 原权重 | M3: 参数优化建议 | N3: 评分口径（更新时采用） | O3: 阶段分项 | P3: 公式分数
A4: 【第一部分：先行指标（Leading Indicators）——提前1-2个季度预示景气变化】 | O4: 先行 | P4: =ROUND(SUMPRODUCT(F5:F8,G5:G8)/SUM(F5:F8),1) -> 4.8
A5: 1-水泥熟料价格 | B5: 数字水泥网 | C5: 320 | D5: 元/吨 | E5: 下行 | F5: 0.15 | G5: 4 | H5: >400=10分,350-400=8分,300-350=6分,250-300=4分,<250=2分 | I5: 32% | J5: 水泥价格低迷，需求端疲软 | K5: 周度 | L5: 0.15 | M5: 目标组权重 50%；按同组相对重要性归一化。 | N5: 改为5年滚动分位(P20/P40/P60/P80)+3个月动量；须与库存、价差或利润交叉确认。 | O5: 同步 | P5: =ROUND(SUMPRODUCT(F10:F13,G10:G13)/SUM(F10:F13),1) -> 4.9
A6: 2-玻璃原片价格 | B6: 卓创资讯 | C6: 1550 | D6: 元/吨 | E6: 下行 | F6: 0.12 | G6: 4 | H6: >1800=10分,1600-1800=8分,1400-1600=6分,1200-1400=4分,<1200=2分 | I6: 35% | J6: 玻璃价格回落，地产需求拖累 | K6: 周度 | L6: 0.12 | M6: 目标组权重 50%；按同组相对重要性归一化。 | N6: 改为5年滚动分位(P20/P40/P60/P80)+3个月动量；须与库存、价差或利润交叉确认。 | O6: 滞后 | P6: =ROUND(SUMPRODUCT(F15:F17,G15:G17)/SUM(F15:F17),1) -> 4
A7: 3-房地产新开工面积增速 | B7: 国家统计局 | C7: -22 | D7: %YoY | E7: 下行 | F7: 0.13 | G7: 4 | H7: >5%=10分,0-5%=8分,-10-0%=6分,-20--10%=4分,<-20%=2分 | I7: 18% | J7: 新开工大幅下滑，需求端收缩 | K7: 月度 | L7: 0.13 | M7: 目标组权重 50%；按同组相对重要性归一化。 | N7: 采用5年滚动分位+同比/环比双阈值；数据滞后超过一个频率周期时自动降权。
A8: 4-基建投资增速 | B8: 国家统计局 | C8: +8.5 | D8: %YoY | E8: 上行 | F8: 0.1 | G8: 8 | H8: >10%=10分,7-10%=8分,5-7%=6分,3-5%=4分,<3%=2分 | I8: 62% | J8: 基建投资发力，对冲地产下滑 | K8: 月度 | L8: 0.1 | M8: 目标组权重 50%；按同组相对重要性归一化。 | N8: 采用5年滚动分位+同比/环比双阈值；数据滞后超过一个频率周期时自动降权。
A9: 【第二部分：同步指标（Coincident Indicators）——与当前景气同步变动】
A10: 5-水泥出货量 | B10: 数字水泥网 | C10: -5.5 | D10: %YoY | E10: 下行 | F10: 0.105 | G10: 4 | H10: >5%=10分,0-5%=8分,-5-0%=6分,-10--5%=4分,<-10%=2分 | I10: 28% | J10: 水泥出货下滑，施工需求不足 | K10: 月度 | L10: 0.12 | M10: 目标组权重 35%；按同组相对重要性归一化。 | N10: 采用季调同比+3个月环比；单月值用3个月移动均值过滤。
A11: 6-玻璃库存天数 | B11: 卓创资讯 | C11: 22 | D11: 天 | E11: 上行 | F11: 0.0875 | G11: 6 | H11: <15天=10分,15-20天=8分,20-25天=6分,25-30天=4分,>30天=2分 | I11: 55% | J11: 玻璃库存累积，供给压力加大 | K11: 周度 | L11: 0.1 | M11: 目标组权重 35%；按同组相对重要性归一化。 | N11: 采用同比、环比、历史分位三维评分；按去库/改善方向计分。
A12: 7-水泥磨机开工率 | B12: 数字水泥网 | C12: 52 | D12: % | E12: 下行 | F12: 0.0875 | G12: 4 | H12: >70%=10分,60-70%=8分,50-60%=6分,40-50%=4分,<40%=2分 | I12: 35% | J12: 开工率低位，产能利用率不足 | K12: 周度 | L12: 0.1 | M12: 目标组权重 35%；按同组相对重要性归一化。 | N12: 采用5年滚动分位+同比/环比双阈值；数据滞后超过一个频率周期时自动降权。
A13: 8-建材出口金额增速 | B13: 海关总署 | C13: +5.5 | D13: %YoY | E13: 上行 | F13: 0.07 | G13: 6 | H13: >10%=10分,5-10%=8分,0-5%=6分,-5-0%=4分,<-5%=2分 | I13: 52% | J13: 建材出口温和增长 | K13: 月度 | L13: 0.08 | M13: 目标组权重 35%；按同组相对重要性归一化。 | N13: 采用5年滚动分位+同比/环比双阈值；数据滞后超过一个频率周期时自动降权。
A14: 【第三部分：滞后指标（Lagging Indicators）——滞后1-2个季度反映景气变化】
A15: 9-建材企业季度净利润 | B15: 上市公司财报 | C15: 8 | D15: 亿元 | E15: 下行 | F15: 0.06 | G15: 4 | H15: >50亿=10分,20-50亿=8分,0-20亿=6分,-20-0亿=4分,<-20亿=2分 | I15: 25% | J15: Q1利润大幅下滑，多数企业亏损 | K15: 季度 | L15: 0.1 | M15: 目标组权重 15%；按同组相对重要性归一化。 | N15: 采用TTM/滚动4季同比+历史分位；剔除一次性损益，IRR按项目现金流复核。
A16: 10-建材行业产能利用率 | B16: 国家统计局 | C16: 68 | D16: % | E16: 下行 | F16: 0.048 | G16: 4 | H16: >80%=10分,75-80%=8分,70-75%=6分,65-70%=4分,<65%=2分 | I16: 32% | J16: 产能利用率低位，产能过剩严重 | K16: 季度 | L16: 0.08 | M16: 目标组权重 15%；按同组相对重要性归一化。 | N16: 采用TTM/滚动4季同比+历史分位；剔除一次性损益，IRR按项目现金流复核。
A17: 11-PPI建材类同比 | B17: 国家统计局 | C17: -1.5 | D17: % | E17: 下行 | F17: 0.042 | G17: 4 | H17: >5%=10分,0-5%=8分,-3-0%=6分,-6--3%=4分,<-6%=2分 | I17: 38% | J17: 建材价格同比下跌，通缩压力 | K17: 月度 | L17: 0.07 | M17: 目标组权重 15%；按同组相对重要性归一化。 | N17: 采用5年滚动分位+同比/环比双阈值；数据滞后超过一个频率周期时自动降权。
A18: 行业综合景气度加权得分 | G18: =ROUND(SUMPRODUCT(F5:F17,G5:G17),1) -> 4.7 | H18: 综合分=Σ(建议权重×单项评分)，建议权重和=100%。

Sheet 建筑装饰
A1: 行业景气度量化跟踪体系（参数优化版）— 建筑装饰
A2: 默认阶段框架：政策资本开支/交付｜先行/同步/滞后=45%/35%/20%。政策与规划只作确认项，必须由招标、交付、回款和利润验证。｜核心验证：财政资金、订单与回款；必选：专项债、项目开工、新签
A3: 指标名称 | B3: 数据来源 | C3: 最新数值 | D3: 单位 | E3: 趋势 | F3: 权重 | G3: 评分 (1-10) | H3: 评分阈值说明 | I3: 历史分位 | J3: 对景气度影响 | K3: 跟踪频率 | L3: 原权重 | M3: 参数优化建议 | N3: 评分口径（更新时采用） | O3: 阶段分项 | P3: 公式分数
A4: 【第一部分：先行指标（Leading Indicators）——提前1-2个季度预示景气变化】 | O4: 先行 | P4: =ROUND(SUMPRODUCT(F5:F8,G5:G8)/SUM(F5:F8),1) -> 7.1
A5: 1-基建投资计划 | B5: 发改委/财政部 | C5: 22 | D5: 万亿元 | E5: 高增 | F5: 0.15 | G5: 8 | H5: >20=10分,15-20=8分,10-15=6分,5-10=4分,<5=2分 | I5: 75% | J5: 基建计划规模创新高，政策发力 | K5: 年度 | L5: 0.15 | M5: 目标组权重 45%；按同组相对重要性归一化。 | N5: 采用5年滚动分位+同比/环比双阈值；数据滞后超过一个频率周期时自动降权。 | O5: 同步 | P5: =ROUND(SUMPRODUCT(F10:F13,G10:G13)/SUM(F10:F13),1) -> 5.3
A6: 2-专项债发行规模 | B6: 财政部 | C6: 4.2 | D6: 万亿元(累计) | E6: 高增 | F6: 0.12 | G6: 8 | H6: >4=10分,3-4=8分,2-3=6分,1-2=4分,<1=2分 | I6: 72% | J6: 专项债发行加速，资金到位改善 | K6: 月度 | L6: 0.12 | M6: 目标组权重 45%；按同组相对重要性归一化。 | N6: 采用5年滚动分位+同比/环比双阈值；数据滞后超过一个频率周期时自动降权。 | O6: 滞后 | P6: =ROUND(SUMPRODUCT(F15:F17,G15:G17)/SUM(F15:F17),1) -> 6
A7: 3-房地产新开工面积增速 | B7: 国家统计局 | C7: -22 | D7: %YoY | E7: 下行 | F7: 0.1 | G7: 4 | H7: >5%=10分,0-5%=8分,-10-0%=6分,-20--10%=4分,<-20%=2分 | I7: 18% | J7: 房建新开工萎缩，房建业务承压 | K7: 月度 | L7: 0.1 | M7: 目标组权重 45%；按同组相对重要性归一化。 | N7: 采用5年滚动分位+同比/环比双阈值；数据滞后超过一个频率周期时自动降权。
A8: 4-钢材价格变化 | B8: 上海钢联 | C8: -3.5 | D8: %YoY | E8: 下行 | F8: 0.08 | G8: 8 | H8: <-5%=10分,-5-0%=8分,0-5%=6分,5-10%=4分,>10%=2分 | I8: 42% | J8: 钢材价格回落，成本端改善 | K8: 周度 | L8: 0.08 | M8: 目标组权重 45%；按同组相对重要性归一化。 | N8: 改为5年滚动分位(P20/P40/P60/P80)+3个月动量；须与库存、价差或利润交叉确认。
A9: 【第二部分：同步指标（Coincident Indicators）——与当前景气同步变动】
A10: 5-建筑业PMI | B10: 国家统计局 | C10: 48.0 | D10: 点 | E10: 下行 | F10: 0.1167 | G10: 4 | H10: >58=10分,55-58=8分,52-55=6分,50-52=4分,<50=2分 | I10: 35% | J10: 建筑业PMI跌破荣枯线，景气回落 | K10: 月度 | L10: 0.15 | M10: 目标组权重 35%；按同组相对重要性归一化。 | N10: 采用5年滚动分位+同比/环比双阈值；数据滞后超过一个频率周期时自动降权。
A11: 6-建筑业新签合同额增速 | B11: 国家统计局 | C11: +3.5 | D11: %YoY | E11: 上行 | F11: 0.0933 | G11: 6 | H11: >10%=10分,5-10%=8分,0-5%=6分,-5-0%=4分,<-5%=2分 | I11: 48% | J11: 新签合同温和增长，基建订单支撑 | K11: 月度 | L11: 0.12 | M11: 目标组权重 35%；按同组相对重要性归一化。 | N11: 采用5年滚动分位+同比/环比双阈值；数据滞后超过一个频率周期时自动降权。
A12: 7-建筑业总产值增速 | B12: 国家统计局 | C12: +4.2 | D12: %YoY | E12: 上行 | F12: 0.0778 | G12: 6 | H12: >8%=10分,5-8%=8分,3-5%=6分,0-3%=4分,<0%=2分 | I12: 48% | J12: 产值增速温和，基建对冲房建 | K12: 月度 | L12: 0.1 | M12: 目标组权重 35%；按同组相对重要性归一化。 | N12: 采用5年滚动分位+同比/环比双阈值；数据滞后超过一个频率周期时自动降权。
A13: 8-建筑企业订单保障倍数 | B13: 上市公司财报 | C13: 1.8 | D13: 倍 | E13: 下行 | F13: 0.0622 | G13: 6 | H13: >2.5=10分,2.0-2.5=8分,1.5-2.0=6分,1.0-1.5=4分,<1.0=2分 | I13: 45% | J13: 订单保障倍数下降，未来收入承压 | K13: 季度 | L13: 0.08 | M13: 目标组权重 35%；按同组相对重要性归一化。 | N13: 滚动3M/4Q同比；以交付、收入或现金流确认，政策/规划单项权重≤8%。
A14: 【第三部分：滞后指标（Lagging Indicators）——滞后1-2个季度反映景气变化】
A15: 9-建筑企业季度净利润 | B15: 上市公司财报 | C15: 45 | D15: 亿元 | E15: 下行 | F15: 0.08 | G15: 6 | H15: >100亿=10分,50-100亿=8分,0-50亿=6分,-50-0亿=4分,<-50亿=2分 | I15: 42% | J15: Q1利润下滑，房建拖累明显 | K15: 季度 | L15: 0.1 | M15: 目标组权重 20%；按同组相对重要性归一化。 | N15: 采用TTM/滚动4季同比+历史分位；剔除一次性损益，IRR按项目现金流复核。
A16: 10-建筑行业资产负债率 | B16: 上市公司财报 | C16: 78 | D16: % | E16: 上行 | F16: 0.064 | G16: 6 | H16: <75%=10分,75-80%=8分,80-85%=6分,85-90%=4分,>90%=2分 | I16: 58% | J16: 负债率偏高，财务风险累积 | K16: 季度 | L16: 0.08 | M16: 目标组权重 20%；按同组相对重要性归一化。 | N16: 采用同比、环比、历史分位三维评分；按去库/改善方向计分。
A17: 11-建筑行业应收账款周转 | B17: 上市公司财报 | C17: 135 | D17: 天 | E17: 上行 | F17: 0.056 | G17: 6 | H17: <90天=10分,90-120天=8分,120-150天=6分,150-180天=4分,>180天=2分 | I17: 55% | J17: 应收账款周转放缓，回款压力加大 | K17: 季度 | L17: 0.07 | M17: 目标组权重 20%；按同组相对重要性归一化。 | N17: 采用同比、环比、历史分位三维评分；按去库/改善方向计分。
A18: 行业综合景气度加权得分 | G18: =ROUND(SUMPRODUCT(F5:F17,G5:G17),1) -> 6.3 | H18: 综合分=Σ(建议权重×单项评分)，建议权重和=100%。

Sheet 电力设备
A1: 行业景气度量化跟踪体系（参数优化版）— 电力设备
A2: 默认阶段框架：政策资本开支/交付｜先行/同步/滞后=45%/35%/20%。政策与规划只作确认项，必须由招标、交付、回款和利润验证。｜核心验证：电网/新能源资本开支与订单；必选：电网投资、招标、海外订单
A3: 指标名称 | B3: 数据来源 | C3: 最新数值 | D3: 单位 | E3: 趋势 | F3: 权重 | G3: 评分 (1-10) | H3: 评分阈值说明 | I3: 历史分位 | J3: 对景气度影响 | K3: 跟踪频率 | L3: 原权重 | M3: 参数优化建议 | N3: 评分口径（更新时采用） | O3: 阶段分项 | P3: 公式分数
A4: 【第一部分：先行指标（Leading Indicators）——提前1-2个季度预示景气变化】 | O4: 先行 | P4: =ROUND(SUMPRODUCT(F5:F9,G5:G9)/SUM(F5:F9),1) -> 8.8
A5: 1-光伏组件价格 | B5: PV InfoLink | C5: 0.82 | D5: 元/W | E5: 下行 | F5: 0.0947 | G5: 8 | H5: <0.8=10分,0.8-1.0=8分,1.0-1.2=6分,1.2-1.4=4分,>1.4=2分 | I5: 25% | J5: 组件价格触底，产业链利润承压 | K5: 周度 | L5: 0.12 | M5: 目标组权重 45%；按同组相对重要性归一化。 | N5: 改为5年滚动分位(P20/P40/P60/P80)+3个月动量；须与库存、价差或利润交叉确认。 | O5: 同步 | P5: =ROUND(SUMPRODUCT(F11:F14,G11:G14)/SUM(F11:F14),1) -> 6.4
A6: 2-硅料价格 | B6: 硅业分会 | C6: 42 | D6: 元/kg | E6: 下行 | F6: 0.0789 | G6: 8 | H6: <40=10分,40-60=8分,60-80=6分,80-100=4分,>100=2分 | I6: 22% | J6: 硅料价格低位，成本端改善 | K6: 周度 | L6: 0.1 | M6: 目标组权重 45%；按同组相对重要性归一化。 | N6: 改为5年滚动分位(P20/P40/P60/P80)+3个月动量；须与库存、价差或利润交叉确认。 | O6: 滞后 | P6: =ROUND(SUMPRODUCT(F16:F18,G16:G18)/SUM(F16:F18),1) -> 5.9
A7: 3-锂电池价格 | B7: SMM | C7: 0.52 | D7: 元/Wh | E7: 下行 | F7: 0.0947 | G7: 8 | H7: <0.5=10分,0.5-0.6=8分,0.6-0.7=6分,0.7-0.8=4分,>0.8=2分 | I7: 28% | J7: 电池价格触底，产业链利润压缩 | K7: 周度 | L7: 0.12 | M7: 目标组权重 45%；按同组相对重要性归一化。 | N7: 改为5年滚动分位(P20/P40/P60/P80)+3个月动量；须与库存、价差或利润交叉确认。
A8: 4-风电招标量 | B8: 金风科技/中国风能协会 | C8: 85 | D8: GW | E8: 高增 | F8: 0.1026 | G8: 10 | H8: >80=10分,60-80=8分,40-60=6分,20-40=4分,<20=2分 | I8: 82% | J8: 风电招标创新高，装机预期强劲 | K8: 季度 | L8: 0.13 | M8: 目标组权重 45%；按同组相对重要性归一化。 | N8: 滚动3M/4Q同比；以交付、收入或现金流确认，政策/规划单项权重≤8%。
A9: 5-电网投资计划 | B9: 国家电网/南方电网 | C9: 6500 | D9: 亿元 | E9: 高增 | F9: 0.0789 | G9: 10 | H9: >6000=10分,5000-6000=8分,4000-5000=6分,3000-4000=4分,<3000=2分 | I9: 85% | J9: 电网投资创新高，特高压建设加速 | K9: 年度 | L9: 0.1 | M9: 目标组权重 45%；按同组相对重要性归一化。 | N9: 采用5年滚动分位+同比/环比双阈值；数据滞后超过一个频率周期时自动降权。
A10: 【第二部分：同步指标（Coincident Indicators）——与当前景气同步变动】
A11: 6-光伏装机量 | B11: 国家能源局 | C11: 65 | D11: GW(累计) | E11: 上行 | F11: 0.1105 | G11: 6 | H11: >100年化=10分,80-100=8分,60-80=6分,40-60=4分,<40=2分 | I11: 55% | J11: 光伏装机稳健，分布式贡献大 | K11: 月度 | L11: 0.12 | M11: 目标组权重 35%；按同组相对重要性归一化。 | N11: 采用季调同比+3个月环比；单月值用3个月移动均值过滤。
A12: 7-风电装机量 | B12: 国家能源局 | C12: 28 | D12: GW(累计) | E12: 上行 | F12: 0.0921 | G12: 6 | H12: >60年化=10分,50-60=8分,40-50=6分,30-40=4分,<30=2分 | I12: 52% | J12: 风电装机平稳，海上风电加速 | K12: 月度 | L12: 0.1 | M12: 目标组权重 35%；按同组相对重要性归一化。 | N12: 采用季调同比+3个月环比；单月值用3个月移动均值过滤。
A13: 8-储能装机量 | B13: CNESA | C13: 18 | D13: GWh(累计) | E13: 上行 | F13: 0.0737 | G13: 6 | H13: >50年化=10分,40-50=8分,30-40=6分,20-30=4分,<20=2分 | I13: 55% | J13: 储能装机高增，工商业储能爆发 | K13: 季度 | L13: 0.08 | M13: 目标组权重 35%；按同组相对重要性归一化。 | N13: 采用季调同比+3个月环比；单月值用3个月移动均值过滤。
A14: 9-电网设备招标量 | B14: 国家电网 | C14: +25 | D14: %YoY | E14: 上行 | F14: 0.0737 | G14: 8 | H14: >20%=10分,10-20%=8分,5-10%=6分,0-5%=4分,<0%=2分 | I14: 70% | J14: 电网设备招标高增，建设提速 | K14: 季度 | L14: 0.08 | M14: 目标组权重 35%；按同组相对重要性归一化。 | N14: 滚动3M/4Q同比；以交付、收入或现金流确认，政策/规划单项权重≤8%。
A15: 【第三部分：滞后指标（Lagging Indicators）——滞后1-2个季度反映景气变化】
A16: 10-电力设备企业季度净利润 | B16: 上市公司财报 | C16: 65 | D16: 亿元 | E16: 下行 | F16: 0.08 | G16: 6 | H16: >80亿=10分,40-80亿=8分,0-40亿=6分,-40-0亿=4分,<-40亿=2分 | I16: 48% | J16: Q1利润分化，光伏承压/风电改善 | K16: 季度 | L16: 0.1 | M16: 目标组权重 20%；按同组相对重要性归一化。 | N16: 采用TTM/滚动4季同比+历史分位；剔除一次性损益，IRR按项目现金流复核。
A17: 11-电力设备行业毛利率 | B17: 上市公司财报 | C17: 18 | D17: % | E17: 下行 | F17: 0.064 | G17: 4 | H17: >25%=10分,20-25%=8分,15-20%=6分,10-15%=4分,<10%=2分 | I17: 38% | J17: 毛利率下滑，价格竞争加剧 | K17: 季度 | L17: 0.08 | M17: 目标组权重 20%；按同组相对重要性归一化。 | N17: 改为5年滚动分位(P20/P40/P60/P80)+3个月动量；须与库存、价差或利润交叉确认。
A18: 12-电力设备出口金额增速 | B18: 海关总署 | C18: +22 | D18: %YoY | E18: 上行 | F18: 0.056 | G18: 8 | H18: >20%=10分,10-20%=8分,5-10%=6分,0-5%=4分,<0%=2分 | I18: 72% | J18: 设备出口强劲，海外需求旺盛 | K18: 月度 | L18: 0.07 | M18: 目标组权重 20%；按同组相对重要性归一化。 | N18: 采用5年滚动分位+同比/环比双阈值；数据滞后超过一个频率周期时自动降权。
A19: 行业综合景气度加权得分 | G19: =ROUND(SUMPRODUCT(F5:F18,G5:G18),1) -> 7.4 | H19: 综合分=Σ(建议权重×单项评分)，建议权重和=100%。

Sheet 国防军工
A1: 行业景气度量化跟踪体系（参数优化版）— 国防军工
A2: 默认阶段框架：政策资本开支/交付｜先行/同步/滞后=45%/35%/20%。政策与规划只作确认项，必须由招标、交付、回款和利润验证。｜核心验证：预算、订单与交付节奏；必选：预算、型号进度、订单/合同负债
A3: 指标名称 | B3: 数据来源 | C3: 最新数值 | D3: 单位 | E3: 趋势 | F3: 权重 | G3: 评分 (1-10) | H3: 评分阈值说明 | I3: 历史分位 | J3: 对景气度影响 | K3: 跟踪频率 | L3: 原权重 | M3: 参数优化建议 | N3: 评分口径（更新时采用） | O3: 阶段分项 | P3: 公式分数
A4: 【第一部分：先行指标（Leading Indicators）——提前1-2个季度预示景气变化】 | O4: 先行 | P4: =ROUND(SUMPRODUCT(F5:F8,G5:G8)/SUM(F5:F8),1) -> 7.2
A5: 1-国防预算增速 | B5: 全国人大 | C5: 7.2 | D5: %YoY | E5: 上行 | F5: 0.1698 | G5: 6 | H5: >8%=10分,6-8%=8分,5-6%=6分,4-5%=4分,<4%=2分 | I5: 55% | J5: 国防预算稳健增长，军品需求确定 | K5: 年度 | L5: 0.2 | M5: 目标组权重 45%；按同组相对重要性归一化。 | N5: 滚动3M/4Q同比；以交付、收入或现金流确认，政策/规划单项权重≤8%。 | O5: 同步 | P5: =ROUND(SUMPRODUCT(F10:F13,G10:G13)/SUM(F10:F13),1) -> 7.7
A6: 2-军工集团订单公告 | B6: 上市公司公告 | C6: 520 | D6: 亿元 | E6: 高增 | F6: 0.1274 | G6: 8 | H6: >500=10分,300-500=8分,100-300=6分,50-100=4分,<50=2分 | I6: 72% | J6: 大额订单密集释放，需求景气确认 | K6: 季度 | L6: 0.15 | M6: 目标组权重 45%；按同组相对重要性归一化。 | N6: 滚动3M/4Q同比；以交付、收入或现金流确认，政策/规划单项权重≤8%。 | O6: 滞后 | P6: =ROUND(SUMPRODUCT(F15:F17,G15:G17)/SUM(F15:F17),1) -> 7.2
A7: 3-军品采购计划 | B7: 全军武器装备采购网 | C7: 1200 | D7: 项 | E7: 高增 | F7: 0.0849 | G7: 8 | H7: >1000=10分,700-1000=8分,400-700=6分,200-400=4分,<200=2分 | I7: 75% | J7: 采购计划饱满，十四五后期冲刺 | K7: 年度 | L7: 0.1 | M7: 目标组权重 45%；按同组相对重要性归一化。 | N7: 采用5年滚动分位+同比/环比双阈值；数据滞后超过一个频率周期时自动降权。
A8: 4-地缘政治风险指数 | B8: 相关智库 | C8: 75 | D8: 点 | E8: 高位 | F8: 0.0679 | G8: 8 | H8: >80=10分,60-80=8分,40-60%=6分,20-40%=4分,<20=2分 | I8: 72% | J8: 地缘风险高位，军品需求刚性 | K8: 月度 | L8: 0.08 | M8: 目标组权重 45%；按同组相对重要性归一化。 | N8: 采用5年滚动分位+同比/环比双阈值；数据滞后超过一个频率周期时自动降权。
A9: 【第二部分：同步指标（Coincident Indicators）——与当前景气同步变动】
A10: 5-军工企业收入增速 | B10: 上市公司财报 | C10: +18.5 | D10: %YoY | E10: 上行 | F10: 0.125 | G10: 8 | H10: >20%=10分,10-20%=8分,5-10%=6分,0-5%=4分,<0%=2分 | I10: 68% | J10: 收入高增长，订单交付加速 | K10: 季度 | L10: 0.15 | M10: 目标组权重 35%；按同组相对重要性归一化。 | N10: 采用季调同比+3个月环比；单月值用3个月移动均值过滤。
A11: 6-军工企业合同负债 | B11: 上市公司财报 | C11: +35 | D11: %YoY | E11: 上行 | F11: 0.1 | G11: 8 | H11: >30%=10分,15-30%=8分,5-15%=6分,0-5%=4分,<0%=2分 | I11: 72% | J11: 合同负债高增，在手订单充裕 | K11: 季度 | L11: 0.12 | M11: 目标组权重 35%；按同组相对重要性归一化。 | N11: 滚动3M/4Q同比；以交付、收入或现金流确认，政策/规划单项权重≤8%。
A12: 7-航空发动机产量 | B12: 航空工业集团 | C12: +15 | D12: %YoY | E12: 上行 | F12: 0.0667 | G12: 8 | H12: >均值20%=10分,0-20%=8分,-10-0%=6分,-20--10%=4分,<-20%=2分 | I12: 65% | J12: 航发产量增长，国产替代加速 | K12: 季度 | L12: 0.08 | M12: 目标组权重 35%；按同组相对重要性归一化。 | N12: 采用季调同比+3个月环比；单月值用3个月移动均值过滤。
A13: 8-舰船下水吨位 | B13: 相关统计 | C13: +12 | D13: %YoY | E13: 上行 | F13: 0.0583 | G13: 6 | H13: >均值20%=10分,0-20%=8分,-10-0%=6分,-20--10%=4分,<-20%=2分 | I13: 58% | J13: 舰船建设稳步推进 | K13: 年度 | L13: 0.07 | M13: 目标组权重 35%；按同组相对重要性归一化。 | N13: 采用5年滚动分位+同比/环比双阈值；数据滞后超过一个频率周期时自动降权。
A14: 【第三部分：滞后指标（Lagging Indicators）——滞后1-2个季度反映景气变化】
A15: 9-军工企业季度净利润 | B15: 上市公司财报 | C15: 38 | D15: 亿元 | E15: 上行 | F15: 0.08 | G15: 6 | H15: >50亿=10分,20-50亿=8分,0-20亿=6分,-20-0亿=4分,<-20亿=2分 | I15: 55% | J15: Q1利润改善，规模效应显现 | K15: 季度 | L15: 0.1 | M15: 目标组权重 20%；按同组相对重要性归一化。 | N15: 采用TTM/滚动4季同比+历史分位；剔除一次性损益，IRR按项目现金流复核。
A16: 10-军工行业研发费用率 | B16: 上市公司财报 | C16: 9.5 | D16: % | E16: 上行 | F16: 0.064 | G16: 8 | H16: >10%=10分,7-10%=8分,4-7%=6分,2-4%=4分,<2%=2分 | I16: 60% | J16: 研发投入维持高位，技术迭代加速 | K16: 季度 | L16: 0.08 | M16: 目标组权重 20%；按同组相对重要性归一化。 | N16: 采用5年滚动分位+同比/环比双阈值；数据滞后超过一个频率周期时自动降权。
A17: 11-军工行业资产负债率 | B17: 上市公司财报 | C17: 48 | D17: % | E17: 下行 | F17: 0.056 | G17: 8 | H17: <50%=10分,50-55%=8分,55-60%=6分,60-65%=4分,>65%=2分 | I17: 42% | J17: 负债率下降，财务结构优化 | K17: 季度 | L17: 0.07 | M17: 目标组权重 20%；按同组相对重要性归一化。 | N17: 采用同比、环比、历史分位三维评分；按去库/改善方向计分。
A18: 行业综合景气度加权得分 | G18: =ROUND(SUMPRODUCT(F5:F17,G5:G17),1) -> 7.4 | H18: 综合分=Σ(建议权重×单项评分)，建议权重和=100%。

Sheet 计算机
A1: 行业景气度量化跟踪体系（参数优化版）— 计算机
A2: 默认阶段框架：科技制造/订单库存周期｜先行/同步/滞后=50%/35%/15%。订单、库存和利用率优先；不同子行业拆分后再汇总。｜核心验证：IT预算、订单和订阅渗透；必选：企业IT预算、云CAPEX、招标
A3: 指标名称 | B3: 数据来源 | C3: 最新数值 | D3: 单位 | E3: 趋势 | F3: 权重 | G3: 评分 (1-10) | H3: 评分阈值说明 | I3: 历史分位 | J3: 对景气度影响 | K3: 跟踪频率 | L3: 原权重 | M3: 参数优化建议 | N3: 评分口径（更新时采用） | O3: 阶段分项 | P3: 公式分数
A4: 【第一部分：先行指标（Leading Indicators）——提前1-2个季度预示景气变化】 | O4: 先行 | P4: =ROUND(SUMPRODUCT(F5:F8,G5:G8)/SUM(F5:F8),1) -> 8.5
A5: 1-全球IT支出增速 | B5: Gartner | C5: +7.5 | D5: %YoY | E5: 上行 | F5: 0.15 | G5: 8 | H5: >8%=10分,5-8%=8分,3-5%=6分,0-3%=4分,<0%=2分 | I5: 62% | J5: IT支出稳健增长，数字化转型加速 | K5: 年度 | L5: 0.15 | M5: 目标组权重 50%；按同组相对重要性归一化。 | N5: 采用5年滚动分位+同比/环比双阈值；数据滞后超过一个频率周期时自动降权。 | O5: 同步 | P5: =ROUND(SUMPRODUCT(F10:F13,G10:G13)/SUM(F10:F13),1) -> 7.6
A6: 2-云计算资本开支 | B6: AWS/Azure/阿里云 | C6: +35 | D6: %YoY | E6: 上行 | F6: 0.12 | G6: 8 | H6: >30%=10分,20-30%=8分,10-20%=6分,0-10%=4分,<0%=2分 | I6: 75% | J6: 云厂商CAPEX高增，AI基建驱动 | K6: 季度 | L6: 0.12 | M6: 目标组权重 50%；按同组相对重要性归一化。 | N6: 采用5年滚动分位+同比/环比双阈值；数据滞后超过一个频率周期时自动降权。 | O6: 滞后 | P6: =ROUND(SUMPRODUCT(F15:F17,G15:G17)/SUM(F15:F17),1) -> 6.6
A7: 3-AI服务器出货量 | B7: IDC | C7: +55 | D7: %YoY | E7: 上行 | F7: 0.13 | G7: 10 | H7: >50%=10分,30-50%=8分,15-30%=6分,0-15%=4分,<0%=2分 | I7: 85% | J7: AI服务器爆发，算力需求井喷 | K7: 季度 | L7: 0.13 | M7: 目标组权重 50%；按同组相对重要性归一化。 | N7: 采用季调同比+3个月环比；单月值用3个月移动均值过滤。
A8: 4-软件业收入增速 | B8: 工信部 | C8: +13.5 | D8: %YoY | E8: 上行 | F8: 0.1 | G8: 8 | H8: >15%=10分,10-15%=8分,5-10%=6分,0-5%=4分,<0%=2分 | I8: 65% | J8: 软件业收入高增，信创/AI驱动 | K8: 月度 | L8: 0.1 | M8: 目标组权重 50%；按同组相对重要性归一化。 | N8: 采用季调同比+3个月环比；单月值用3个月移动均值过滤。
A9: 【第二部分：同步指标（Coincident Indicators）——与当前景气同步变动】
A10: 5-信创采购规模 | B10: 财政部/地方政府 | C10: 1200 | D10: 亿元 | E10: 高增 | F10: 0.105 | G10: 8 | H10: >1000=10分,700-1000=8分,400-700=6分,200-400=4分,<200=2分 | I10: 72% | J10: 信创采购放量，国产替代加速 | K10: 季度 | L10: 0.12 | M10: 目标组权重 35%；按同组相对重要性归一化。 | N10: 采用5年滚动分位+同比/环比双阈值；数据滞后超过一个频率周期时自动降权。
A11: 6-企业SaaS渗透率 | B11: 艾瑞咨询 | C11: 28 | D11: % | E11: 上行 | F11: 0.07 | G11: 6 | H11: >30%=10分,25-30%=8分,20-25%=6分,15-20%=4分,<15%=2分 | I11: 58% | J11: SaaS渗透率提升，企业数字化深化 | K11: 年度 | L11: 0.08 | M11: 目标组权重 35%；按同组相对重要性归一化。 | N11: 采用5年滚动分位+同比/环比双阈值；数据滞后超过一个频率周期时自动降权。
A12: 7-网络安全市场规模 | B12: CCID | C12: +18 | D12: %YoY | E12: 上行 | F12: 0.0875 | G12: 8 | H12: >20%=10分,15-20%=8分,10-15%=6分,5-10%=4分,<5%=2分 | I12: 65% | J12: 网安市场高增，合规需求驱动 | K12: 年度 | L12: 0.1 | M12: 目标组权重 35%；按同组相对重要性归一化。 | N12: 采用5年滚动分位+同比/环比双阈值；数据滞后超过一个频率周期时自动降权。
A13: 8-计算机行业订单增速 | B13: 上市公司财报 | C13: +22 | D13: %YoY | E13: 上行 | F13: 0.0875 | G13: 8 | H13: >20%=10分,10-20%=8分,5-10%=6分,0-5%=4分,<0%=2分 | I13: 70% | J13: 订单高增，AI/信创需求旺盛 | K13: 季度 | L13: 0.1 | M13: 目标组权重 35%；按同组相对重要性归一化。 | N13: 滚动3M/4Q同比；以交付、收入或现金流确认，政策/规划单项权重≤8%。
A14: 【第三部分：滞后指标（Lagging Indicators）——滞后1-2个季度反映景气变化】
A15: 9-计算机企业季度净利润 | B15: 上市公司财报 | C15: 42 | D15: 亿元 | E15: 上行 | F15: 0.06 | G15: 6 | H15: >50亿=10分,20-50亿=8分,0-20亿=6分,-20-0亿=4分,<-20亿=2分 | I15: 55% | J15: Q1利润改善，AI业务贡献 | K15: 季度 | L15: 0.1 | M15: 目标组权重 15%；按同组相对重要性归一化。 | N15: 采用TTM/滚动4季同比+历史分位；剔除一次性损益，IRR按项目现金流复核。
A16: 10-计算机行业毛利率 | B16: 上市公司财报 | C16: 38 | D16: % | E16: 上行 | F16: 0.048 | G16: 6 | H16: >40%=10分,35-40%=8分,30-35%=6分,25-30%=4分,<25%=2分 | I16: 58% | J16: 毛利率改善，高毛利业务占比提升 | K16: 季度 | L16: 0.08 | M16: 目标组权重 15%；按同组相对重要性归一化。 | N16: 改为5年滚动分位(P20/P40/P60/P80)+3个月动量；须与库存、价差或利润交叉确认。
A17: 11-软件从业人员增速 | B17: 工信部 | C17: +8.5 | D17: %YoY | E17: 上行 | F17: 0.042 | G17: 8 | H17: >10%=10分,5-10%=8分,0-5%=6分,-5-0%=4分,<-5%=2分 | I17: 60% | J17: 从业人员增长，行业扩张积极 | K17: 季度 | L17: 0.07 | M17: 目标组权重 15%；按同组相对重要性归一化。 | N17: 采用5年滚动分位+同比/环比双阈值；数据滞后超过一个频率周期时自动降权。
A18: 行业综合景气度加权得分 | G18: =ROUND(SUMPRODUCT(F5:F17,G5:G17),1) -> 7.9 | H18: 综合分=Σ(建议权重×单项评分)，建议权重和=100%。

Sheet 传媒
A1: 行业景气度量化跟踪体系（参数优化版）— 传媒
A2: 默认阶段框架：消费/需求恢复｜先行/同步/滞后=40%/40%/20%。高频需求、渠道库存和价格/利润交叉确认，使用季调数据。｜核心验证：广告预算、内容供给与变现；必选：广告预算、版号、内容排期
A3: 指标名称 | B3: 数据来源 | C3: 最新数值 | D3: 单位 | E3: 趋势 | F3: 权重 | G3: 评分 (1-10) | H3: 评分阈值说明 | I3: 历史分位 | J3: 对景气度影响 | K3: 跟踪频率 | L3: 原权重 | M3: 参数优化建议 | N3: 评分口径（更新时采用） | O3: 阶段分项 | P3: 公式分数
A4: 【第一部分：先行指标（Leading Indicators）——提前1-2个季度预示景气变化】 | O4: 先行 | P4: =ROUND(SUMPRODUCT(F5:F8,G5:G8)/SUM(F5:F8),1) -> 7.2
A5: 1-互联网广告收入增速 | B5: QuestMobile | C5: +16 | D5: %YoY | E5: 上行 | F5: 0.1333 | G5: 8 | H5: >15%=10分,10-15%=8分,5-10%=6分,0-5%=4分,<0%=2分 | I5: 68% | J5: 广告收入高增，AI营销驱动 | K5: 季度 | L5: 0.15 | M5: 目标组权重 40%；按同组相对重要性归一化。 | N5: 采用季调同比+3个月环比；单月值用3个月移动均值过滤。 | O5: 同步 | P5: =ROUND(SUMPRODUCT(F10:F13,G10:G13)/SUM(F10:F13),1) -> 7
A6: 2-游戏版号发放数量 | B6: 国家新闻出版署 | C6: 118 | D6: 个/月 | E6: 高增 | F6: 0.1067 | G6: 8 | H6: >100=10分,80-100=8分,60-80=6分,40-60=4分,<40=2分 | I6: 72% | J6: 版号发放常态化，供给端改善 | K6: 月度 | L6: 0.12 | M6: 目标组权重 40%；按同组相对重要性归一化。 | N6: 滚动3M/4Q同比；以交付、收入或现金流确认，政策/规划单项权重≤8%。 | O6: 滞后 | P6: =ROUND(SUMPRODUCT(F15:F17,G15:G17)/SUM(F15:F17),1) -> 6.6
A7: 3-短视频用户时长 | B7: QuestMobile | C7: +8.5 | D7: %YoY | E7: 上行 | F7: 0.0889 | G7: 6 | H7: >10%=10分,5-10%=8分,0-5%=6分,-5-0%=4分,<-5%=2分 | I7: 60% | J7: 用户时长增长，流量红利持续 | K7: 季度 | L7: 0.1 | M7: 目标组权重 40%；按同组相对重要性归一化。 | N7: 采用5年滚动分位+同比/环比双阈值；数据滞后超过一个频率周期时自动降权。
A8: 4-广告主预算变化 | B8: CTR | C8: +8 | D8: %YoY | E8: 上行 | F8: 0.0711 | G8: 6 | H8: >10%=10分,5-10%=8分,0-5%=6分,-5-0%=4分,<-5%=2分 | I8: 58% | J8: 广告预算回暖，品牌投放恢复 | K8: 季度 | L8: 0.08 | M8: 目标组权重 40%；按同组相对重要性归一化。 | N8: 滚动3M/4Q同比；以交付、收入或现金流确认，政策/规划单项权重≤8%。
A9: 【第二部分：同步指标（Coincident Indicators）——与当前景气同步变动】
A10: 5-游戏市场规模 | B10: 伽马数据 | C10: +16.5 | D10: %YoY | E10: 上行 | F10: 0.12 | G10: 8 | H10: >15%=10分,10-15%=8分,5-10%=6分,0-5%=4分,<0%=2分 | I10: 70% | J10: 游戏市场高增，新品周期+出海 | K10: 季度 | L10: 0.12 | M10: 目标组权重 40%；按同组相对重要性归一化。 | N10: 采用5年滚动分位+同比/环比双阈值；数据滞后超过一个频率周期时自动降权。
A11: 6-电影票房收入 | B11: 猫眼/灯塔 | C11: 38 | D11: 亿元/月 | E11: 上行 | F11: 0.1 | G11: 6 | H11: >50=10分,40-50=8分,30-40=6分,20-30=4分,<20=2分 | I11: 52% | J11: 票房温和复苏，内容供给恢复 | K11: 月度 | L11: 0.1 | M11: 目标组权重 40%；按同组相对重要性归一化。 | N11: 采用季调同比+3个月环比；单月值用3个月移动均值过滤。
A12: 7-在线视频付费用户数 | B12: 爱奇艺/腾讯视频 | C12: 2.85 | D12: 亿人 | E12: 上行 | F12: 0.1 | G12: 6 | H12: >3=10分,2.5-3=8分,2.0-2.5=6分,1.5-2.0=4分,<1.5=2分 | I12: 55% | J12: 付费用户增长，ARPU提升 | K12: 季度 | L12: 0.1 | M12: 目标组权重 40%；按同组相对重要性归一化。 | N12: 采用5年滚动分位+同比/环比双阈值；数据滞后超过一个频率周期时自动降权。
A13: 8-直播电商GMV | B13: 相关统计 | C13: +28 | D13: %YoY | E13: 上行 | F13: 0.08 | G13: 8 | H13: >30%=10分,20-30%=8分,10-20%=6分,0-10%=4分,<0%=2分 | I13: 72% | J13: 直播电商高增，内容电商崛起 | K13: 季度 | L13: 0.08 | M13: 目标组权重 40%；按同组相对重要性归一化。 | N13: 采用5年滚动分位+同比/环比双阈值；数据滞后超过一个频率周期时自动降权。
A14: 【第三部分：滞后指标（Lagging Indicators）——滞后1-2个季度反映景气变化】
A15: 9-传媒企业季度净利润 | B15: 上市公司财报 | C15: 22 | D15: 亿元 | E15: 上行 | F15: 0.08 | G15: 6 | H15: >30亿=10分,15-30亿=8分,0-15亿=6分,-15-0亿=4分,<-15亿=2分 | I15: 55% | J15: Q1利润改善，广告/游戏贡献 | K15: 季度 | L15: 0.1 | M15: 目标组权重 20%；按同组相对重要性归一化。 | N15: 采用TTM/滚动4季同比+历史分位；剔除一次性损益，IRR按项目现金流复核。
A16: 10-传媒行业毛利率 | B16: 上市公司财报 | C16: 42 | D16: % | E16: 上行 | F16: 0.064 | G16: 8 | H16: >40%=10分,30-40%=8分,20-30%=6分,10-20%=4分,<10%=2分 | I16: 65% | J16: 毛利率改善，内容成本优化 | K16: 季度 | L16: 0.08 | M16: 目标组权重 20%；按同组相对重要性归一化。 | N16: 改为5年滚动分位(P20/P40/P60/P80)+3个月动量；须与库存、价差或利润交叉确认。
A17: 11-传媒行业人均产出 | B17: 上市公司财报 | C17: 88 | D17: 万元 | E17: 上行 | F17: 0.056 | G17: 6 | H17: >100=10分,80-100=8分,60-80=6分,40-60=4分,<40=2分 | I17: 58% | J17: 人均产出提升，效率改善 | K17: 年度 | L17: 0.07 | M17: 目标组权重 20%；按同组相对重要性归一化。 | N17: 采用5年滚动分位+同比/环比双阈值；数据滞后超过一个频率周期时自动降权。
A18: 行业综合景气度加权得分 | G18: =ROUND(SUMPRODUCT(F5:F17,G5:G17),1) -> 7 | H18: 综合分=Σ(建议权重×单项评分)，建议权重和=100%。

Sheet 通信
A1: 行业景气度量化跟踪体系（参数优化版）— 通信
A2: 默认阶段框架：科技制造/订单库存周期｜先行/同步/滞后=50%/35%/15%。订单、库存和利用率优先；不同子行业拆分后再汇总。｜核心验证：运营商/云CAPEX与订单；必选：CAPEX计划、光模块/设备订单
A3: 指标名称 | B3: 数据来源 | C3: 最新数值 | D3: 单位 | E3: 趋势 | F3: 权重 | G3: 评分 (1-10) | H3: 评分阈值说明 | I3: 历史分位 | J3: 对景气度影响 | K3: 跟踪频率 | L3: 原权重 | M3: 参数优化建议 | N3: 评分口径（更新时采用） | O3: 阶段分项 | P3: 公式分数
A4: 【第一部分：先行指标（Leading Indicators）——提前1-2个季度预示景气变化】 | O4: 先行 | P4: =ROUND(SUMPRODUCT(F5:F8,G5:G8)/SUM(F5:F8),1) -> 9.5
A5: 1-5G基站建设进度 | B5: 工信部 | C5: 425 | D5: 万个 | E5: 高增 | F5: 0.1667 | G5: 10 | H5: >400=10分,350-400=8分,300-350=6分,250-300=4分,<250=2分 | I5: 88% | J5: 5G基站覆盖完善，网络建设领先 | K5: 季度 | L5: 0.15 | M5: 目标组权重 50%；按同组相对重要性归一化。 | N5: 采用5年滚动分位+同比/环比双阈值；数据滞后超过一个频率周期时自动降权。 | O5: 同步 | P5: =ROUND(SUMPRODUCT(F10:F13,G10:G13)/SUM(F10:F13),1) -> 8.5
A6: 2-运营商资本开支 | B6: 三大运营商 | C6: 3800 | D6: 亿元 | E6: 高增 | F6: 0.1333 | G6: 8 | H6: >3500=10分,3000-3500=8分,2500-3000=6分,2000-2500=4分,<2000=2分 | I6: 72% | J6: 资本开支高增，算力网络投资加大 | K6: 年度 | L6: 0.12 | M6: 目标组权重 50%；按同组相对重要性归一化。 | N6: 采用5年滚动分位+同比/环比双阈值；数据滞后超过一个频率周期时自动降权。 | O6: 滞后 | P6: =ROUND(SUMPRODUCT(F15:F17,G15:G17)/SUM(F15:F17),1) -> 8
A7: 3-光模块出货量 | B7: LightCounting | C7: +45 | D7: %YoY | E7: 上行 | F7: 0.1111 | G7: 10 | H7: >40%=10分,30-40%=8分,20-30%=6分,10-20%=4分,<10%=2分 | I7: 85% | J7: 光模块爆发，AI算力互联需求井喷 | K7: 季度 | L7: 0.1 | M7: 目标组权重 50%；按同组相对重要性归一化。 | N7: 采用季调同比+3个月环比；单月值用3个月移动均值过滤。
A8: 4-数据中心建设规模 | B8: 工信部 | C8: 110 | D8: 万架 | E8: 高增 | F8: 0.0889 | G8: 10 | H8: >100=10分,80-100=8分,60-80=6分,40-60=4分,<40=2分 | I8: 82% | J8: 数据中心建设加速，智算中心爆发 | K8: 年度 | L8: 0.08 | M8: 目标组权重 50%；按同组相对重要性归一化。 | N8: 采用5年滚动分位+同比/环比双阈值；数据滞后超过一个频率周期时自动降权。
A9: 【第二部分：同步指标（Coincident Indicators）——与当前景气同步变动】
A10: 5-移动互联网流量 | B10: 工信部 | C10: +22 | D10: %YoY | E10: 上行 | F10: 0.105 | G10: 8 | H10: >20%=10分,15-20%=8分,10-15%=6分,5-10%=4分,<5%=2分 | I10: 72% | J10: 流量高增，5G应用渗透 | K10: 月度 | L10: 0.12 | M10: 目标组权重 35%；按同组相对重要性归一化。 | N10: 采用5年滚动分位+同比/环比双阈值；数据滞后超过一个频率周期时自动降权。
A11: 6-5G用户数 | B11: 三大运营商 | C11: 10.5 | D11: 亿人 | E11: 高增 | F11: 0.0875 | G11: 10 | H11: >10=10分,8-10=8分,6-8=6分,4-6=4分,<4=2分 | I11: 88% | J11: 5G用户突破10亿，渗透率持续提升 | K11: 月度 | L11: 0.1 | M11: 目标组权重 35%；按同组相对重要性归一化。 | N11: 采用5年滚动分位+同比/环比双阈值；数据滞后超过一个频率周期时自动降权。
A12: 7-电信业务收入 | B12: 工信部 | C12: +7.5 | D12: %YoY | E12: 上行 | F12: 0.0875 | G12: 8 | H12: >8%=10分,5-8%=8分,3-5%=6分,0-3%=4分,<0%=2分 | I12: 62% | J12: 电信收入稳健，新兴业务贡献 | K12: 月度 | L12: 0.1 | M12: 目标组权重 35%；按同组相对重要性归一化。 | N12: 采用季调同比+3个月环比；单月值用3个月移动均值过滤。
A13: 8-通信设备出货量 | B13: 工信部 | C13: +18 | D13: %YoY | E13: 上行 | F13: 0.07 | G13: 8 | H13: >15%=10分,10-15%=8分,5-10%=6分,0-5%=4分,<0%=2分 | I13: 68% | J13: 设备出货高增，5G/算力需求 | K13: 月度 | L13: 0.08 | M13: 目标组权重 35%；按同组相对重要性归一化。 | N13: 采用季调同比+3个月环比；单月值用3个月移动均值过滤。
A14: 【第三部分：滞后指标（Lagging Indicators）——滞后1-2个季度反映景气变化】
A15: 9-通信企业季度净利润 | B15: 上市公司财报 | C15: 125 | D15: 亿元 | E15: 上行 | F15: 0.06 | G15: 8 | H15: >100亿=10分,50-100亿=8分,0-50亿=6分,-50-0亿=4分,<-50亿=2分 | I15: 72% | J15: Q1利润高增，运营商/设备商贡献 | K15: 季度 | L15: 0.1 | M15: 目标组权重 15%；按同组相对重要性归一化。 | N15: 采用TTM/滚动4季同比+历史分位；剔除一次性损益，IRR按项目现金流复核。
A16: 10-通信行业ROE | B16: 上市公司财报 | C16: 9.5 | D16: % | E16: 上行 | F16: 0.048 | G16: 8 | H16: >10%=10分,7-10%=8分,4-7%=6分,1-4%=4分,<1%=2分 | I16: 60% | J16: ROE改善，盈利能力提升 | K16: 季度 | L16: 0.08 | M16: 目标组权重 15%；按同组相对重要性归一化。 | N16: 采用TTM/滚动4季同比+历史分位；剔除一次性损益，IRR按项目现金流复核。
A17: 11-通信行业资产负债率 | B17: 上市公司财报 | C17: 48 | D17: % | E17: 下行 | F17: 0.042 | G17: 8 | H17: <50%=10分,50-55%=8分,55-60%=6分,60-65%=4分,>65%=2分 | I17: 42% | J17: 负债率下降，财务结构优化 | K17: 季度 | L17: 0.07 | M17: 目标组权重 15%；按同组相对重要性归一化。 | N17: 采用同比、环比、历史分位三维评分；按去库/改善方向计分。
A18: 行业综合景气度加权得分 | G18: =ROUND(SUMPRODUCT(F5:F17,G5:G17),1) -> 8.9 | H18: 综合分=Σ(建议权重×单项评分)，建议权重和=100%。

Sheet 银行
A1: 行业景气度量化跟踪体系（参数优化版）— 银行
A2: 默认阶段框架：防御/成熟｜先行/同步/滞后=30%/45%/25%。同步经营和现金流优先；先行指标只作边际变化确认。｜核心验证：信用扩张、息差与资产质量；必选：社融、贷款投放、利率曲线
A3: 指标名称 | B3: 数据来源 | C3: 最新数值 | D3: 单位 | E3: 趋势 | F3: 权重 | G3: 评分 (1-10) | H3: 评分阈值说明 | I3: 历史分位 | J3: 对景气度影响 | K3: 跟踪频率 | L3: 原权重 | M3: 参数优化建议 | N3: 评分口径（更新时采用） | O3: 阶段分项 | P3: 公式分数
A4: 【第一部分：先行指标（Leading Indicators）——提前1-2个季度预示景气变化】 | O4: 先行 | P4: =ROUND(SUMPRODUCT(F5:F8,G5:G8)/SUM(F5:F8),1) -> 8
A5: 1-社融规模增速 | B5: 央行 | C5: +11.5 | D5: %YoY | E5: 上行 | F5: 0.1 | G5: 8 | H5: >12%=10分,10-12%=8分,8-10%=6分,6-8%=4分,<6%=2分 | I5: 58% | J5: 社融稳健增长，信用环境宽松 | K5: 月度 | L5: 0.15 | M5: 目标组权重 30%；按同组相对重要性归一化。 | N5: 采用5年滚动分位+同比/环比双阈值；数据滞后超过一个频率周期时自动降权。 | O5: 同步 | P5: =ROUND(SUMPRODUCT(F10:F13,G10:G13)/SUM(F10:F13),1) -> 6.5
A6: 2-M2增速 | B6: 央行 | C6: +8.8 | D6: %YoY | E6: 上行 | F6: 0.08 | G6: 8 | H6: >10%=10分,8-10%=8分,6-8%=6分,4-6%=4分,<4%=2分 | I6: 55% | J6: M2增速回升，流动性充裕 | K6: 月度 | L6: 0.12 | M6: 目标组权重 30%；按同组相对重要性归一化。 | N6: 采用5年滚动分位+同比/环比双阈值；数据滞后超过一个频率周期时自动降权。 | O6: 滞后 | P6: =ROUND(SUMPRODUCT(F15:F17,G15:G17)/SUM(F15:F17),1) -> 6.6
A7: 3-10年期国债收益率 | B7: 中债登 | C7: 2.35 | D7: % | E7: 下行 | F7: 0.0667 | G7: 8 | H7: 2.5-3.0=10分,2.0-2.5或3.0-3.5=8分,1.5-2.0或3.5-4.0=6分,<1.5或>4.0=4分 | I7: 35% | J7: 利率处于低位，息差承压 | K7: 日度 | L7: 0.1 | M7: 目标组权重 30%；按同组相对重要性归一化。 | N7: 采用5年滚动分位+同比/环比双阈值；数据滞后超过一个频率周期时自动降权。
A8: 4-LPR利率变化 | B8: 央行 | C8: -25 | D8: bp(累计) | E8: 下行 | F8: 0.0533 | G8: 8 | H8: 下调>20bp=10分,下调10-20bp=8分,不变=6分,上调10-20bp=4分,上调>20bp=2分 | I8: 32% | J8: LPR多次下调，刺激信贷需求 | K8: 月度 | L8: 0.08 | M8: 目标组权重 30%；按同组相对重要性归一化。 | N8: 改为5年滚动分位(P20/P40/P60/P80)+3个月动量；须与库存、价差或利润交叉确认。
A9: 【第二部分：同步指标（Coincident Indicators）——与当前景气同步变动】
A10: 5-人民币贷款增速 | B10: 央行 | C10: +10.5 | D10: %YoY | E10: 上行 | F10: 0.1286 | G10: 8 | H10: >12%=10分,10-12%=8分,8-10%=6分,6-8%=4分,<6%=2分 | I10: 55% | J10: 贷款增速稳健，信贷需求恢复 | K10: 月度 | L10: 0.12 | M10: 目标组权重 45%；按同组相对重要性归一化。 | N10: 采用5年滚动分位+同比/环比双阈值；数据滞后超过一个频率周期时自动降权。
A11: 6-净息差(NIM) | B11: 银保监会 | C11: 1.75 | D11: % | E11: 下行 | F11: 0.1286 | G11: 4 | H11: >2.2%=10分,1.9-2.2%=8分,1.6-1.9%=6分,1.3-1.6%=4分,<1.3%=2分 | I11: 25% | J11: 净息差收窄，盈利能力承压 | K11: 季度 | L11: 0.12 | M11: 目标组权重 45%；按同组相对重要性归一化。 | N11: 采用TTM/滚动4季同比+历史分位；剔除一次性损益，IRR按项目现金流复核。
A12: 7-不良贷款率 | B12: 银保监会 | C12: 1.62 | D12: % | E12: 下行 | F12: 0.1071 | G12: 8 | H12: <1.5%=10分,1.5-1.8%=8分,1.8-2.1%=6分,2.1-2.5%=4分,>2.5%=2分 | I12: 48% | J12: 不良率可控，资产质量稳定 | K12: 季度 | L12: 0.1 | M12: 目标组权重 45%；按同组相对重要性归一化。 | N12: 采用同比、环比、历史分位三维评分；按去库/改善方向计分。
A13: 8-银行中间业务收入增速 | B13: 上市公司财报 | C13: +6.5 | D13: %YoY | E13: 上行 | F13: 0.0857 | G13: 6 | H13: >15%=10分,10-15%=8分,5-10%=6分,0-5%=4分,<0%=2分 | I13: 52% | J13: 中收增速温和，财富管理恢复 | K13: 季度 | L13: 0.08 | M13: 目标组权重 45%；按同组相对重要性归一化。 | N13: 采用季调同比+3个月环比；单月值用3个月移动均值过滤。
A14: 【第三部分：滞后指标（Lagging Indicators）——滞后1-2个季度反映景气变化】
A15: 9-银行季度净利润增速 | B15: 上市公司财报 | C15: +3.5 | D15: %YoY | E15: 上行 | F15: 0.1 | G15: 6 | H15: >10%=10分,5-10%=8分,0-5%=6分,-5-0%=4分,<-5%=2分 | I15: 45% | J15: Q1利润正增，但增速放缓 | K15: 季度 | L15: 0.1 | M15: 目标组权重 25%；按同组相对重要性归一化。 | N15: 采用TTM/滚动4季同比+历史分位；剔除一次性损益，IRR按项目现金流复核。
A16: 10-银行ROE | B16: 上市公司财报 | C16: 9.8 | D16: % | E16: 下行 | F16: 0.08 | G16: 6 | H16: >12%=10分,10-12%=8分,8-10%=6分,6-8%=4分,<6%=2分 | I16: 42% | J16: ROE下行，息差收窄拖累 | K16: 季度 | L16: 0.08 | M16: 目标组权重 25%；按同组相对重要性归一化。 | N16: 采用TTM/滚动4季同比+历史分位；剔除一次性损益，IRR按项目现金流复核。
A17: 11-拨备覆盖率 | B17: 银保监会 | C17: 245 | D17: % | E17: 上行 | F17: 0.07 | G17: 8 | H17: >300%=10分,250-300%=8分,200-250%=6分,150-200%=4分,<150%=2分 | I17: 55% | J17: 拨备充足，风险抵补能力强 | K17: 季度 | L17: 0.07 | M17: 目标组权重 25%；按同组相对重要性归一化。 | N17: 采用5年滚动分位+同比/环比双阈值；数据滞后超过一个频率周期时自动降权。
A18: 行业综合景气度加权得分 | G18: =ROUND(SUMPRODUCT(F5:F17,G5:G17),1) -> 7 | H18: 综合分=Σ(建议权重×单项评分)，建议权重和=100%。

Sheet 非银金融
A1: 行业景气度量化跟踪体系（参数优化版）— 非银金融
A2: 默认阶段框架：信用/风险偏好周期｜先行/同步/滞后=35%/45%/20%。信用与资产质量优先；券商、保险、银行不宜混算。｜核心验证：成交活跃、产品发行与投资回报；必选：成交额、两融、基金发行
A3: 指标名称 | B3: 数据来源 | C3: 最新数值 | D3: 单位 | E3: 趋势 | F3: 权重 | G3: 评分 (1-10) | H3: 评分阈值说明 | I3: 历史分位 | J3: 对景气度影响 | K3: 跟踪频率 | L3: 原权重 | M3: 参数优化建议 | N3: 评分口径（更新时采用） | O3: 阶段分项 | P3: 公式分数
A4: 【第一部分：先行指标（Leading Indicators）——提前1-2个季度预示景气变化】 | O4: 先行 | P4: =ROUND(SUMPRODUCT(F5:F8,G5:G8)/SUM(F5:F8),1) -> 7.1
A5: 1-A股日均成交额 | B5: 交易所 | C5: 11800 | D5: 亿元 | E5: 上行 | F5: 0.1167 | G5: 8 | H5: >15000=10分,10000-15000=8分,7000-10000=6分,4000-7000=4分,<4000=2分 | I5: 58% | J5: 成交额回升，市场活跃度改善 | K5: 日度 | L5: 0.15 | M5: 目标组权重 35%；按同组相对重要性归一化。 | N5: 采用5年滚动分位+同比/环比双阈值；数据滞后超过一个频率周期时自动降权。 | O5: 同步 | P5: =ROUND(SUMPRODUCT(F10:F13,G10:G13)/SUM(F10:F13),1) -> 7.1
A6: 2-两融余额变化 | B6: 交易所 | C6: +3.5 | D6: %MoM | E6: 上行 | F6: 0.0933 | G6: 6 | H6: >5%=10分,0-5%=8分,-5-0%=6分,-10--5%=4分,<-10%=2分 | I6: 55% | J6: 两融余额回升，杠杆资金入场 | K6: 月度 | L6: 0.12 | M6: 目标组权重 35%；按同组相对重要性归一化。 | N6: 采用5年滚动分位+同比/环比双阈值；数据滞后超过一个频率周期时自动降权。 | O6: 滞后 | P6: =ROUND(SUMPRODUCT(F15:F17,G15:G17)/SUM(F15:F17),1) -> 7.4
A7: 3-新成立基金规模 | B7: 中基协 | C7: 1850 | D7: 亿元 | E7: 上行 | F7: 0.0778 | G7: 8 | H7: >2000=10分,1500-2000=8分,1000-1500=6分,500-1000=4分,<500=2分 | I7: 62% | J7: 基金发行回暖，居民配置意愿恢复 | K7: 月度 | L7: 0.1 | M7: 目标组权重 35%；按同组相对重要性归一化。 | N7: 采用5年滚动分位+同比/环比双阈值；数据滞后超过一个频率周期时自动降权。
A8: 4-IPO/再融资规模 | B8: 证监会 | C8: 850 | D8: 亿元 | E8: 上行 | F8: 0.0622 | G8: 6 | H8: >1000=10分,700-1000=8分,400-700=6分,200-400=4分,<200=2分 | I8: 52% | J8: IPO再融资温和，投行业务恢复 | K8: 月度 | L8: 0.08 | M8: 目标组权重 35%；按同组相对重要性归一化。 | N8: 滚动3M/4Q同比；以交付、收入或现金流确认，政策/规划单项权重≤8%。
A9: 【第二部分：同步指标（Coincident Indicators）——与当前景气同步变动】
A10: 5-券商经纪业务收入 | B10: 证券业协会 | C10: +15 | D10: %YoY | E10: 上行 | F10: 0.135 | G10: 8 | H10: >20%=10分,10-20%=8分,0-10%=6分,-10-0%=4分,<-10%=2分 | I10: 62% | J10: 经纪收入增长，成交活跃度提升 | K10: 季度 | L10: 0.12 | M10: 目标组权重 45%；按同组相对重要性归一化。 | N10: 采用季调同比+3个月环比；单月值用3个月移动均值过滤。
A11: 6-券商投行业务收入 | B11: 证券业协会 | C11: +8.5 | D11: %YoY | E11: 上行 | F11: 0.1125 | G11: 6 | H11: >15%=10分,5-15%=8分,0-5%=6分,-10-0%=4分,<-10%=2分 | I11: 55% | J11: 投行收入温和增长 | K11: 季度 | L11: 0.1 | M11: 目标组权重 45%；按同组相对重要性归一化。 | N11: 采用季调同比+3个月环比；单月值用3个月移动均值过滤。
A12: 7-保险保费收入增速 | B12: 银保监会 | C12: +8.5 | D12: %YoY | E12: 上行 | F12: 0.1125 | G12: 8 | H12: >10%=10分,5-10%=8分,0-5%=6分,-5-0%=4分,<-5%=2分 | I12: 62% | J12: 保费收入回暖，储蓄型产品热销 | K12: 月度 | L12: 0.1 | M12: 目标组权重 45%；按同组相对重要性归一化。 | N12: 采用季调同比+3个月环比；单月值用3个月移动均值过滤。
A13: 8-保险资金运用收益率 | B13: 银保监会 | C13: 3.8 | D13: % | E13: 上行 | F13: 0.09 | G13: 6 | H13: >5%=10分,3-5%=8分,1-3%=6分,0-1%=4分,<0%=2分 | I13: 52% | J13: 投资收益改善，权益市场回暖 | K13: 季度 | L13: 0.08 | M13: 目标组权重 45%；按同组相对重要性归一化。 | N13: 采用5年滚动分位+同比/环比双阈值；数据滞后超过一个频率周期时自动降权。
A14: 【第三部分：滞后指标（Lagging Indicators）——滞后1-2个季度反映景气变化】
A15: 9-非银企业季度净利润 | B15: 上市公司财报 | C15: 165 | D15: 亿元 | E15: 上行 | F15: 0.08 | G15: 8 | H15: >200亿=10分,100-200亿=8分,0-100亿=6分,-100-0亿=4分,<-100亿=2分 | I15: 60% | J15: Q1利润改善，券商/保险贡献 | K15: 季度 | L15: 0.1 | M15: 目标组权重 20%；按同组相对重要性归一化。 | N15: 采用TTM/滚动4季同比+历史分位；剔除一次性损益，IRR按项目现金流复核。
A16: 10-券商ROE | B16: 上市公司财报 | C16: 6.5 | D16: % | E16: 上行 | F16: 0.064 | G16: 6 | H16: >10%=10分,7-10%=8分,4-7%=6分,1-4%=4分,<1%=2分 | I16: 48% | J16: ROE改善，但绝对水平仍偏低 | K16: 季度 | L16: 0.08 | M16: 目标组权重 20%；按同组相对重要性归一化。 | N16: 采用TTM/滚动4季同比+历史分位；剔除一次性损益，IRR按项目现金流复核。
A17: 11-保险综合偿付能力充足率 | B17: 银保监会 | C17: 225 | D17: % | E17: 上行 | F17: 0.056 | G17: 8 | H17: >250%=10分,200-250%=8分,150-200%=6分,120-150%=4分,<120%=2分 | I17: 55% | J17: 偿付能力充足，风险抵御能力强 | K17: 季度 | L17: 0.07 | M17: 目标组权重 20%；按同组相对重要性归一化。 | N17: 采用5年滚动分位+同比/环比双阈值；数据滞后超过一个频率周期时自动降权。
A18: 行业综合景气度加权得分 | G18: =ROUND(SUMPRODUCT(F5:F17,G5:G17),1) -> 7.2 | H18: 综合分=Σ(建议权重×单项评分)，建议权重和=100%。

Sheet 汽车
A1: 行业景气度量化跟踪体系（参数优化版）— 汽车
A2: 默认阶段框架：消费/需求恢复｜先行/同步/滞后=40%/40%/20%。高频需求、渠道库存和价格/利润交叉确认，使用季调数据。｜核心验证：产品周期、出口与库存；必选：库存系数、新品周期、出口订单
A3: 指标名称 | B3: 数据来源 | C3: 最新数值 | D3: 单位 | E3: 趋势 | F3: 权重 | G3: 评分 (1-10) | H3: 评分阈值说明 | I3: 历史分位 | J3: 对景气度影响 | K3: 跟踪频率 | L3: 原权重 | M3: 参数优化建议 | N3: 评分口径（更新时采用） | O3: 阶段分项 | P3: 公式分数
A4: 【第一部分：先行指标（Leading Indicators）——提前1-2个季度预示景气变化】 | O4: 先行 | P4: =ROUND(SUMPRODUCT(F5:F8,G5:G8)/SUM(F5:F8),1) -> 7.3
A5: 1-汽车经销商库存系数 | B5: 中国汽车流通协会 | C5: 1.55 | E5: 下行 | F5: 0.1333 | G5: 6 | H5: <1.2=10分,1.2-1.5=8分,1.5-1.8=6分,1.8-2.2=4分,>2.2=2分 | I5: 52% | J5: 库存系数回落，去库进展顺利 | K5: 月度 | L5: 0.15 | M5: 目标组权重 40%；按同组相对重要性归一化。 | N5: 采用同比、环比、历史分位三维评分；按去库/改善方向计分。 | O5: 同步 | P5: =ROUND(SUMPRODUCT(F10:F13,G10:G13)/SUM(F10:F13),1) -> 8
A6: 2-新能源汽车渗透率 | B6: 中汽协 | C6: 42.5 | D6: % | E6: 上行 | F6: 0.1067 | G6: 8 | H6: >50%=10分,40-50%=8分,30-40%=6分,20-30%=4分,<20%=2分 | I6: 72% | J6: 渗透率快速提升，电动化加速 | K6: 月度 | L6: 0.12 | M6: 目标组权重 40%；按同组相对重要性归一化。 | N6: 采用5年滚动分位+同比/环比双阈值；数据滞后超过一个频率周期时自动降权。 | O6: 滞后 | P6: =ROUND(SUMPRODUCT(F15:F17,G15:G17)/SUM(F15:F17),1) -> 7.4
A7: 3-动力电池装车量增速 | B7: 中国汽车动力电池产业创新联盟 | C7: +38 | D7: %YoY | E7: 上行 | F7: 0.0889 | G7: 8 | H7: >40%=10分,30-40%=8分,20-30%=6分,10-20%=4分,<10%=2分 | I7: 75% | J7: 电池装车高增，新能源车产销两旺 | K7: 月度 | L7: 0.1 | M7: 目标组权重 40%；按同组相对重要性归一化。 | N7: 采用5年滚动分位+同比/环比双阈值；数据滞后超过一个频率周期时自动降权。
A8: 4-汽车出口量增速 | B8: 海关总署 | C8: +28 | D8: %YoY | E8: 上行 | F8: 0.0711 | G8: 8 | H8: >30%=10分,20-30%=8分,10-20%=6分,0-10%=4分,<0%=2分 | I8: 78% | J8: 汽车出口强劲，全球化加速 | K8: 月度 | L8: 0.08 | M8: 目标组权重 40%；按同组相对重要性归一化。 | N8: 采用5年滚动分位+同比/环比双阈值；数据滞后超过一个频率周期时自动降权。
A9: 【第二部分：同步指标（Coincident Indicators）——与当前景气同步变动】
A10: 5-汽车销量增速 | B10: 中汽协 | C10: +9.5 | D10: %YoY | E10: 上行 | F10: 0.1333 | G10: 8 | H10: >10%=10分,5-10%=8分,0-5%=6分,-5-0%=4分,<-5%=2分 | I10: 62% | J10: 汽车销量稳健增长 | K10: 月度 | L10: 0.15 | M10: 目标组权重 40%；按同组相对重要性归一化。 | N10: 采用季调同比+3个月环比；单月值用3个月移动均值过滤。
A11: 6-新能源汽车销量 | B11: 中汽协 | C11: 88 | D11: 万辆/月 | E11: 上行 | F11: 0.1067 | G11: 8 | H11: >100=10分,80-100=8分,60-80=6分,40-60=4分,<40=2分 | I11: 68% | J11: 新能源车销量高增 | K11: 月度 | L11: 0.12 | M11: 目标组权重 40%；按同组相对重要性归一化。 | N11: 采用季调同比+3个月环比；单月值用3个月移动均值过滤。
A12: 7-乘用车批发量 | B12: 乘联会 | C12: 198 | D12: 万辆/月 | E12: 上行 | F12: 0.0889 | G12: 8 | H12: >200=10分,180-200=8分,160-180=6分,140-160=4分,<140=2分 | I12: 65% | J12: 乘用车批发接近200万，需求旺盛 | K12: 月度 | L12: 0.1 | M12: 目标组权重 40%；按同组相对重要性归一化。 | N12: 采用5年滚动分位+同比/环比双阈值；数据滞后超过一个频率周期时自动降权。
A13: 8-汽车制造业PMI | B13: 国家统计局 | C13: 52.5 | D13: 点 | E13: 上行 | F13: 0.0711 | G13: 8 | H13: >52=10分,50-52=8分,48-50=6分,45-48=4分,<45=2分 | I13: 65% | J13: 制造业PMI扩张，汽车生产活跃 | K13: 月度 | L13: 0.08 | M13: 目标组权重 40%；按同组相对重要性归一化。 | N13: 采用5年滚动分位+同比/环比双阈值；数据滞后超过一个频率周期时自动降权。
A14: 【第三部分：滞后指标（Lagging Indicators）——滞后1-2个季度反映景气变化】
A15: 9-汽车企业季度净利润 | B15: 上市公司财报 | C15: 185 | D15: 亿元 | E15: 上行 | F15: 0.08 | G15: 8 | H15: >200亿=10分,100-200亿=8分,0-100亿=6分,-100-0亿=4分,<-100亿=2分 | I15: 65% | J15: Q1利润高增，出口/新能源贡献 | K15: 季度 | L15: 0.1 | M15: 目标组权重 20%；按同组相对重要性归一化。 | N15: 采用TTM/滚动4季同比+历史分位；剔除一次性损益，IRR按项目现金流复核。
A16: 10-汽车行业产能利用率 | B16: 国家统计局 | C16: 78 | D16: % | E16: 上行 | F16: 0.064 | G16: 6 | H16: >80%=10分,75-80%=8分,70-75%=6分,65-70%=4分,<65%=2分 | I16: 55% | J16: 产能利用率回升，供需改善 | K16: 季度 | L16: 0.08 | M16: 目标组权重 20%；按同组相对重要性归一化。 | N16: 采用TTM/滚动4季同比+历史分位；剔除一次性损益，IRR按项目现金流复核。
A17: 11-汽车制造业固定资产投资 | B17: 国家统计局 | C17: +12.5 | D17: %YoY | E17: 上行 | F17: 0.056 | G17: 8 | H17: >15%=10分,10-15%=8分,5-10%=6分,0-5%=4分,<0%=2分 | I17: 65% | J17: 投资高增，新能源产能扩张 | K17: 季度 | L17: 0.07 | M17: 目标组权重 20%；按同组相对重要性归一化。 | N17: 采用5年滚动分位+同比/环比双阈值；数据滞后超过一个频率周期时自动降权。
A18: 行业综合景气度加权得分 | G18: =ROUND(SUMPRODUCT(F5:F17,G5:G17),1) -> 7.6 | H18: 综合分=Σ(建议权重×单项评分)，建议权重和=100%。

Sheet 机械设备
A1: 行业景气度量化跟踪体系（参数优化版）— 机械设备
A2: 默认阶段框架：科技制造/订单库存周期｜先行/同步/滞后=50%/35%/15%。订单、库存和利用率优先；不同子行业拆分后再汇总。｜核心验证：制造业资本开支、订单与出口；必选：PMI新订单、开工小时、设备订单
A3: 指标名称 | B3: 数据来源 | C3: 最新数值 | D3: 单位 | E3: 趋势 | F3: 权重 | G3: 评分 (1-10) | H3: 评分阈值说明 | I3: 历史分位 | J3: 对景气度影响 | K3: 跟踪频率 | L3: 原权重 | M3: 参数优化建议 | N3: 评分口径（更新时采用） | O3: 阶段分项 | P3: 公式分数
A4: 【第一部分：先行指标（Leading Indicators）——提前1-2个季度预示景气变化】 | O4: 先行 | P4: =ROUND(SUMPRODUCT(F5:F8,G5:G8)/SUM(F5:F8),1) -> 7.5
A5: 1-制造业固定资产投资增速 | B5: 国家统计局 | C5: +9.5 | D5: %YoY | E5: 上行 | F5: 0.1667 | G5: 8 | H5: >10%=10分,7-10%=8分,5-7%=6分,3-5%=4分,<3%=2分 | I5: 65% | J5: 制造业投资高增，设备更新需求 | K5: 月度 | L5: 0.15 | M5: 目标组权重 50%；按同组相对重要性归一化。 | N5: 采用5年滚动分位+同比/环比双阈值；数据滞后超过一个频率周期时自动降权。 | O5: 同步 | P5: =ROUND(SUMPRODUCT(F10:F13,G10:G13)/SUM(F10:F13),1) -> 7.5
A6: 2-挖掘机开工小时数 | B6: 小松 | C6: 108 | D6: 小时/月 | E6: 上行 | F6: 0.1333 | G6: 6 | H6: >120=10分,100-120=8分,80-100=6分,60-80=4分,<60=2分 | I6: 55% | J6: 开工小时回升，施工活跃度改善 | K6: 月度 | L6: 0.12 | M6: 目标组权重 50%；按同组相对重要性归一化。 | N6: 采用5年滚动分位+同比/环比双阈值；数据滞后超过一个频率周期时自动降权。 | O6: 滞后 | P6: =ROUND(SUMPRODUCT(F15:F17,G15:G17)/SUM(F15:F17),1) -> 6
A7: 3-机床订单增速 | B7: 日本机床工业协会 | C7: +15 | D7: %YoY | E7: 上行 | F7: 0.1111 | G7: 8 | H7: >20%=10分,10-20%=8分,0-10%=6分,-10-0%=4分,<-10%=2分 | I7: 62% | J7: 机床订单回暖，制造业复苏 | K7: 月度 | L7: 0.1 | M7: 目标组权重 50%；按同组相对重要性归一化。 | N7: 滚动3M/4Q同比；以交付、收入或现金流确认，政策/规划单项权重≤8%。
A8: 4-工业机器人产量增速 | B8: 国家统计局 | C8: +18.5 | D8: %YoY | E8: 上行 | F8: 0.0889 | G8: 8 | H8: >20%=10分,10-20%=8分,0-10%=6分,-10-0%=4分,<-10%=2分 | I8: 68% | J8: 机器人产量高增，自动化升级加速 | K8: 月度 | L8: 0.08 | M8: 目标组权重 50%；按同组相对重要性归一化。 | N8: 采用季调同比+3个月环比；单月值用3个月移动均值过滤。
A9: 【第二部分：同步指标（Coincident Indicators）——与当前景气同步变动】
A10: 5-挖掘机销量增速 | B10: 中国工程机械工业协会 | C10: +12 | D10: %YoY | E10: 上行 | F10: 0.1105 | G10: 8 | H10: >20%=10分,10-20%=8分,0-10%=6分,-10-0%=4分,<-10%=2分 | I10: 58% | J10: 挖机销量转正，基建/矿山需求 | K10: 月度 | L10: 0.12 | M10: 目标组权重 35%；按同组相对重要性归一化。 | N10: 采用季调同比+3个月环比；单月值用3个月移动均值过滤。
A11: 6-金属切削机床产量 | B11: 国家统计局 | C11: +8.5 | D11: %YoY | E11: 上行 | F11: 0.0921 | G11: 6 | H11: >10%=10分,5-10%=8分,0-5%=6分,-5-0%=4分,<-5%=2分 | I11: 58% | J11: 机床产量回升，高端制造需求 | K11: 月度 | L11: 0.1 | M11: 目标组权重 35%；按同组相对重要性归一化。 | N11: 采用季调同比+3个月环比；单月值用3个月移动均值过滤。
A12: 7-叉车销量增速 | B12: 中国工程机械工业协会 | C12: +12.5 | D12: %YoY | E12: 上行 | F12: 0.0737 | G12: 8 | H12: >15%=10分,10-15%=8分,5-10%=6分,0-5%=4分,<0%=2分 | I12: 62% | J12: 叉车销量高增，物流/仓储需求 | K12: 月度 | L12: 0.08 | M12: 目标组权重 35%；按同组相对重要性归一化。 | N12: 采用季调同比+3个月环比；单月值用3个月移动均值过滤。
A13: 8-机械设备出口增速 | B13: 海关总署 | C13: +16.5 | D13: %YoY | E13: 上行 | F13: 0.0737 | G13: 8 | H13: >15%=10分,10-15%=8分,5-10%=6分,0-5%=4分,<0%=2分 | I13: 68% | J13: 机械出口强劲，海外竞争力提升 | K13: 月度 | L13: 0.08 | M13: 目标组权重 35%；按同组相对重要性归一化。 | N13: 采用5年滚动分位+同比/环比双阈值；数据滞后超过一个频率周期时自动降权。
A14: 【第三部分：滞后指标（Lagging Indicators）——滞后1-2个季度反映景气变化】
A15: 9-机械企业季度净利润 | B15: 上市公司财报 | C15: 55 | D15: 亿元 | E15: 上行 | F15: 0.06 | G15: 6 | H15: >80亿=10分,40-80亿=8分,0-40亿=6分,-40-0亿=4分,<-40亿=2分 | I15: 55% | J15: Q1利润改善，出口/自动化贡献 | K15: 季度 | L15: 0.1 | M15: 目标组权重 15%；按同组相对重要性归一化。 | N15: 采用TTM/滚动4季同比+历史分位；剔除一次性损益，IRR按项目现金流复核。
A16: 10-机械行业毛利率 | B16: 上市公司财报 | C16: 22 | D16: % | E16: 上行 | F16: 0.048 | G16: 6 | H16: >25%=10分,20-25%=8分,15-20%=6分,10-15%=4分,<10%=2分 | I16: 52% | J16: 毛利率改善，成本管控见效 | K16: 季度 | L16: 0.08 | M16: 目标组权重 15%；按同组相对重要性归一化。 | N16: 改为5年滚动分位(P20/P40/P60/P80)+3个月动量；须与库存、价差或利润交叉确认。
A17: 11-机械行业产能利用率 | B17: 国家统计局 | C17: 76 | D17: % | E17: 上行 | F17: 0.042 | G17: 6 | H17: >80%=10分,75-80%=8分,70-75%=6分,65-70%=4分,<65%=2分 | I17: 55% | J17: 产能利用率回升，供需改善 | K17: 季度 | L17: 0.07 | M17: 目标组权重 15%；按同组相对重要性归一化。 | N17: 采用TTM/滚动4季同比+历史分位；剔除一次性损益，IRR按项目现金流复核。
A18: 行业综合景气度加权得分 | G18: =ROUND(SUMPRODUCT(F5:F17,G5:G17),1) -> 7.2 | H18: 综合分=Σ(建议权重×单项评分)，建议权重和=100%。

Sheet 煤炭
A1: 行业景气度量化跟踪体系（参数优化版）— 煤炭
A2: 默认阶段框架：强周期/供给出清｜先行/同步/滞后=50%/35%/15%。先用库存、供给、订单确认反转；价格本身不能直接等同高景气。｜核心验证：日耗/库存与供给约束；必选：日耗、港口/电厂库存、进口、安监
A3: 指标名称 | B3: 数据来源 | C3: 最新数值 | D3: 单位 | E3: 趋势 | F3: 权重 | G3: 评分 (1-10) | H3: 评分阈值说明 | I3: 历史分位 | J3: 对景气度影响 | K3: 跟踪频率 | L3: 原权重 | M3: 参数优化建议 | N3: 评分口径（更新时采用） | O3: 阶段分项 | P3: 公式分数
A4: 【第一部分：先行指标（Leading Indicators）——提前1-2个季度预示景气变化】 | O4: 先行 | P4: =ROUND(SUMPRODUCT(F5:F8,G5:G8)/SUM(F5:F8),1) -> 7.6
A5: 1-动力煤港口库存 | B5: 秦皇岛港 | C5: 520 | D5: 万吨 | E5: 下行 | F5: 0.1667 | G5: 8 | H5: <500=10分,500-600=8分,600-700=6分,700-800=4分,>800=2分 | I5: 42% | J5: 港口库存偏低，供给偏紧 | K5: 周度 | L5: 0.15 | M5: 目标组权重 50%；按同组相对重要性归一化。 | N5: 采用同比、环比、历史分位三维评分；按去库/改善方向计分。 | O5: 同步 | P5: =ROUND(SUMPRODUCT(F10:F13,G10:G13)/SUM(F10:F13),1) -> 7.6
A6: 2-焦煤港口库存 | B6: 京唐港 | C6: 185 | D6: 万吨 | E6: 下行 | F6: 0.1111 | G6: 8 | H6: <200=10分,200-250=8分,250-300=6分,300-350=4分,>350=2分 | I6: 45% | J6: 焦煤库存低位，供给紧张 | K6: 周度 | L6: 0.1 | M6: 目标组权重 50%；按同组相对重要性归一化。 | N6: 采用同比、环比、历史分位三维评分；按去库/改善方向计分。 | O6: 滞后 | P6: =ROUND(SUMPRODUCT(F15:F17,G15:G17)/SUM(F15:F17),1) -> 6.6
A7: 3-电厂日耗煤量 | B7: 六大电厂 | C7: 78 | D7: 万吨 | E7: 上行 | F7: 0.1333 | G7: 8 | H7: >80=10分,70-80=8分,60-70=6分,50-60=4分,<50=2分 | I7: 65% | J7: 日耗高增，夏季用电高峰来临 | K7: 日度 | L7: 0.12 | M7: 目标组权重 50%；按同组相对重要性归一化。 | N7: 采用5年滚动分位+同比/环比双阈值；数据滞后超过一个频率周期时自动降权。
A8: 4-进口煤数量增速 | B8: 海关总署 | C8: +2.5 | D8: %YoY | E8: 上行 | F8: 0.0889 | G8: 6 | H8: <-5%=10分,-5-0%=8分,0-5%=6分,5-10%=4分,>10%=2分 | I8: 52% | J8: 进口煤平稳，国内供给充足 | K8: 月度 | L8: 0.08 | M8: 目标组权重 50%；按同组相对重要性归一化。 | N8: 采用5年滚动分位+同比/环比双阈值；数据滞后超过一个频率周期时自动降权。
A9: 【第二部分：同步指标（Coincident Indicators）——与当前景气同步变动】
A10: 5-动力煤现货价格 | B10: CCI指数 | C10: 860 | D10: 元/吨 | E10: 上行 | F10: 0.128 | G10: 8 | H10: 800-900=10分,700-800或900-1000=8分,600-700或1000-1100=6分,<600或>1100=4分 | I10: 58% | J10: 煤价中枢回升，供需偏紧 | K10: 周度 | L10: 0.15 | M10: 目标组权重 35%；按同组相对重要性归一化。 | N10: 改为5年滚动分位(P20/P40/P60/P80)+3个月动量；须与库存、价差或利润交叉确认。
A11: 6-焦煤现货价格 | B11: CCI指数 | C11: 1950 | D11: 元/吨 | E11: 上行 | F11: 0.0854 | G11: 8 | H11: 1800-2200=10分,1500-1800或2200-2500=8分,1200-1500或2500-2800=6分,<1200或>2800=4分 | I11: 55% | J11: 焦煤价格回升，钢铁需求拉动 | K11: 周度 | L11: 0.1 | M11: 目标组权重 35%；按同组相对重要性归一化。 | N11: 改为5年滚动分位(P20/P40/P60/P80)+3个月动量；须与库存、价差或利润交叉确认。
A12: 7-焦炭价格 | B12: Mysteel | C12: 2350 | D12: 元/吨 | E12: 上行 | F12: 0.0683 | G12: 8 | H12: >2500=10分,2200-2500=8分,1900-2200=6分,1600-1900=4分,<1600=2分 | I12: 58% | J12: 焦炭价格上涨，成本传导顺畅 | K12: 周度 | L12: 0.08 | M12: 目标组权重 35%；按同组相对重要性归一化。 | N12: 改为5年滚动分位(P20/P40/P60/P80)+3个月动量；须与库存、价差或利润交叉确认。
A13: 8-煤炭运价指数 | B13: CBCFI | C13: 950 | D13: 点 | E13: 上行 | F13: 0.0683 | G13: 6 | H13: >1000=10分,800-1000=8分,600-800=6分,400-600=4分,<400=2分 | I13: 55% | J13: 运价回升，煤炭运输活跃 | K13: 周度 | L13: 0.08 | M13: 目标组权重 35%；按同组相对重要性归一化。 | N13: 采用5年滚动分位+同比/环比双阈值；数据滞后超过一个频率周期时自动降权。
A14: 【第三部分：滞后指标（Lagging Indicators）——滞后1-2个季度反映景气变化】
A15: 9-煤炭企业季度净利润 | B15: 上市公司财报 | C15: 285 | D15: 亿元 | E15: 下行 | F15: 0.06 | G15: 6 | H15: >300亿=10分,150-300亿=8分,0-150亿=6分,-150-0亿=4分,<-150亿=2分 | I15: 48% | J15: Q1利润下滑，煤价同比回落 | K15: 季度 | L15: 0.1 | M15: 目标组权重 15%；按同组相对重要性归一化。 | N15: 采用TTM/滚动4季同比+历史分位；剔除一次性损益，IRR按项目现金流复核。
A16: 10-煤炭行业ROE | B16: 上市公司财报 | C16: 12 | D16: % | E16: 下行 | F16: 0.048 | G16: 6 | H16: >15%=10分,10-15%=8分,5-10%=6分,0-5%=4分,<0%=2分 | I16: 48% | J16: ROE回落，但仍处较好水平 | K16: 季度 | L16: 0.08 | M16: 目标组权重 15%；按同组相对重要性归一化。 | N16: 采用TTM/滚动4季同比+历史分位；剔除一次性损益，IRR按项目现金流复核。
A17: 11-煤炭行业资产负债率 | B17: 上市公司财报 | C17: 52 | D17: % | E17: 下行 | F17: 0.042 | G17: 8 | H17: <50%=10分,50-55%=8分,55-60%=6分,60-65%=4分,>65%=2分 | I17: 45% | J17: 负债率下降，现金流充裕 | K17: 季度 | L17: 0.07 | M17: 目标组权重 15%；按同组相对重要性归一化。 | N17: 采用同比、环比、历史分位三维评分；按去库/改善方向计分。
A18: 行业综合景气度加权得分 | G18: =ROUND(SUMPRODUCT(F5:F17,G5:G17),1) -> 7.5 | H18: 综合分=Σ(建议权重×单项评分)，建议权重和=100%。

Sheet 石油石化
A1: 行业景气度量化跟踪体系（参数优化版）— 石油石化
A2: 默认阶段框架：强周期/供给出清｜先行/同步/滞后=50%/35%/15%。先用库存、供给、订单确认反转；价格本身不能直接等同高景气。｜核心验证：全球供需、库存与炼化价差；必选：OPEC、库存、需求预期
A3: 指标名称 | B3: 数据来源 | C3: 最新数值 | D3: 单位 | E3: 趋势 | F3: 权重 | G3: 评分 (1-10) | H3: 评分阈值说明 | I3: 历史分位 | J3: 对景气度影响 | K3: 跟踪频率 | L3: 原权重 | M3: 参数优化建议 | N3: 评分口径（更新时采用） | O3: 阶段分项 | P3: 公式分数
A4: 【第一部分：先行指标（Leading Indicators）——提前1-2个季度预示景气变化】 | O4: 先行 | P4: =ROUND(SUMPRODUCT(F5:F8,G5:G8)/SUM(F5:F8),1) -> 7.6
A5: 1-原油价格(Brent) | B5: ICE | C5: 78 | D5: 美元/桶 | E5: 下行 | F5: 0.1744 | G5: 8 | H5: 70-80=10分,60-70或80-90=8分,50-60或90-100=6分,<50或>100=4分 | I5: 55% | J5: 油价中枢回落，成本压力缓解 | K5: 日度 | L5: 0.15 | M5: 目标组权重 50%；按同组相对重要性归一化。 | N5: 改为5年滚动分位(P20/P40/P60/P80)+3个月动量；须与库存、价差或利润交叉确认。 | O5: 同步 | P5: =ROUND(SUMPRODUCT(F10:F13,G10:G13)/SUM(F10:F13),1) -> 6
A6: 2-OPEC+产量政策 | B6: OPEC | C6: -50 | D6: 万桶/日(减产) | E6: 支撑 | F6: 0.1163 | G6: 8 | H6: 减产>100=10分,减产50-100=8分,不变=6分,增产50-100=4分,增产>100=2分 | I6: 55% | J6: OPEC+维持减产，供给端有支撑 | K6: 月度 | L6: 0.1 | M6: 目标组权重 50%；按同组相对重要性归一化。 | N6: 滚动3M/4Q同比；以交付、收入或现金流确认，政策/规划单项权重≤8%。 | O6: 滞后 | P6: =ROUND(SUMPRODUCT(F15:F17,G15:G17)/SUM(F15:F17),1) -> 6.6
A7: 3-美国原油库存变化 | B7: EIA | C7: -0.8 | D7: %WoW | E7: 去库 | F7: 0.1163 | G7: 8 | H7: <-1%=10分,-1-0%=8分,0-1%=6分,1-2%=4分,>2%=2分 | I7: 42% | J7: 原油库存去化，供需偏紧 | K7: 周度 | L7: 0.1 | M7: 目标组权重 50%；按同组相对重要性归一化。 | N7: 采用同比、环比、历史分位三维评分；按去库/改善方向计分。
A8: 4-全球石油需求预期 | B8: IEA/EIA/OPEC | C8: +1.8 | D8: %YoY | E8: 上行 | F8: 0.093 | G8: 6 | H8: >2%=10分,1-2%=8分,0-1%=6分,-1-0%=4分,<-1%=2分 | I8: 55% | J8: 需求预期温和增长 | K8: 月度 | L8: 0.08 | M8: 目标组权重 50%；按同组相对重要性归一化。 | N8: 采用5年滚动分位+同比/环比双阈值；数据滞后超过一个频率周期时自动降权。
A9: 【第二部分：同步指标（Coincident Indicators）——与当前景气同步变动】
A10: 5-成品油价格 | B10: 发改委 | C10: 7.85 | D10: 元/升 | E10: 上行 | F10: 0.105 | G10: 6 | H10: >8=10分,7-8=8分,6-7=6分,5-6=4分,<5=2分 | I10: 58% | J10: 成品油价格上调，炼化利润改善 | K10: 周度 | L10: 0.12 | M10: 目标组权重 35%；按同组相对重要性归一化。 | N10: 改为5年滚动分位(P20/P40/P60/P80)+3个月动量；须与库存、价差或利润交叉确认。
A11: 6-炼化开工率 | B11: 隆众资讯 | C11: 78 | D11: % | E11: 上行 | F11: 0.0875 | G11: 6 | H11: >80%=10分,75-80%=8分,70-75%=6分,65-70%=4分,<65%=2分 | I11: 55% | J11: 炼化开工回升，需求端改善 | K11: 周度 | L11: 0.1 | M11: 目标组权重 35%；按同组相对重要性归一化。 | N11: 采用5年滚动分位+同比/环比双阈值；数据滞后超过一个频率周期时自动降权。
A12: 7-化工品价差 | B12: 相关统计 | C12: +6 | D12: %vs均值 | E12: 上行 | F12: 0.0875 | G12: 6 | H12: >均值20%=10分,0-20%=8分,-10-0%=6分,-20--10%=4分,<-20%=2分 | I12: 55% | J12: 化工品价差改善，炼化利润修复 | K12: 周度 | L12: 0.1 | M12: 目标组权重 35%；按同组相对重要性归一化。 | N12: 改为5年滚动分位(P20/P40/P60/P80)+3个月动量；须与库存、价差或利润交叉确认。
A13: 8-石油制品出口增速 | B13: 海关总署 | C13: +8.5 | D13: %YoY | E13: 上行 | F13: 0.07 | G13: 6 | H13: >10%=10分,5-10%=8分,0-5%=6分,-5-0%=4分,<-5%=2分 | I13: 58% | J13: 石油制品出口温和增长 | K13: 月度 | L13: 0.08 | M13: 目标组权重 35%；按同组相对重要性归一化。 | N13: 采用5年滚动分位+同比/环比双阈值；数据滞后超过一个频率周期时自动降权。
A14: 【第三部分：滞后指标（Lagging Indicators）——滞后1-2个季度反映景气变化】
A15: 9-石化企业季度净利润 | B15: 上市公司财报 | C15: 385 | D15: 亿元 | E15: 上行 | F15: 0.06 | G15: 6 | H15: >500亿=10分,200-500亿=8分,0-200亿=6分,-200-0亿=4分,<-200亿=2分 | I15: 55% | J15: Q1利润改善，炼化/化工贡献 | K15: 季度 | L15: 0.1 | M15: 目标组权重 15%；按同组相对重要性归一化。 | N15: 采用TTM/滚动4季同比+历史分位；剔除一次性损益，IRR按项目现金流复核。
A16: 10-石化行业ROE | B16: 上市公司财报 | C16: 8.5 | D16: % | E16: 上行 | F16: 0.048 | G16: 6 | H16: >10%=10分,7-10%=8分,4-7%=6分,1-4%=4分,<1%=2分 | I16: 52% | J16: ROE改善，盈利能力回升 | K16: 季度 | L16: 0.08 | M16: 目标组权重 15%；按同组相对重要性归一化。 | N16: 采用TTM/滚动4季同比+历史分位；剔除一次性损益，IRR按项目现金流复核。
A17: 11-PPI石油和天然气开采 | B17: 国家统计局 | C17: +8.5 | D17: % | E17: 上行 | F17: 0.042 | G17: 8 | H17: >10%=10分,5-10%=8分,0-5%=6分,-5-0%=4分,<-5%=2分 | I17: 62% | J17: 价格同比大涨，上游景气度高 | K17: 月度 | L17: 0.07 | M17: 目标组权重 15%；按同组相对重要性归一化。 | N17: 采用5年滚动分位+同比/环比双阈值；数据滞后超过一个频率周期时自动降权。
A18: 行业综合景气度加权得分 | G18: =ROUND(SUMPRODUCT(F5:F17,G5:G17),1) -> 6.9 | H18: 综合分=Σ(建议权重×单项评分)，建议权重和=100%。

Sheet 环保
A1: 行业景气度量化跟踪体系（参数优化版）— 环保
A2: 默认阶段框架：政策资本开支/交付｜先行/同步/滞后=45%/35%/20%。政策与规划只作确认项，必须由招标、交付、回款和利润验证。｜核心验证：财政支付、订单与回款；必选：财政预算、项目订单、政策落地
A3: 指标名称 | B3: 数据来源 | C3: 最新数值 | D3: 单位 | E3: 趋势 | F3: 权重 | G3: 评分 (1-10) | H3: 评分阈值说明 | I3: 历史分位 | J3: 对景气度影响 | K3: 跟踪频率 | L3: 原权重 | M3: 参数优化建议 | N3: 评分口径（更新时采用） | O3: 阶段分项 | P3: 公式分数
A4: 【第一部分：先行指标（Leading Indicators）——提前1-2个季度预示景气变化】 | O4: 先行 | P4: =ROUND(SUMPRODUCT(F5:F8,G5:G8)/SUM(F5:F8),1) -> 8
A5: 1-环保固定资产投资计划 | B5: 发改委 | C5: 5200 | D5: 亿元 | E5: 高增 | F5: 0.15 | G5: 8 | H5: >5000=10分,4000-5000=8分,3000-4000=6分,2000-3000=4分,<2000=2分 | I5: 72% | J5: 环保投资计划饱满，政策驱动 | K5: 年度 | L5: 0.15 | M5: 目标组权重 45%；按同组相对重要性归一化。 | N5: 采用5年滚动分位+同比/环比双阈值；数据滞后超过一个频率周期时自动降权。 | O5: 同步 | P5: =ROUND(SUMPRODUCT(F10:F13,G10:G13)/SUM(F10:F13),1) -> 6.5
A6: 2-环保政策发布数量 | B6: 生态环境部 | C6: 42 | D6: 项/年 | E6: 高增 | F6: 0.1 | G6: 8 | H6: >50=10分,40-50=8分,30-40=6分,20-30=4分,<20=2分 | I6: 65% | J6: 政策发布密集，监管趋严 | K6: 年度 | L6: 0.1 | M6: 目标组权重 45%；按同组相对重要性归一化。 | N6: 滚动3M/4Q同比；以交付、收入或现金流确认，政策/规划单项权重≤8%。 | O6: 滞后 | P6: =ROUND(SUMPRODUCT(F15:F17,G15:G17)/SUM(F15:F17),1) -> 6
A7: 3-碳交易价格 | B7: 全国碳市场 | C7: 85 | D7: 元/吨 | E7: 上行 | F7: 0.12 | G7: 8 | H7: >100=10分,80-100=8分,60-80=6分,40-60=4分,<40=2分 | I7: 68% | J7: 碳价回升，碳资产价值提升 | K7: 月度 | L7: 0.12 | M7: 目标组权重 45%；按同组相对重要性归一化。 | N7: 改为5年滚动分位(P20/P40/P60/P80)+3个月动量；须与库存、价差或利润交叉确认。
A8: 4-地方政府环保支出 | B8: 财政部 | C8: +8.5 | D8: %YoY | E8: 上行 | F8: 0.08 | G8: 8 | H8: >10%=10分,5-10%=8分,0-5%=6分,-5-0%=4分,<-5%=2分 | I8: 62% | J8: 环保支出增长，财政支持力度加大 | K8: 年度 | L8: 0.08 | M8: 目标组权重 45%；按同组相对重要性归一化。 | N8: 采用5年滚动分位+同比/环比双阈值；数据滞后超过一个频率周期时自动降权。
A9: 【第二部分：同步指标（Coincident Indicators）——与当前景气同步变动】
A10: 5-污水处理量 | B10: 住建部 | C10: +4.5 | D10: %YoY | E10: 上行 | F10: 0.105 | G10: 6 | H10: >5%=10分,3-5%=8分,0-3%=6分,-3-0%=4分,<-3%=2分 | I10: 55% | J10: 污水处理量增长，运营业务稳定 | K10: 月度 | L10: 0.12 | M10: 目标组权重 35%；按同组相对重要性归一化。 | N10: 采用5年滚动分位+同比/环比双阈值；数据滞后超过一个频率周期时自动降权。
A11: 6-垃圾处理量 | B11: 住建部 | C11: +5.2 | D11: %YoY | E11: 上行 | F11: 0.0875 | G11: 6 | H11: >5%=10分,3-5%=8分,0-3%=6分,-3-0%=4分,<-3%=2分 | I11: 58% | J11: 垃圾处理量增长，焚烧发电需求 | K11: 月度 | L11: 0.1 | M11: 目标组权重 35%；按同组相对重要性归一化。 | N11: 采用5年滚动分位+同比/环比双阈值；数据滞后超过一个频率周期时自动降权。
A12: 7-环保企业订单金额 | B12: 上市公司公告 | C12: +18.5 | D12: %YoY | E12: 上行 | F12: 0.0875 | G12: 8 | H12: >20%=10分,10-20%=8分,5-10%=6分,0-5%=4分,<0%=2分 | I12: 65% | J12: 订单高增，水/固废治理需求 | K12: 季度 | L12: 0.1 | M12: 目标组权重 35%；按同组相对重要性归一化。 | N12: 滚动3M/4Q同比；以交付、收入或现金流确认，政策/规划单项权重≤8%。
A13: 8-环保设备产量 | B13: 国家统计局 | C13: +8.5 | D13: %YoY | E13: 上行 | F13: 0.07 | G13: 6 | H13: >10%=10分,5-10%=8分,0-5%=6分,-5-0%=4分,<-5%=2分 | I13: 58% | J13: 设备产量增长，更新需求释放 | K13: 月度 | L13: 0.08 | M13: 目标组权重 35%；按同组相对重要性归一化。 | N13: 采用季调同比+3个月环比；单月值用3个月移动均值过滤。
A14: 【第三部分：滞后指标（Lagging Indicators）——滞后1-2个季度反映景气变化】
A15: 9-环保企业季度净利润 | B15: 上市公司财报 | C15: 22 | D15: 亿元 | E15: 上行 | F15: 0.08 | G15: 6 | H15: >30亿=10分,15-30亿=8分,0-15亿=6分,-15-0亿=4分,<-15亿=2分 | I15: 52% | J15: Q1利润改善，运营业务贡献 | K15: 季度 | L15: 0.1 | M15: 目标组权重 20%；按同组相对重要性归一化。 | N15: 采用TTM/滚动4季同比+历史分位；剔除一次性损益，IRR按项目现金流复核。
A16: 10-环保行业毛利率 | B16: 上市公司财报 | C16: 28 | D16: % | E16: 上行 | F16: 0.064 | G16: 6 | H16: >30%=10分,25-30%=8分,20-25%=6分,15-20%=4分,<15%=2分 | I16: 52% | J16: 毛利率改善，运营占比提升 | K16: 季度 | L16: 0.08 | M16: 目标组权重 20%；按同组相对重要性归一化。 | N16: 改为5年滚动分位(P20/P40/P60/P80)+3个月动量；须与库存、价差或利润交叉确认。
A17: 11-环保行业应收账款周转 | B17: 上市公司财报 | C17: 135 | D17: 天 | E17: 上行 | F17: 0.056 | G17: 6 | H17: <120天=10分,120-150天=8分,150-180天=6分,180-210天=4分,>210天=2分 | I17: 55% | J17: 应收账款周转放缓，回款压力仍存 | K17: 季度 | L17: 0.07 | M17: 目标组权重 20%；按同组相对重要性归一化。 | N17: 采用同比、环比、历史分位三维评分；按去库/改善方向计分。
A18: 行业综合景气度加权得分 | G18: =ROUND(SUMPRODUCT(F5:F17,G5:G17),1) -> 7.1 | H18: 综合分=Σ(建议权重×单项评分)，建议权重和=100%。

Sheet 美容护理
A1: 行业景气度量化跟踪体系（参数优化版）— 美容护理
A2: 默认阶段框架：消费/需求恢复｜先行/同步/滞后=40%/40%/20%。高频需求、渠道库存和价格/利润交叉确认，使用季调数据。｜核心验证：品牌渗透、渠道效率与复购；必选：内容转化、渠道库存、消费信心
A3: 指标名称 | B3: 数据来源 | C3: 最新数值 | D3: 单位 | E3: 趋势 | F3: 权重 | G3: 评分 (1-10) | H3: 评分阈值说明 | I3: 历史分位 | J3: 对景气度影响 | K3: 跟踪频率 | L3: 原权重 | M3: 参数优化建议 | N3: 评分口径（更新时采用） | O3: 阶段分项 | P3: 公式分数
A4: 【第一部分：先行指标（Leading Indicators）——提前1-2个季度预示景气变化】 | O4: 先行 | P4: =ROUND(SUMPRODUCT(F5:F8,G5:G8)/SUM(F5:F8),1) -> 5.8
A5: 1-居民人均可支配收入增速 | B5: 国家统计局 | C5: +5.8 | D5: %YoY | E5: 上行 | F5: 0.1333 | G5: 6 | H5: >8%=10分,6-8%=8分,4-6%=6分,2-4%=4分,<2%=2分 | I5: 48% | J5: 收入增速放缓，高端消费承压 | K5: 季度 | L5: 0.15 | M5: 目标组权重 40%；按同组相对重要性归一化。 | N5: 采用季调同比+3个月环比；单月值用3个月移动均值过滤。 | O5: 同步 | P5: =ROUND(SUMPRODUCT(F10:F13,G10:G13)/SUM(F10:F13),1) -> 7.6
A6: 2-化妆品进口金额增速 | B6: 海关总署 | C6: +6.5 | D6: %YoY | E6: 上行 | F6: 0.0889 | G6: 6 | H6: >10%=10分,5-10%=8分,0-5%=6分,-5-0%=4分,<-5%=2分 | I6: 55% | J6: 进口化妆品增长，消费升级 | K6: 月度 | L6: 0.1 | M6: 目标组权重 40%；按同组相对重要性归一化。 | N6: 采用5年滚动分位+同比/环比双阈值；数据滞后超过一个频率周期时自动降权。 | O6: 滞后 | P6: =ROUND(SUMPRODUCT(F15:F17,G15:G17)/SUM(F15:F17),1) -> 7.2
A7: 3-消费者信心指数 | B7: 国家统计局 | C7: 88 | D7: 点 | E7: 下行 | F7: 0.1067 | G7: 4 | H7: >120=10分,110-120=8分,100-110=6分,90-100=4分,<90=2分 | I7: 25% | J7: 信心指数低迷，可选消费承压 | K7: 月度 | L7: 0.12 | M7: 目标组权重 40%；按同组相对重要性归一化。 | N7: 采用5年滚动分位+同比/环比双阈值；数据滞后超过一个频率周期时自动降权。
A8: 4-社交媒体美妆话题热度 | B8: 相关平台 | C8: +15 | D8: %YoY | E8: 上行 | F8: 0.0711 | G8: 8 | H8: >20%=10分,10-20%=8分,0-10%=6分,-10-0%=4分,<-10%=2分 | I8: 62% | J8: 社媒热度高增，内容营销活跃 | K8: 月度 | L8: 0.08 | M8: 目标组权重 40%；按同组相对重要性归一化。 | N8: 采用5年滚动分位+同比/环比双阈值；数据滞后超过一个频率周期时自动降权。
A9: 【第二部分：同步指标（Coincident Indicators）——与当前景气同步变动】
A10: 5-化妆品零售额增速 | B10: 国家统计局 | C10: +8.5 | D10: %YoY | E10: 上行 | F10: 0.1463 | G10: 8 | H10: >15%=10分,10-15%=8分,5-10%=6分,0-5%=4分,<0%=2分 | I10: 58% | J10: 化妆品零售回暖，国货崛起 | K10: 月度 | L10: 0.15 | M10: 目标组权重 40%；按同组相对重要性归一化。 | N10: 采用季调同比+3个月环比；单月值用3个月移动均值过滤。
A11: 6-医美市场规模 | B11: 艾瑞咨询 | C11: +18 | D11: %YoY | E11: 上行 | F11: 0.0976 | G11: 8 | H11: >20%=10分,15-20%=8分,10-15%=6分,5-10%=4分,<5%=2分 | I11: 68% | J11: 医美市场高增，渗透率提升 | K11: 年度 | L11: 0.1 | M11: 目标组权重 40%；按同组相对重要性归一化。 | N11: 采用5年滚动分位+同比/环比双阈值；数据滞后超过一个频率周期时自动降权。
A12: 7-个护用品产量 | B12: 国家统计局 | C12: +6.5 | D12: %YoY | E12: 上行 | F12: 0.078 | G12: 6 | H12: >10%=10分,5-10%=8分,0-5%=6分,-5-0%=4分,<-5%=2分 | I12: 55% | J12: 个护产量增长，基础需求稳定 | K12: 月度 | L12: 0.08 | M12: 目标组权重 40%；按同组相对重要性归一化。 | N12: 采用季调同比+3个月环比；单月值用3个月移动均值过滤。
A13: 8-美容护理线上销售额 | B13: 魔镜/欧特欧 | C13: +18.5 | D13: %YoY | E13: 上行 | F13: 0.078 | G13: 8 | H13: >20%=10分,15-20%=8分,10-15%=6分,5-10%=4分,<5%=2分 | I13: 68% | J13: 线上销售高增，渠道红利持续 | K13: 月度 | L13: 0.08 | M13: 目标组权重 40%；按同组相对重要性归一化。 | N13: 采用5年滚动分位+同比/环比双阈值；数据滞后超过一个频率周期时自动降权。
A14: 【第三部分：滞后指标（Lagging Indicators）——滞后1-2个季度反映景气变化】
A15: 9-美容护理企业季度净利润 | B15: 上市公司财报 | C15: 12 | D15: 亿元 | E15: 上行 | F15: 0.08 | G15: 6 | H15: >20亿=10分,10-20亿=8分,0-10亿=6分,-10-0亿=4分,<-10亿=2分 | I15: 52% | J15: Q1利润改善，国货品牌贡献 | K15: 季度 | L15: 0.1 | M15: 目标组权重 20%；按同组相对重要性归一化。 | N15: 采用TTM/滚动4季同比+历史分位；剔除一次性损益，IRR按项目现金流复核。
A16: 10-美容护理行业毛利率 | B16: 上市公司财报 | C16: 62 | D16: % | E16: 上行 | F16: 0.064 | G16: 8 | H16: >60%=10分,50-60%=8分,40-50%=6分,30-40%=4分,<30%=2分 | I16: 72% | J16: 毛利率高位，品牌溢价能力强 | K16: 季度 | L16: 0.08 | M16: 目标组权重 20%；按同组相对重要性归一化。 | N16: 改为5年滚动分位(P20/P40/P60/P80)+3个月动量；须与库存、价差或利润交叉确认。
A17: 11-美容护理行业销售费用率 | B17: 上市公司财报 | C17: 32 | D17: % | E17: 下行 | F17: 0.056 | G17: 8 | H17: <30%=10分,30-40%=8分,40-50%=6分,50-60%=4分,>60%=2分 | I17: 55% | J17: 费用率下降，品牌效率提升 | K17: 季度 | L17: 0.07 | M17: 目标组权重 20%；按同组相对重要性归一化。 | N17: 采用5年滚动分位+同比/环比双阈值；数据滞后超过一个频率周期时自动降权。
A18: 行业综合景气度加权得分 | G18: =ROUND(SUMPRODUCT(F5:F17,G5:G17),1) -> 6.8 | H18: 综合分=Σ(建议权重×单项评分)，建议权重和=100%。

Sheet 半导体
A1: 行业景气度量化跟踪体系（参数优化版）— 半导体
A2: 默认阶段框架：科技制造/订单库存周期｜先行/同步/滞后=50%/35%/15%。订单、库存和利用率优先；不同子行业拆分后再汇总。｜核心验证：库存周期、供给约束与订单；必选：库存、存储价格、订单、CAPEX
A3: 指标名称 | B3: 数据来源 | C3: 最新数值 | D3: 单位 | E3: 趋势 | F3: 权重 | G3: 评分 (1-10) | H3: 评分阈值说明 | I3: 历史分位 | J3: 对景气度影响 | K3: 跟踪频率 | L3: 原权重 | M3: 参数优化建议 | N3: 评分口径（更新时采用） | O3: 阶段分项 | P3: 公式分数
A4: 【第一部分：先行指标（Leading Indicators）——提前1-2个季度预示景气变化】 | O4: 先行 | P4: =ROUND(SUMPRODUCT(F5:F12,G5:G12)/SUM(F5:F12),1) -> 8
A5: 1-全球半导体销售额增速 | B5: SIA/WSTS | C5: +18.5 | D5: %YoY | E5: 上行 | F5: 0.075 | G5: 8 | H5: >20%=10分,10-20%=8分,5-10%=6分,0-5%=4分,<0%=2分 | I5: 75% | J5: 半导体周期强劲复苏，AI需求驱动 | K5: 月度 | L5: 0.15 | M5: 目标组权重 50%；按同组相对重要性归一化。 | N5: 采用5年滚动分位+同比/环比双阈值；数据滞后超过一个频率周期时自动降权。 | O5: 同步 | P5: =ROUND(SUMPRODUCT(F14:F17,G14:G17)/SUM(F14:F17),1) -> 7.6
A6: 2-存储芯片价格变化(DRAM/NAND) | B6: DRAMeXchange | C6: +22 | D6: %MoM | E6: 大涨 | F6: 0.06 | G6: 9 | H6: 涨价>10%=10分,涨价5-10%=8分,持平=5分,跌价5-10%=3分,跌价>10%=1分 | I6: 82% | J6: 存储超级周期，HBM需求爆发 | K6: 周度 | L6: 0.12 | M6: 目标组权重 50%；按同组相对重要性归一化。 | N6: 改为5年滚动分位(P20/P40/P60/P80)+3个月动量；须与库存、价差或利润交叉确认。 | O6: 滞后 | P6: =ROUND(SUMPRODUCT(F19:F21,G19:G21)/SUM(F19:F21),1) -> 8.6
A7: 3-硅片出货量增速 | B7: SEMI | C7: +15.2 | D7: %YoY | E7: 上行 | F7: 0.05 | G7: 7 | H7: >30%=10分,20-30%=8分,10-20%=6分,0-10%=4分,<0%=2分 | I7: 68% | J7: 硅片需求回暖，晶圆厂扩产 | K7: 季度 | L7: 0.1 | M7: 目标组权重 50%；按同组相对重要性归一化。 | N7: 采用季调同比+3个月环比；单月值用3个月移动均值过滤。
A8: 4-设备商订单增速(应用材料/ASML) | B8: 公司财报 | C8: +28 | D8: %YoY | E8: 上行 | F8: 0.065 | G8: 8 | H8: >40%=10分,20-40%=8分,10-20%=6分,0-10%=4分,<0%=2分 | I8: 72% | J8: 设备订单高增，扩产周期确认 | K8: 季度 | L8: 0.13 | M8: 目标组权重 50%；按同组相对重要性归一化。 | N8: 滚动3M/4Q同比；以交付、收入或现金流确认，政策/规划单项权重≤8%。
A9: 5-下游客户库存周转天数 | B9: 下游公司财报 | C9: 58 | D9: 天 | E9: 去库完成 | F9: 0.06 | G9: 9 | H9: 去库完成<60天=10分,去库中60-80天=7分,高位80-100天=4分,补库初期100-120天=6分,补库后期>120天=3分 | I9: 35% | J9: 库存去化完成，补库周期即将启动 | K9: 季度 | L9: 0.12 | M9: 目标组权重 50%；按同组相对重要性归一化。 | N9: 采用同比、环比、历史分位三维评分；按去库/改善方向计分。
A10: 6-龙头企业资本开支增速 | B10: 中芯/台积电财报 | C10: +15 | D10: %YoY | E10: 上行 | F10: 0.065 | G10: 6 | H10: >50%=10分,30-50%=8分,10-30%=6分,0-10%=4分,<0%=2分 | I10: 58% | J10: 资本开支增长，但增速放缓 | K10: 季度 | L10: 0.13 | M10: 目标组权重 50%；按同组相对重要性归一化。 | N10: 采用5年滚动分位+同比/环比双阈值；数据滞后超过一个频率周期时自动降权。
A11: 7-新签订单/合同负债增速 | B11: 设备/材料商财报 | C11: +45 | D11: %YoY | E11: 爆发 | F11: 0.06 | G11: 9 | H11: >50%=10分,30-50%=8分,10-30%=6分,0-10%=4分,<0%=2分 | I11: 85% | J11: 订单爆发，设备/材料商景气确认 | K11: 季度 | L11: 0.12 | M11: 目标组权重 50%；按同组相对重要性归一化。 | N11: 滚动3M/4Q同比；以交付、收入或现金流确认，政策/规划单项权重≤8%。
A12: 8-进口替代进度(国产化率提升) | B12: 产业调研 | C12: +5.2 | D12: pct | E12: 加速 | F12: 0.065 | G12: 8 | H12: 提升>10pct=10分,提升5-10pct=8分,提升2-5pct=6分,持平=4分,下降=2分 | I12: 65% | J12: 国产替代加速，设备/材料突破 | K12: 半年度 | L12: 0.13 | M12: 目标组权重 50%；按同组相对重要性归一化。 | N12: 采用5年滚动分位+同比/环比双阈值；数据滞后超过一个频率周期时自动降权。
A13: 【第二部分：同步指标（Coincident Indicators）——与当前景气同步变动】
A14: 9-晶圆厂产能利用率 | B14: 台积电/中芯国际 | C14: 88 | D14: % | E14: 上行 | F14: 0.1167 | G14: 8 | H14: >90%=10分,80-90%=8分,70-80%=6分,60-70%=4分,<60%=2分 | I14: 72% | J14: 产能利用率高位，供需偏紧 | K14: 月度 | L14: 0.15 | M14: 目标组权重 35%；按同组相对重要性归一化。 | N14: 采用TTM/滚动4季同比+历史分位；剔除一次性损益，IRR按项目现金流复核。
A15: 10-半导体设备出货额 | B15: SEMI | C15: +25 | D15: %YoY | E15: 上行 | F15: 0.0933 | G15: 8 | H15: >30%=10分,20-30%=8分,10-20%=6分,0-10%=4分,<0%=2分 | I15: 70% | J15: 设备出货高增，扩产需求旺盛 | K15: 季度 | L15: 0.12 | M15: 目标组权重 35%；按同组相对重要性归一化。 | N15: 采用季调同比+3个月环比；单月值用3个月移动均值过滤。
A16: 11-封测产能利用率 | B16: 日月光/长电科技 | C16: 82 | D16: % | E16: 上行 | F16: 0.0778 | G16: 8 | H16: >85%=10分,75-85%=8分,65-75%=6分,55-65%=4分,<55%=2分 | I16: 65% | J16: 封测利用率回升，订单饱满 | K16: 月度 | L16: 0.1 | M16: 目标组权重 35%；按同组相对重要性归一化。 | N16: 采用TTM/滚动4季同比+历史分位；剔除一次性损益，IRR按项目现金流复核。
A17: 12-半导体材料出货量 | B17: SEMI | C17: +12 | D17: %YoY | E17: 上行 | F17: 0.0622 | G17: 6 | H17: >15%=10分,10-15%=8分,5-10%=6分,0-5%=4分,<0%=2分 | I17: 62% | J17: 材料出货增长，国产替代推进 | K17: 季度 | L17: 0.08 | M17: 目标组权重 35%；按同组相对重要性归一化。 | N17: 采用季调同比+3个月环比；单月值用3个月移动均值过滤。
A18: 【第三部分：滞后指标（Lagging Indicators）——滞后1-2个季度反映景气变化】
A19: 13-半导体企业季度毛利率 | B19: 上市公司财报 | C19: 32 | D19: % | E19: 上行 | F19: 0.06 | G19: 8 | H19: >40%=10分,35-40%=8分,30-35%=6分,25-30%=4分,<25%=2分 | I19: 62% | J19: Q1毛利率改善，产品结构优化 | K19: 季度 | L19: 0.1 | M19: 目标组权重 15%；按同组相对重要性归一化。 | N19: 改为5年滚动分位(P20/P40/P60/P80)+3个月动量；须与库存、价差或利润交叉确认。
A20: 14-半导体行业净利润增速 | B20: 上市公司财报 | C20: +85 | D20: %YoY | E20: 上行 | F20: 0.048 | G20: 10 | H20: >50%=10分,30-50%=8分,10-30%=6分,0-10%=4分,<0%=2分 | I20: 88% | J20: Q1净利暴增，存储/设备领涨 | K20: 季度 | L20: 0.08 | M20: 目标组权重 15%；按同组相对重要性归一化。 | N20: 采用TTM/滚动4季同比+历史分位；剔除一次性损益，IRR按项目现金流复核。
A21: 15-半导体行业ROE | B21: 上市公司财报 | C21: 12 | D21: % | E21: 上行 | F21: 0.042 | G21: 8 | H21: >15%=10分,10-15%=8分,5-10%=6分,0-5%=4分,<0%=2分 | I21: 65% | J21: ROE改善，盈利能力回升 | K21: 季度 | L21: 0.07 | M21: 目标组权重 15%；按同组相对重要性归一化。 | N21: 采用TTM/滚动4季同比+历史分位；剔除一次性损益，IRR按项目现金流复核。
A22: 行业综合景气度加权得分 | G22: =ROUND(SUMPRODUCT(F5:F21,G5:G21),1) -> 8 | H22: 综合分=Σ(建议权重×单项评分)，建议权重和=100%。

Sheet 新能源
A1: 行业景气度量化跟踪体系（参数优化版）— 新能源
A2: 默认阶段框架：强周期/供给出清｜先行/同步/滞后=50%/35%/15%。先用库存、供给、订单确认反转；价格本身不能直接等同高景气。｜核心验证：供给出清与终端需求；必选：供给投放、库存、招标、出口
A3: 指标名称 | B3: 数据来源 | C3: 最新数值 | D3: 单位 | E3: 趋势 | F3: 权重 | G3: 评分 (1-10) | H3: 评分阈值说明 | I3: 历史分位 | J3: 对景气度影响 | K3: 跟踪频率 | L3: 原权重 | M3: 参数优化建议 | N3: 评分口径（更新时采用） | O3: 阶段分项 | P3: 公式分数
A4: 【第一部分：先行指标（Leading Indicators）——提前1-2个季度预示景气变化】 | O4: 先行 | P4: =ROUND(SUMPRODUCT(F5:F12,G5:G12)/SUM(F5:F12),1) -> 8.6
A5: 1-光伏组件价格 | B5: PV InfoLink | C5: 0.82 | D5: 元/W | E5: 下行 | F5: 0.0723 | G5: 8 | H5: <0.8=10分,0.8-1.0=8分,1.0-1.2=6分,1.2-1.4=4分,>1.4=2分 | I5: 25% | J5: 组件价格触底，产业链利润承压 | K5: 周度 | L5: 0.12 | M5: 目标组权重 50%；按同组相对重要性归一化。 | N5: 改为5年滚动分位(P20/P40/P60/P80)+3个月动量；须与库存、价差或利润交叉确认。 | O5: 同步 | P5: =ROUND(SUMPRODUCT(F14:F17,G14:G17)/SUM(F14:F17),1) -> 6.5
A6: 2-硅料价格 | B6: 硅业分会 | C6: 42 | D6: 元/kg | E6: 下行 | F6: 0.0602 | G6: 8 | H6: <40=10分,40-60=8分,60-80=6分,80-100=4分,>100=2分 | I6: 22% | J6: 硅料价格低位，成本端改善 | K6: 周度 | L6: 0.1 | M6: 目标组权重 50%；按同组相对重要性归一化。 | N6: 改为5年滚动分位(P20/P40/P60/P80)+3个月动量；须与库存、价差或利润交叉确认。 | O6: 滞后 | P6: =ROUND(SUMPRODUCT(F19:F21,G19:G21)/SUM(F19:F21),1) -> 5.4
A7: 3-锂电池价格 | B7: SMM | C7: 0.52 | D7: 元/Wh | E7: 下行 | F7: 0.0723 | G7: 8 | H7: <0.5=10分,0.5-0.6=8分,0.6-0.7=6分,0.7-0.8=4分,>0.8=2分 | I7: 28% | J7: 电池价格触底，产业链利润压缩 | K7: 周度 | L7: 0.12 | M7: 目标组权重 50%；按同组相对重要性归一化。 | N7: 改为5年滚动分位(P20/P40/P60/P80)+3个月动量；须与库存、价差或利润交叉确认。
A8: 4-风电招标量 | B8: 金风科技/中国风能协会 | C8: 85 | D8: GW | E8: 高增 | F8: 0.0783 | G8: 10 | H8: >80=10分,60-80=8分,40-60=6分,20-40=4分,<20=2分 | I8: 82% | J8: 风电招标创新高，装机预期强劲 | K8: 季度 | L8: 0.13 | M8: 目标组权重 50%；按同组相对重要性归一化。 | N8: 滚动3M/4Q同比；以交付、收入或现金流确认，政策/规划单项权重≤8%。
A9: 5-电网投资计划 | B9: 国家电网/南方电网 | C9: 6500 | D9: 亿元 | E9: 高增 | F9: 0.0602 | G9: 10 | H9: >6000=10分,5000-6000=8分,4000-5000=6分,3000-4000=4分,<3000=2分 | I9: 85% | J9: 电网投资创新高，特高压建设加速 | K9: 年度 | L9: 0.1 | M9: 目标组权重 50%；按同组相对重要性归一化。 | N9: 采用5年滚动分位+同比/环比双阈值；数据滞后超过一个频率周期时自动降权。
A10: 6-储能招标量 | B10: CNESA | C10: 65 | D10: GWh | E10: 高增 | F10: 0.0602 | G10: 8 | H10: >50=10分,40-50=8分,30-40=6分,20-30=4分,<20=2分 | I10: 78% | J10: 储能招标高增，工商业储能爆发 | K10: 季度 | L10: 0.1 | M10: 目标组权重 50%；按同组相对重要性归一化。 | N10: 滚动3M/4Q同比；以交付、收入或现金流确认，政策/规划单项权重≤8%。
A11: 7-氢能项目规划 | B11: 国家能源局 | C11: 12 | D11: GW | E11: 高增 | F11: 0.0482 | G11: 8 | H11: >10=10分,7-10=8分,4-7=6分,2-4=4分,<2=2分 | I11: 72% | J11: 氢能规划加码，绿氢项目落地 | K11: 年度 | L11: 0.08 | M11: 目标组权重 50%；按同组相对重要性归一化。 | N11: 滚动3M/4Q同比；以交付、收入或现金流确认，政策/规划单项权重≤8%。
A12: 8-新能源车渗透率 | B12: 中汽协 | C12: 42.5 | D12: % | E12: 上行 | F12: 0.0482 | G12: 8 | H12: >50%=10分,40-50%=8分,30-40%=6分,20-30%=4分,<20%=2分 | I12: 72% | J12: 渗透率快速提升，电动化加速 | K12: 月度 | L12: 0.08 | M12: 目标组权重 50%；按同组相对重要性归一化。 | N12: 采用5年滚动分位+同比/环比双阈值；数据滞后超过一个频率周期时自动降权。
A13: 【第二部分：同步指标（Coincident Indicators）——与当前景气同步变动】
A14: 9-光伏装机量 | B14: 国家能源局 | C14: 65 | D14: GW(累计) | E14: 上行 | F14: 0.1 | G14: 6 | H14: >100年化=10分,80-100=8分,60-80=6分,40-60=4分,<40=2分 | I14: 55% | J14: 光伏装机稳健，分布式贡献大 | K14: 月度 | L14: 0.12 | M14: 目标组权重 35%；按同组相对重要性归一化。 | N14: 采用季调同比+3个月环比；单月值用3个月移动均值过滤。
A15: 10-风电装机量 | B15: 国家能源局 | C15: 28 | D15: GW(累计) | E15: 上行 | F15: 0.0833 | G15: 6 | H15: >60年化=10分,50-60=8分,40-50=6分,30-40=4分,<30=2分 | I15: 52% | J15: 风电装机平稳，海上风电加速 | K15: 月度 | L15: 0.1 | M15: 目标组权重 35%；按同组相对重要性归一化。 | N15: 采用季调同比+3个月环比；单月值用3个月移动均值过滤。
A16: 11-储能装机量 | B16: CNESA | C16: 18 | D16: GWh(累计) | E16: 上行 | F16: 0.0833 | G16: 6 | H16: >50年化=10分,40-50=8分,30-40=6分,20-30=4分,<20=2分 | I16: 55% | J16: 储能装机高增，工商业储能爆发 | K16: 季度 | L16: 0.1 | M16: 目标组权重 35%；按同组相对重要性归一化。 | N16: 采用季调同比+3个月环比；单月值用3个月移动均值过滤。
A17: 12-新能源车销量 | B17: 中汽协 | C17: 88 | D17: 万辆/月 | E17: 上行 | F17: 0.0833 | G17: 8 | H17: >100=10分,80-100=8分,60-80=6分,40-60=4分,<40=2分 | I17: 68% | J17: 新能源车销量高增 | K17: 月度 | L17: 0.1 | M17: 目标组权重 35%；按同组相对重要性归一化。 | N17: 采用季调同比+3个月环比；单月值用3个月移动均值过滤。
A18: 【第三部分：滞后指标（Lagging Indicators）——滞后1-2个季度反映景气变化】
A19: 13-新能源企业季度净利润 | B19: 上市公司财报 | C19: 95 | D19: 亿元 | E19: 下行 | F19: 0.06 | G19: 6 | H19: >100亿=10分,50-100亿=8分,0-50亿=6分,-50-0亿=4分,<-50亿=2分 | I19: 48% | J19: Q1利润分化，光伏承压/风电改善 | K19: 季度 | L19: 0.1 | M19: 目标组权重 15%；按同组相对重要性归一化。 | N19: 采用TTM/滚动4季同比+历史分位；剔除一次性损益，IRR按项目现金流复核。
A20: 14-新能源行业毛利率 | B20: 上市公司财报 | C20: 18 | D20: % | E20: 下行 | F20: 0.048 | G20: 4 | H20: >25%=10分,20-25%=8分,15-20%=6分,10-15%=4分,<10%=2分 | I20: 38% | J20: 毛利率下滑，价格竞争加剧 | K20: 季度 | L20: 0.08 | M20: 目标组权重 15%；按同组相对重要性归一化。 | N20: 改为5年滚动分位(P20/P40/P60/P80)+3个月动量；须与库存、价差或利润交叉确认。
A21: 15-新能源行业产能利用率 | B21: 相关统计 | C21: 72 | D21: % | E21: 下行 | F21: 0.042 | G21: 6 | H21: >80%=10分,75-80%=8分,70-75%=6分,65-70%=4分,<65%=2分 | I21: 48% | J21: 产能利用率偏低，产能过剩 | K21: 季度 | L21: 0.07 | M21: 目标组权重 15%；按同组相对重要性归一化。 | N21: 采用TTM/滚动4季同比+历史分位；剔除一次性损益，IRR按项目现金流复核。
A22: 行业综合景气度加权得分 | G22: =ROUND(SUMPRODUCT(F5:F21,G5:G21),1) -> 7.3 | H22: 综合分=Σ(建议权重×单项评分)，建议权重和=100%。

Sheet 医药医疗
A1: 行业景气度量化跟踪体系（参数优化版）— 医药医疗
A2: 默认阶段框架：科技制造/订单库存周期｜先行/同步/滞后=50%/35%/15%。订单、库存和利用率优先；不同子行业拆分后再汇总。｜核心验证：细分商业化与支付环境；必选：注册/审批、医保、研发/订单
A3: 指标名称 | B3: 数据来源 | C3: 最新数值 | D3: 单位 | E3: 趋势 | F3: 权重 | G3: 评分 (1-10) | H3: 评分阈值说明 | I3: 历史分位 | J3: 对景气度影响 | K3: 跟踪频率 | L3: 原权重 | M3: 参数优化建议 | N3: 评分口径（更新时采用） | O3: 阶段分项 | P3: 公式分数
A4: 【第一部分：先行指标（Leading Indicators）——提前1-2个季度预示景气变化】 | O4: 先行 | P4: =ROUND(SUMPRODUCT(F5:F12,G5:G12)/SUM(F5:F12),1) -> 8
A5: 1-创新药IND数量 | B5: CDE | C5: 185 | D5: 个/月 | E5: 上行 | F5: 0.0937 | G5: 8 | H5: >200=10分,150-200=8分,100-150=6分,50-100=4分,<50=2分 | I5: 72% | J5: 创新药申报活跃，研发管线丰富 | K5: 月度 | L5: 0.15 | M5: 目标组权重 50%；按同组相对重要性归一化。 | N5: 采用5年滚动分位+同比/环比双阈值；数据滞后超过一个频率周期时自动降权。 | O5: 同步 | P5: =ROUND(SUMPRODUCT(F14:F17,G14:G17)/SUM(F14:F17),1) -> 7.2
A6: 2-医保谈判降价幅度 | B6: 国家医保局 | C6: 45 | D6: % | E6: 温和 | F6: 0.0625 | G6: 8 | H6: <40%=10分,40-50%=8分,50-60%=6分,60-70%=4分,>70%=2分 | I6: 55% | J6: 降价幅度可控，创新药定价环境改善 | K6: 年度 | L6: 0.1 | M6: 目标组权重 50%；按同组相对重要性归一化。 | N6: 采用5年滚动分位+同比/环比双阈值；数据滞后超过一个频率周期时自动降权。 | O6: 滞后 | P6: =ROUND(SUMPRODUCT(F19:F21,G19:G21)/SUM(F19:F21),1) -> 8
A7: 3-原料药价格变化 | B7: 健康网 | C7: -2.5 | D7: %YoY | E7: 下行 | F7: 0.0625 | G7: 8 | H7: <-5%=10分,-5-0%=8分,0-5%=6分,5-10%=4分,>10%=2分 | I7: 42% | J7: 原料药价格回落，制剂成本改善 | K7: 月度 | L7: 0.1 | M7: 目标组权重 50%；按同组相对重要性归一化。 | N7: 改为5年滚动分位(P20/P40/P60/P80)+3个月动量；须与库存、价差或利润交叉确认。
A8: 4-全球生物医药融资额 | B8: PitchBook | C8: +15 | D8: %YoY | E8: 上行 | F8: 0.0625 | G8: 8 | H8: >20%=10分,10-20%=8分,0-10%=6分,-10-0%=4分,<-10%=2分 | I8: 60% | J8: 融资回暖，创新药估值修复 | K8: 季度 | L8: 0.1 | M8: 目标组权重 50%；按同组相对重要性归一化。 | N8: 滚动3M/4Q同比；以交付、收入或现金流确认，政策/规划单项权重≤8%。
A9: 5-医疗器械注册证数量 | B9: NMPA | C9: 520 | D9: 个/月 | E9: 高增 | F9: 0.05 | G9: 8 | H9: >500=10分,400-500=8分,300-400=6分,200-300=4分,<200=2分 | I9: 72% | J9: 器械注册活跃，创新产品涌现 | K9: 月度 | L9: 0.08 | M9: 目标组权重 50%；按同组相对重要性归一化。 | N9: 滚动3M/4Q同比；以交付、收入或现金流确认，政策/规划单项权重≤8%。
A10: 6-CXO订单增速 | B10: 药明/康龙化成财报 | C10: +18 | D10: %YoY | E10: 上行 | F10: 0.075 | G10: 8 | H10: >20%=10分,10-20%=8分,0-10%=6分,-10-0%=4分,<-10%=2分 | I10: 65% | J10: CXO订单回暖，全球外包转移 | K10: 季度 | L10: 0.12 | M10: 目标组权重 50%；按同组相对重要性归一化。 | N10: 滚动3M/4Q同比；以交付、收入或现金流确认，政策/规划单项权重≤8%。
A11: 7-仿制药一致性评价通过数 | B11: NMPA | C11: 95 | D11: 个/月 | E11: 上行 | F11: 0.05 | G11: 8 | H11: >100=10分,80-100=8分,60-80=6分,40-60=4分,<40=2分 | I11: 65% | J11: 一致性评价推进，质量升级 | K11: 月度 | L11: 0.08 | M11: 目标组权重 50%；按同组相对重要性归一化。 | N11: 采用5年滚动分位+同比/环比双阈值；数据滞后超过一个频率周期时自动降权。
A12: 8-医疗AI产品获批数量 | B12: NMPA | C12: 42 | D12: 个/年 | E12: 高增 | F12: 0.0438 | G12: 8 | H12: >50=10分,40-50=8分,30-40=6分,20-30=4分,<20=2分 | I12: 68% | J12: AI医疗产品获批加速，数字化医疗崛起 | K12: 年度 | L12: 0.07 | M12: 目标组权重 50%；按同组相对重要性归一化。 | N12: 采用5年滚动分位+同比/环比双阈值；数据滞后超过一个频率周期时自动降权。
A13: 【第二部分：同步指标（Coincident Indicators）——与当前景气同步变动】
A14: 9-医药制造业收入增速 | B14: 国家统计局 | C14: +8.5 | D14: %YoY | E14: 上行 | F14: 0.1105 | G14: 8 | H14: >10%=10分,5-10%=8分,0-5%=6分,-5-0%=4分,<-5%=2分 | I14: 62% | J14: 制造业收入稳健增长 | K14: 月度 | L14: 0.12 | M14: 目标组权重 35%；按同组相对重要性归一化。 | N14: 采用季调同比+3个月环比；单月值用3个月移动均值过滤。
A15: 10-化学药品原药产量 | B15: 国家统计局 | C15: +4.2 | D15: %YoY | E15: 上行 | F15: 0.0737 | G15: 6 | H15: >5%=10分,2-5%=8分,0-2%=6分,-3-0%=4分,<-3%=2分 | I15: 55% | J15: 原料药产量温和增长 | K15: 月度 | L15: 0.08 | M15: 目标组权重 35%；按同组相对重要性归一化。 | N15: 采用季调同比+3个月环比；单月值用3个月移动均值过滤。
A16: 11-医疗器械出口增速 | B16: 海关总署 | C16: +18.5 | D16: %YoY | E16: 上行 | F16: 0.0921 | G16: 8 | H16: >15%=10分,5-15%=8分,0-5%=6分,-5-0%=4分,<-5%=2分 | I16: 70% | J16: 器械出口强劲，海外需求旺盛 | K16: 月度 | L16: 0.1 | M16: 目标组权重 35%；按同组相对重要性归一化。 | N16: 采用5年滚动分位+同比/环比双阈值；数据滞后超过一个频率周期时自动降权。
A17: 12-医院诊疗人次增速 | B17: 国家卫健委 | C17: +6.5 | D17: %YoY | E17: 上行 | F17: 0.0737 | G17: 6 | H17: >10%=10分,5-10%=8分,0-5%=6分,-5-0%=4分,<-5%=2分 | I17: 58% | J17: 诊疗人次恢复，院内需求回暖 | K17: 月度 | L17: 0.08 | M17: 目标组权重 35%；按同组相对重要性归一化。 | N17: 采用5年滚动分位+同比/环比双阈值；数据滞后超过一个频率周期时自动降权。
A18: 【第三部分：滞后指标（Lagging Indicators）——滞后1-2个季度反映景气变化】
A19: 13-医药企业季度毛利率 | B19: 上市公司财报 | C19: 58 | D19: % | E19: 上行 | F19: 0.06 | G19: 8 | H19: >60%=10分,50-60%=8分,40-50%=6分,30-40%=4分,<30%=2分 | I19: 68% | J19: Q1毛利率稳健，产品结构优化 | K19: 季度 | L19: 0.1 | M19: 目标组权重 15%；按同组相对重要性归一化。 | N19: 改为5年滚动分位(P20/P40/P60/P80)+3个月动量；须与库存、价差或利润交叉确认。
A20: 14-医药企业研发费用率 | B20: 上市公司财报 | C20: 13.5 | D20: % | E20: 上行 | F20: 0.048 | G20: 8 | H20: >15%=10分,10-15%=8分,5-10%=6分,2-5%=4分,<2%=2分 | I20: 62% | J20: 研发投入维持高位，创新转型加速 | K20: 季度 | L20: 0.08 | M20: 目标组权重 15%；按同组相对重要性归一化。 | N20: 采用5年滚动分位+同比/环比双阈值；数据滞后超过一个频率周期时自动降权。
A21: 15-医药制造业利润增速 | B21: 国家统计局 | C21: +12 | D21: %YoY | E21: 上行 | F21: 0.042 | G21: 8 | H21: >15%=10分,5-15%=8分,0-5%=6分,-5-0%=4分,<-5%=2分 | I21: 65% | J21: 利润增速回升，盈利能力改善 | K21: 月度 | L21: 0.07 | M21: 目标组权重 15%；按同组相对重要性归一化。 | N21: 采用TTM/滚动4季同比+历史分位；剔除一次性损益，IRR按项目现金流复核。
A22: 行业综合景气度加权得分 | G22: =ROUND(SUMPRODUCT(F5:F21,G5:G21),1) -> 7.7 | H22: 综合分=Σ(建议权重×单项评分)，建议权重和=100%。

Sheet 高端制造
A1: 行业景气度量化跟踪体系（参数优化版）— 高端制造
A2: 默认阶段框架：科技制造/订单库存周期｜先行/同步/滞后=50%/35%/15%。订单、库存和利用率优先；不同子行业拆分后再汇总。｜核心验证：国产替代、订单与交付；必选：订单、进口替代、研发转化
A3: 指标名称 | B3: 数据来源 | C3: 最新数值 | D3: 单位 | E3: 趋势 | F3: 权重 | G3: 评分 (1-10) | H3: 评分阈值说明 | I3: 历史分位 | J3: 对景气度影响 | K3: 跟踪频率 | L3: 原权重 | M3: 参数优化建议 | N3: 评分口径（更新时采用） | O3: 阶段分项 | P3: 公式分数
A4: 【第一部分：先行指标（Leading Indicators）——提前1-2个季度预示景气变化】 | O4: 先行 | P4: =ROUND(SUMPRODUCT(F5:F9,G5:G9)/SUM(F5:F9),1) -> 7.6
A5: 1-制造业固定资产投资增速 | B5: 国家统计局 | C5: +9.5 | D5: %YoY | E5: 上行 | F5: 0.1364 | G5: 8 | H5: >10%=10分,7-10%=8分,5-7%=6分,3-5%=4分,<3%=2分 | I5: 65% | J5: 制造业投资高增，设备更新需求 | K5: 月度 | L5: 0.15 | M5: 目标组权重 50%；按同组相对重要性归一化。 | N5: 采用5年滚动分位+同比/环比双阈值；数据滞后超过一个频率周期时自动降权。 | O5: 同步 | P5: =ROUND(SUMPRODUCT(F11:F14,G11:G14)/SUM(F11:F14),1) -> 7
A6: 2-工业机器人产量增速 | B6: 国家统计局 | C6: +18.5 | D6: %YoY | E6: 上行 | F6: 0.1091 | G6: 8 | H6: >20%=10分,10-20%=8分,0-10%=6分,-10-0%=4分,<-10%=2分 | I6: 68% | J6: 机器人产量高增，自动化升级加速 | K6: 月度 | L6: 0.12 | M6: 目标组权重 50%；按同组相对重要性归一化。 | N6: 采用季调同比+3个月环比；单月值用3个月移动均值过滤。 | O6: 滞后 | P6: =ROUND(SUMPRODUCT(F16:F18,G16:G18)/SUM(F16:F18),1) -> 6
A7: 3-数控机床进口金额 | B7: 海关总署 | C7: +8.5 | D7: %YoY | E7: 上行 | F7: 0.0909 | G7: 6 | H7: >10%=10分,5-10%=8分,0-5%=6分,-5-0%=4分,<-5%=2分 | I7: 58% | J7: 机床进口增长，高端需求旺盛 | K7: 月度 | L7: 0.1 | M7: 目标组权重 50%；按同组相对重要性归一化。 | N7: 采用5年滚动分位+同比/环比双阈值；数据滞后超过一个频率周期时自动降权。
A8: 4-高端装备研发支出增速 | B8: 上市公司财报 | C8: +22 | D8: %YoY | E8: 上行 | F8: 0.0909 | G8: 8 | H8: >20%=10分,15-20%=8分,10-15%=6分,5-10%=4分,<5%=2分 | I8: 72% | J8: 研发支出高增，技术突破加速 | K8: 季度 | L8: 0.1 | M8: 目标组权重 50%；按同组相对重要性归一化。 | N8: 采用5年滚动分位+同比/环比双阈值；数据滞后超过一个频率周期时自动降权。
A9: 5-国产替代政策力度 | B9: 工信部/发改委 | C9: 28 | D9: 项/年 | E9: 高增 | F9: 0.0727 | G9: 8 | H9: >30=10分,20-30=8分,10-20=6分,5-10=4分,<5=2分 | I9: 68% | J9: 政策密集出台，国产替代加速 | K9: 年度 | L9: 0.08 | M9: 目标组权重 50%；按同组相对重要性归一化。 | N9: 滚动3M/4Q同比；以交付、收入或现金流确认，政策/规划单项权重≤8%。
A10: 【第二部分：同步指标（Coincident Indicators）——与当前景气同步变动】
A11: 6-金属切削机床产量 | B11: 国家统计局 | C11: +8.5 | D11: %YoY | E11: 上行 | F11: 0.105 | G11: 6 | H11: >10%=10分,5-10%=8分,0-5%=6分,-5-0%=4分,<-5%=2分 | I11: 58% | J11: 机床产量回升，高端制造需求 | K11: 月度 | L11: 0.12 | M11: 目标组权重 35%；按同组相对重要性归一化。 | N11: 采用季调同比+3个月环比；单月值用3个月移动均值过滤。
A12: 7-工业机器人销量 | B12: 中国机器人产业联盟 | C12: +20 | D12: %YoY | E12: 上行 | F12: 0.0875 | G12: 8 | H12: >20%=10分,10-20%=8分,0-10%=6分,-10-0%=4分,<-10%=2分 | I12: 65% | J12: 机器人销量高增，制造业升级 | K12: 季度 | L12: 0.1 | M12: 目标组权重 35%；按同组相对重要性归一化。 | N12: 采用季调同比+3个月环比；单月值用3个月移动均值过滤。
A13: 8-高端装备出口增速 | B13: 海关总署 | C13: +18.5 | D13: %YoY | E13: 上行 | F13: 0.0875 | G13: 8 | H13: >15%=10分,10-15%=8分,5-10%=6分,0-5%=4分,<0%=2分 | I13: 70% | J13: 高端装备出口强劲，国际竞争力提升 | K13: 月度 | L13: 0.1 | M13: 目标组权重 35%；按同组相对重要性归一化。 | N13: 采用5年滚动分位+同比/环比双阈值；数据滞后超过一个频率周期时自动降权。
A14: 9-航空航天器产量 | B14: 国家统计局 | C14: +8.5 | D14: %YoY | E14: 上行 | F14: 0.07 | G14: 6 | H14: >10%=10分,5-10%=8分,0-5%=6分,-5-0%=4分,<-5%=2分 | I14: 58% | J14: 航空航天产量增长，国防/民航双驱动 | K14: 季度 | L14: 0.08 | M14: 目标组权重 35%；按同组相对重要性归一化。 | N14: 采用季调同比+3个月环比；单月值用3个月移动均值过滤。
A15: 【第三部分：滞后指标（Lagging Indicators）——滞后1-2个季度反映景气变化】
A16: 10-高端制造企业季度净利润 | B16: 上市公司财报 | C16: 45 | D16: 亿元 | E16: 上行 | F16: 0.06 | G16: 6 | H16: >50亿=10分,20-50亿=8分,0-20亿=6分,-20-0亿=4分,<-20亿=2分 | I16: 55% | J16: Q1利润改善，出口/自动化贡献 | K16: 季度 | L16: 0.1 | M16: 目标组权重 15%；按同组相对重要性归一化。 | N16: 采用TTM/滚动4季同比+历史分位；剔除一次性损益，IRR按项目现金流复核。
A17: 11-高端制造行业毛利率 | B17: 上市公司财报 | C17: 28 | D17: % | E17: 上行 | F17: 0.048 | G17: 6 | H17: >30%=10分,25-30%=8分,20-25%=6分,15-20%=4分,<15%=2分 | I17: 55% | J17: 毛利率改善，高附加值产品占比提升 | K17: 季度 | L17: 0.08 | M17: 目标组权重 15%；按同组相对重要性归一化。 | N17: 改为5年滚动分位(P20/P40/P60/P80)+3个月动量；须与库存、价差或利润交叉确认。
A18: 12-高端制造行业产能利用率 | B18: 国家统计局 | C18: 78 | D18: % | E18: 上行 | F18: 0.042 | G18: 6 | H18: >80%=10分,75-80%=8分,70-75%=6分,65-70%=4分,<65%=2分 | I18: 58% | J18: 产能利用率回升，供需改善 | K18: 季度 | L18: 0.07 | M18: 目标组权重 15%；按同组相对重要性归一化。 | N18: 采用TTM/滚动4季同比+历史分位；剔除一次性损益，IRR按项目现金流复核。
A19: 行业综合景气度加权得分 | G19: =ROUND(SUMPRODUCT(F5:F18,G5:G18),1) -> 7.2 | H19: 综合分=Σ(建议权重×单项评分)，建议权重和=100%。

Sheet 人形机器人
A1: 行业景气度量化跟踪体系（参数优化版）— 人形机器人
A2: 默认阶段框架：早期产业化/兑现｜先行/同步/滞后=55%/30%/15%。量产、订单、交付优先；热度与规划指标不得主导评分。｜核心验证：量产里程碑与商业订单；必选：量产时间、BOM降本、订单/客户验证
A3: 指标名称 | B3: 数据来源 | C3: 最新数值 | D3: 单位 | E3: 趋势 | F3: 权重 | G3: 评分 (1-10) | H3: 评分阈值说明 | I3: 历史分位 | J3: 对景气度影响 | K3: 跟踪频率 | L3: 原权重 | M3: 参数优化建议 | N3: 评分口径（更新时采用） | O3: 阶段分项 | P3: 公式分数
A4: 【第一部分：先行指标（Leading Indicators）——提前1-2个季度预示景气变化】 | O4: 先行 | P4: =ROUND(SUMPRODUCT(F5:F9,G5:G9)/SUM(F5:F9),1) -> 8.4
A5: 1-人形机器人量产计划 | B5: 特斯拉/优必选/小米 | C5: 5 | D5: 万台 | E5: 高增 | F5: 0.15 | G5: 8 | H5: >10万=10分,5-10万=8分,1-5万=6分,0.5-1万=4分,<0.5万=2分 | I5: 72% | J5: 量产计划明确，2026年商业化元年 | K5: 季度 | L5: 0.15 | M5: 目标组权重 55%；按同组相对重要性归一化。 | N5: 采用5年滚动分位+同比/环比双阈值；数据滞后超过一个频率周期时自动降权。 | O5: 同步 | P5: =ROUND(SUMPRODUCT(F11:F14,G11:G14)/SUM(F11:F14),1) -> 7.6
A6: 2-核心零部件订单 | B6: 绿的谐波/汇川技术 | C6: +120 | D6: %YoY | E6: 爆发 | F6: 0.12 | G6: 10 | H6: >100%=10分,50-100%=8分,20-50%=6分,0-20%=4分,<0%=2分 | I6: 88% | J6: 零部件订单爆发，供应链景气确认 | K6: 季度 | L6: 0.12 | M6: 目标组权重 55%；按同组相对重要性归一化。 | N6: 滚动3M/4Q同比；以交付、收入或现金流确认，政策/规划单项权重≤8%。 | O6: 滞后 | P6: =ROUND(SUMPRODUCT(F16:F18,G16:G18)/SUM(F16:F18),1) -> 5.8
A7: 3-减速器价格变化 | B7: 产业调研 | C7: -18 | D7: %YoY | E7: 下行 | F7: 0.1 | G7: 8 | H7: <-20%=10分,-20-0%=8分,0-10%=6分,10-20%=4分,>20%=2分 | I7: 35% | J7: 减速器价格下降，规模化降本 | K7: 季度 | L7: 0.1 | M7: 目标组权重 55%；按同组相对重要性归一化。 | N7: 改为5年滚动分位(P20/P40/P60/P80)+3个月动量；须与库存、价差或利润交叉确认。
A8: 4-伺服电机出货量 | B8: 汇川技术/禾川科技 | C8: +55 | D8: %YoY | E8: 上行 | F8: 0.1 | G8: 8 | H8: >50%=10分,30-50%=8分,10-30%=6分,0-10%=4分,<0%=2分 | I8: 78% | J8: 伺服电机出货高增，自动化+机器人双驱动 | K8: 季度 | L8: 0.1 | M8: 目标组权重 55%；按同组相对重要性归一化。 | N8: 采用季调同比+3个月环比；单月值用3个月移动均值过滤。
A9: 5-AI大模型迭代进度 | B9: OpenAI/百度/阿里 | C9: V4 | D9: 版本 | E9: 重大升级 | F9: 0.08 | G9: 8 | H9: 重大升级=10分,常规升级=8分,小更新=6分,停滞=4分,倒退=2分 | I9: 75% | J9: 大模型迭代加速，机器人智能化提升 | K9: 季度 | L9: 0.08 | M9: 目标组权重 55%；按同组相对重要性归一化。 | N9: 采用5年滚动分位+同比/环比双阈值；数据滞后超过一个频率周期时自动降权。
A10: 【第二部分：同步指标（Coincident Indicators）——与当前景气同步变动】
A11: 6-人形机器人出货量 | B11: 相关统计 | C11: 850 | D11: 台/月 | E11: 上行 | F11: 0.1047 | G11: 8 | H11: >1000=10分,500-1000=8分,200-500=6分,50-200=4分,<50=2分 | I11: 72% | J11: 出货量逐月提升，工厂场景落地 | K11: 月度 | L11: 0.15 | M11: 目标组权重 30%；按同组相对重要性归一化。 | N11: 采用季调同比+3个月环比；单月值用3个月移动均值过滤。
A12: 7-核心零部件国产化率 | B12: 产业调研 | C12: 72 | D12: % | E12: 上行 | F12: 0.0698 | G12: 8 | H12: >80%=10分,60-80%=8分,40-60%=6分,20-40%=4分,<20%=2分 | I12: 68% | J12: 国产化率提升，供应链自主可控 | K12: 季度 | L12: 0.1 | M12: 目标组权重 30%；按同组相对重要性归一化。 | N12: 采用5年滚动分位+同比/环比双阈值；数据滞后超过一个频率周期时自动降权。
A13: 8-人形机器人应用场景拓展 | B13: 产业调研 | C13: 8 | D13: 个 | E13: 上行 | F13: 0.0558 | G13: 6 | H13: >10=10分,7-10=8分,4-7=6分,2-4=4分,<2=2分 | I13: 62% | J13: 应用场景拓展，工业/服务双轮驱动 | K13: 季度 | L13: 0.08 | M13: 目标组权重 30%；按同组相对重要性归一化。 | N13: 采用5年滚动分位+同比/环比双阈值；数据滞后超过一个频率周期时自动降权。
A14: 9-相关上市公司收入增速 | B14: 上市公司财报 | C14: +45 | D14: %YoY | E14: 上行 | F14: 0.0698 | G14: 8 | H14: >50%=10分,30-50%=8分,10-30%=6分,0-10%=4分,<0%=2分 | I14: 75% | J14: 产业链收入高增，订单饱满 | K14: 季度 | L14: 0.1 | M14: 目标组权重 30%；按同组相对重要性归一化。 | N14: 采用季调同比+3个月环比；单月值用3个月移动均值过滤。
A15: 【第三部分：滞后指标（Lagging Indicators）——滞后1-2个季度反映景气变化】
A16: 10-人形机器人企业净利润 | B16: 上市公司财报 | C16: 3.5 | D16: 亿元 | E16: 亏损收窄 | F16: 0.06 | G16: 4 | H16: >10亿=10分,5-10亿=8分,0-5亿=6分,-5-0亿=4分,<-5亿=2分 | I16: 45% | J16: 多数企业仍亏损，商业化早期 | K16: 季度 | L16: 0.1 | M16: 目标组权重 15%；按同组相对重要性归一化。 | N16: 采用TTM/滚动4季同比+历史分位；剔除一次性损益，IRR按项目现金流复核。
A17: 11-人形机器人行业毛利率 | B17: 上市公司财报 | C17: 22 | D17: % | E17: 上行 | F17: 0.048 | G17: 6 | H17: >30%=10分,20-30%=8分,10-20%=6分,0-10%=4分,<0%=2分 | I17: 52% | J17: 毛利率改善，规模效应显现 | K17: 季度 | L17: 0.08 | M17: 目标组权重 15%；按同组相对重要性归一化。 | N17: 改为5年滚动分位(P20/P40/P60/P80)+3个月动量；须与库存、价差或利润交叉确认。
A18: 12-人形机器人行业研发投入 | B18: 上市公司财报 | C18: 18 | D18: % | E18: 上行 | F18: 0.042 | G18: 8 | H18: >20%=10分,15-20%=8分,10-15%=6分,5-10%=4分,<5%=2分 | I18: 72% | J18: 研发投入维持高位，技术迭代快 | K18: 季度 | L18: 0.07 | M18: 目标组权重 15%；按同组相对重要性归一化。 | N18: 采用5年滚动分位+同比/环比双阈值；数据滞后超过一个频率周期时自动降权。
A19: 行业综合景气度加权得分 | G19: =ROUND(SUMPRODUCT(F5:F18,G5:G18),1) -> 7.8 | H19: 综合分=Σ(建议权重×单项评分)，建议权重和=100%。

Sheet AI算力
A1: 行业景气度量化跟踪体系（参数优化版）— AI算力
A2: 默认阶段框架：早期产业化/兑现｜先行/同步/滞后=55%/30%/15%。量产、订单、交付优先；热度与规划指标不得主导评分。｜核心验证：云CAPEX、供给与利用率；必选：云厂商CAPEX、GPU/光模块订单、供给交期
A3: 指标名称 | B3: 数据来源 | C3: 最新数值 | D3: 单位 | E3: 趋势 | F3: 权重 | G3: 评分 (1-10) | H3: 评分阈值说明 | I3: 历史分位 | J3: 对景气度影响 | K3: 跟踪频率 | L3: 原权重 | M3: 参数优化建议 | N3: 评分口径（更新时采用） | O3: 阶段分项 | P3: 公式分数
A4: 【第一部分：先行指标（Leading Indicators）——提前1-2个季度预示景气变化】 | O4: 先行 | P4: =ROUND(SUMPRODUCT(F5:F9,G5:G9)/SUM(F5:F9),1) -> 9.4
A5: 1-全球AI服务器出货量增速 | B5: IDC | C5: +58 | D5: %YoY | E5: 上行 | F5: 0.15 | G5: 10 | H5: >50%=10分,30-50%=8分,15-30%=6分,0-15%=4分,<0%=2分 | I5: 88% | J5: AI服务器爆发，算力基建狂飙 | K5: 季度 | L5: 0.15 | M5: 目标组权重 55%；按同组相对重要性归一化。 | N5: 采用季调同比+3个月环比；单月值用3个月移动均值过滤。 | O5: 同步 | P5: =ROUND(SUMPRODUCT(F11:F14,G11:G14)/SUM(F11:F14),1) -> 8.5
A6: 2-GPU/ASIC出货量 | B6: 英伟达/AMD/华为 | C6: +62 | D6: %YoY | E6: 上行 | F6: 0.12 | G6: 10 | H6: >50%=10分,30-50%=8分,15-30%=6分,0-15%=4分,<0%=2分 | I6: 90% | J6: GPU/ASIC出货井喷，供不应求 | K6: 季度 | L6: 0.12 | M6: 目标组权重 55%；按同组相对重要性归一化。 | N6: 采用季调同比+3个月环比；单月值用3个月移动均值过滤。 | O6: 滞后 | P6: =ROUND(SUMPRODUCT(F16:F18,G16:G18)/SUM(F16:F18),1) -> 8
A7: 3-光模块出货量 | B7: LightCounting | C7: +48 | D7: %YoY | E7: 上行 | F7: 0.1 | G7: 10 | H7: >40%=10分,30-40%=8分,20-30%=6分,10-20%=4分,<10%=2分 | I7: 85% | J7: 光模块爆发，800G/1.6T放量 | K7: 季度 | L7: 0.1 | M7: 目标组权重 55%；按同组相对重要性归一化。 | N7: 采用季调同比+3个月环比；单月值用3个月移动均值过滤。
A8: 4-数据中心建设规模 | B8: 工信部 | C8: 115 | D8: 万架 | E8: 高增 | F8: 0.1 | G8: 10 | H8: >100=10分,80-100=8分,60-80=6分,40-60=4分,<40=2分 | I8: 85% | J8: 数据中心建设加速，智算中心爆发 | K8: 年度 | L8: 0.1 | M8: 目标组权重 55%；按同组相对重要性归一化。 | N8: 采用5年滚动分位+同比/环比双阈值；数据滞后超过一个频率周期时自动降权。
A9: 5-液冷技术渗透率 | B9: 产业调研 | C9: 25 | D9: % | E9: 上行 | F9: 0.08 | G9: 6 | H9: >30%=10分,20-30%=8分,10-20%=6分,5-10%=4分,<5%=2分 | I9: 58% | J9: 液冷渗透率提升，高密度算力需求 | K9: 季度 | L9: 0.08 | M9: 目标组权重 55%；按同组相对重要性归一化。 | N9: 采用5年滚动分位+同比/环比双阈值；数据滞后超过一个频率周期时自动降权。
A10: 【第二部分：同步指标（Coincident Indicators）——与当前景气同步变动】
A11: 6-AI算力租赁价格 | B11: 相关平台 | C11: +15 | D11: %vs均值 | E11: 上行 | F11: 0.09 | G11: 8 | H11: >均值20%=10分,0-20%=8分,-10-0%=6分,-20--10%=4分,<-20%=2分 | I11: 68% | J11: 算力租赁价格上涨，供需偏紧 | K11: 月度 | L11: 0.12 | M11: 目标组权重 30%；按同组相对重要性归一化。 | N11: 改为5年滚动分位(P20/P40/P60/P80)+3个月动量；须与库存、价差或利润交叉确认。
A12: 7-云计算收入增速 | B12: 阿里云/腾讯云/AWS | C12: +28 | D12: %YoY | E12: 上行 | F12: 0.075 | G12: 8 | H12: >30%=10分,20-30%=8分,10-20%=6分,5-10%=4分,<5%=2分 | I12: 72% | J12: 云收入高增，AI云服务贡献 | K12: 季度 | L12: 0.1 | M12: 目标组权重 30%；按同组相对重要性归一化。 | N12: 采用季调同比+3个月环比；单月值用3个月移动均值过滤。
A13: 8-算力中心PUE值 | B13: 工信部 | C13: 1.28 | E13: 改善 | F13: 0.06 | G13: 8 | H13: <1.2=10分,1.2-1.3=8分,1.3-1.4=6分,1.4-1.5=4分,>1.5=2分 | I13: 62% | J13: PUE改善，绿色算力推进 | K13: 季度 | L13: 0.08 | M13: 目标组权重 30%；按同组相对重要性归一化。 | N13: 采用5年滚动分位+同比/环比双阈值；数据滞后超过一个频率周期时自动降权。
A14: 9-国产AI芯片出货量 | B14: 华为/寒武纪/海光 | C14: +120 | D14: %YoY | E14: 上行 | F14: 0.075 | G14: 10 | H14: >100%=10分,50-100%=8分,20-50%=6分,0-20%=4分,<0%=2分 | I14: 85% | J14: 国产芯片出货翻倍，自主可控加速 | K14: 季度 | L14: 0.1 | M14: 目标组权重 30%；按同组相对重要性归一化。 | N14: 采用季调同比+3个月环比；单月值用3个月移动均值过滤。
A15: 【第三部分：滞后指标（Lagging Indicators）——滞后1-2个季度反映景气变化】
A16: 10-AI算力企业季度净利润 | B16: 上市公司财报 | C16: 65 | D16: 亿元 | E16: 上行 | F16: 0.06 | G16: 8 | H16: >50亿=10分,20-50亿=8分,0-20亿=6分,-20-0亿=4分,<-20亿=2分 | I16: 72% | J16: Q1利润高增，光模块/服务器领涨 | K16: 季度 | L16: 0.1 | M16: 目标组权重 15%；按同组相对重要性归一化。 | N16: 采用TTM/滚动4季同比+历史分位；剔除一次性损益，IRR按项目现金流复核。
A17: 11-AI算力行业毛利率 | B17: 上市公司财报 | C17: 32 | D17: % | E17: 上行 | F17: 0.048 | G17: 8 | H17: >35%=10分,28-35%=8分,20-28%=6分,12-20%=4分,<12%=2分 | I17: 65% | J17: 毛利率改善，高端产品占比提升 | K17: 季度 | L17: 0.08 | M17: 目标组权重 15%；按同组相对重要性归一化。 | N17: 改为5年滚动分位(P20/P40/P60/P80)+3个月动量；须与库存、价差或利润交叉确认。
A18: 12-AI算力行业产能利用率 | B18: 产业调研 | C18: 88 | D18: % | E18: 上行 | F18: 0.042 | G18: 8 | H18: >85%=10分,75-85%=8分,65-75%=6分,55-65%=4分,<55%=2分 | I18: 75% | J18: 产能利用率高位，供不应求 | K18: 季度 | L18: 0.07 | M18: 目标组权重 15%；按同组相对重要性归一化。 | N18: 采用TTM/滚动4季同比+历史分位；剔除一次性损益，IRR按项目现金流复核。
A19: 行业综合景气度加权得分 | G19: =ROUND(SUMPRODUCT(F5:F18,G5:G18),1) -> 8.9 | H19: 综合分=Σ(建议权重×单项评分)，建议权重和=100%。

Sheet 锂电
A1: 行业景气度量化跟踪体系（参数优化版）— 锂电
A2: 默认阶段框架：强周期/供给出清｜先行/同步/滞后=50%/35%/15%。先用库存、供给、订单确认反转；价格本身不能直接等同高景气。｜核心验证：供给出清、库存与订单；必选：产能投放、库存、排产、车型订单
A3: 指标名称 | B3: 数据来源 | C3: 最新数值 | D3: 单位 | E3: 趋势 | F3: 权重 | G3: 评分 (1-10) | H3: 评分阈值说明 | I3: 历史分位 | J3: 对景气度影响 | K3: 跟踪频率 | L3: 原权重 | M3: 参数优化建议 | N3: 评分口径（更新时采用） | O3: 阶段分项 | P3: 公式分数
A4: 【第一部分：先行指标（Leading Indicators）——提前1-2个季度预示景气变化】 | O4: 先行 | P4: =ROUND(SUMPRODUCT(F5:F11,G5:G11)/SUM(F5:F11),1) -> 7.8
A5: 1-碳酸锂价格变化 | B5: SMM/上海有色网 | C5: 7.2 | D5: 万元/吨 | E5: 下行 | F5: 0.1056 | G5: 8 | H5: <7=10分,7-9=8分,9-11=6分,11-13=4分,>13=2分 | I5: 28% | J5: 碳酸锂价格触底，成本端改善 | K5: 周度 | L5: 0.15 | M5: 目标组权重 50%；按同组相对重要性归一化。 | N5: 改为5年滚动分位(P20/P40/P60/P80)+3个月动量；须与库存、价差或利润交叉确认。 | O5: 同步 | P5: =ROUND(SUMPRODUCT(F13:F18,G13:G18)/SUM(F13:F18),1) -> 8
A6: 2-氢氧化锂价格变化 | B6: SMM | C6: 8.5 | D6: 万元/吨 | E6: 下行 | F6: 0.0563 | G6: 8 | H6: <8=10分,8-10=8分,10-12=6分,12-14=4分,>14=2分 | I6: 30% | J6: 氢氧化锂价格回落，高镍成本下降 | K6: 周度 | L6: 0.08 | M6: 目标组权重 50%；按同组相对重要性归一化。 | N6: 改为5年滚动分位(P20/P40/P60/P80)+3个月动量；须与库存、价差或利润交叉确认。 | O6: 滞后 | P6: =ROUND(SUMPRODUCT(F20:F23,G20:G23)/SUM(F20:F23),1) -> 5.5
A7: 3-钴/镍价格变化 | B7: LME/SMM | C7: -8.5 | D7: %YoY | E7: 下行 | F7: 0.0563 | G7: 8 | H7: <-10%=10分,-10-0%=8分,0-10%=6分,10-20%=4分,>20%=2分 | I7: 38% | J7: 钴镍价格回落，三元材料成本改善 | K7: 周度 | L7: 0.08 | M7: 目标组权重 50%；按同组相对重要性归一化。 | N7: 改为5年滚动分位(P20/P40/P60/P80)+3个月动量；须与库存、价差或利润交叉确认。
A8: 4-动力电池产能规划增速 | B8: 高工锂电 | C8: +25 | D8: %YoY | E8: 放缓 | F8: 0.0704 | G8: 8 | H8: <20%=10分,20-40%=8分,40-60%=6分,60-80%=4分,>80%=2分 | I8: 55% | J8: 产能扩张放缓，供给压力减轻 | K8: 季度 | L8: 0.1 | M8: 目标组权重 50%；按同组相对重要性归一化。 | N8: 滚动3M/4Q同比；以交付、收入或现金流确认，政策/规划单项权重≤8%。
A9: 5-新能源车渗透率预期 | B9: 中汽协/乘联会 | C9: 42.5 | D9: % | E9: 上行 | F9: 0.0845 | G9: 8 | H9: >50%=10分,40-50%=8分,30-40%=6分,20-30%=4分,<20%=2分 | I9: 72% | J9: 渗透率快速提升，需求端强劲 | K9: 月度 | L9: 0.12 | M9: 目标组权重 50%；按同组相对重要性归一化。 | N9: 采用5年滚动分位+同比/环比双阈值；数据滞后超过一个频率周期时自动降权。
A10: 6-锂电设备订单增速 | B10: 先导智能/赢合科技 | C10: +35 | D10: %YoY | E10: 上行 | F10: 0.0704 | G10: 8 | H10: >30%=10分,15-30%=8分,5-15%=6分,0-5%=4分,<0%=2分 | I10: 72% | J10: 设备订单高增，海外扩产+固态电池 | K10: 季度 | L10: 0.1 | M10: 目标组权重 50%；按同组相对重要性归一化。 | N10: 滚动3M/4Q同比；以交付、收入或现金流确认，政策/规划单项权重≤8%。
A11: 7-正极材料企业排产计划 | B11: 高工锂电 | C11: +8.5 | D11: %MoM | E11: 上行 | F11: 0.0563 | G11: 6 | H11: >10%=10分,5-10%=8分,0-5%=6分,-5-0%=4分,<-5%=2分 | I11: 58% | J11: 排产温和增长，5月旺季来临 | K11: 月度 | L11: 0.08 | M11: 目标组权重 50%；按同组相对重要性归一化。 | N11: 采用5年滚动分位+同比/环比双阈值；数据滞后超过一个频率周期时自动降权。
A12: 【第二部分：同步指标（Coincident Indicators）——与当前景气同步变动】
A13: 8-动力电池装车量增速 | B13: 中国汽车动力电池产业创新联盟 | C13: +38 | D13: %YoY | E13: 上行 | F13: 0.0905 | G13: 8 | H13: >40%=10分,30-40%=8分,20-30%=6分,10-20%=4分,<10%=2分 | I13: 75% | J13: 装车量高增，新能源车产销两旺 | K13: 月度 | L13: 0.15 | M13: 目标组权重 35%；按同组相对重要性归一化。 | N13: 采用5年滚动分位+同比/环比双阈值；数据滞后超过一个频率周期时自动降权。
A14: 9-动力电池产量增速 | B14: 中国汽车动力电池产业创新联盟 | C14: +35 | D14: %YoY | E14: 上行 | F14: 0.0603 | G14: 8 | H14: >35%=10分,25-35%=8分,15-25%=6分,5-15%=4分,<5%=2分 | I14: 72% | J14: 电池产量高增，出口+国内双驱动 | K14: 月度 | L14: 0.1 | M14: 目标组权重 35%；按同组相对重要性归一化。 | N14: 采用季调同比+3个月环比；单月值用3个月移动均值过滤。
A15: 10-锂电池出口金额增速 | B15: 海关总署 | C15: +32 | D15: %YoY | E15: 上行 | F15: 0.0603 | G15: 8 | H15: >30%=10分,20-30%=8分,10-20%=6分,0-10%=4分,<0%=2分 | I15: 78% | J15: 锂电池出口强劲，海外车企订单 | K15: 月度 | L15: 0.1 | M15: 目标组权重 35%；按同组相对重要性归一化。 | N15: 采用5年滚动分位+同比/环比双阈值；数据滞后超过一个频率周期时自动降权。
A16: 11-正极材料产量增速 | B16: 高工锂电 | C16: +22 | D16: %YoY | E16: 上行 | F16: 0.0483 | G16: 8 | H16: >25%=10分,15-25%=8分,5-15%=6分,0-5%=4分,<0%=2分 | I16: 68% | J16: 正极材料产量高增 | K16: 月度 | L16: 0.08 | M16: 目标组权重 35%；按同组相对重要性归一化。 | N16: 采用季调同比+3个月环比；单月值用3个月移动均值过滤。
A17: 12-负极材料产量增速 | B17: 高工锂电 | C17: +18 | D17: %YoY | E17: 上行 | F17: 0.0483 | G17: 8 | H17: >20%=10分,10-20%=8分,0-10%=6分,-10-0%=4分,<-10%=2分 | I17: 65% | J17: 负极材料产量增长 | K17: 月度 | L17: 0.08 | M17: 目标组权重 35%；按同组相对重要性归一化。 | N17: 采用季调同比+3个月环比；单月值用3个月移动均值过滤。
A18: 13-电解液产量增速 | B18: 高工锂电 | C18: +20 | D18: %YoY | E18: 上行 | F18: 0.0422 | G18: 8 | H18: >20%=10分,10-20%=8分,0-10%=6分,-10-0%=4分,<-10%=2分 | I18: 68% | J18: 电解液产量增长 | K18: 月度 | L18: 0.07 | M18: 目标组权重 35%；按同组相对重要性归一化。 | N18: 采用季调同比+3个月环比；单月值用3个月移动均值过滤。
A19: 【第三部分：滞后指标（Lagging Indicators）——滞后1-2个季度反映景气变化】
A20: 14-锂电企业季度毛利率 | B20: 上市公司财报 | C20: 16.5 | D20: % | E20: 上行 | F20: 0.0455 | G20: 6 | H20: >20%=10分,15-20%=8分,10-15%=6分,5-10%=4分,<5%=2分 | I20: 48% | J20: Q1毛利率改善，价格竞争趋缓 | K20: 季度 | L20: 0.1 | M20: 目标组权重 15%；按同组相对重要性归一化。 | N20: 改为5年滚动分位(P20/P40/P60/P80)+3个月动量；须与库存、价差或利润交叉确认。
A21: 15-锂电企业季度净利润 | B21: 上市公司财报 | C21: 85 | D21: 亿元 | E21: 上行 | F21: 0.0364 | G21: 6 | H21: >100亿=10分,50-100亿=8分,0-50亿=6分,-50-0亿=4分,<-50亿=2分 | I21: 52% | J21: Q1利润分化，龙头盈利改善 | K21: 季度 | L21: 0.08 | M21: 目标组权重 15%；按同组相对重要性归一化。 | N21: 采用TTM/滚动4季同比+历史分位；剔除一次性损益，IRR按项目现金流复核。
A22: 16-锂电行业产能利用率 | B22: 高工锂电 | C22: 68 | D22: % | E22: 下行 | F22: 0.0364 | G22: 4 | H22: >80%=10分,70-80%=8分,60-70%=6分,50-60%=4分,<50%=2分 | I22: 42% | J22: 产能利用率偏低，产能过剩 | K22: 季度 | L22: 0.08 | M22: 目标组权重 15%；按同组相对重要性归一化。 | N22: 采用TTM/滚动4季同比+历史分位；剔除一次性损益，IRR按项目现金流复核。
A23: 17-锂电行业应收账款周转 | B23: 上市公司财报 | C23: 105 | D23: 天 | E23: 下行 | F23: 0.0318 | G23: 6 | H23: <90天=10分,90-120天=8分,120-150天=6分,150-180天=4分,>180天=2分 | I23: 52% | J23: 应收账款周转放缓，回款压力仍存 | K23: 季度 | L23: 0.07 | M23: 目标组权重 15%；按同组相对重要性归一化。 | N23: 采用同比、环比、历史分位三维评分；按去库/改善方向计分。
A24: 行业综合景气度加权得分 | G24: =ROUND(SUMPRODUCT(F5:F23,G5:G23),1) -> 7.5 | H24: 综合分=Σ(建议权重×单项评分)，建议权重和=100%。

Sheet 光伏
A1: 行业景气度量化跟踪体系（参数优化版）— 光伏
A2: 默认阶段框架：强周期/供给出清｜先行/同步/滞后=50%/35%/15%。先用库存、供给、订单确认反转；价格本身不能直接等同高景气。｜核心验证：供给出清、排产与现金流；必选：产能出清、库存、排产、招标
A3: 指标名称 | B3: 数据来源 | C3: 最新数值 | D3: 单位 | E3: 趋势 | F3: 权重 | G3: 评分 (1-10) | H3: 评分阈值说明 | I3: 历史分位 | J3: 对景气度影响 | K3: 跟踪频率 | L3: 原权重 | M3: 参数优化建议 | N3: 评分口径（更新时采用） | O3: 阶段分项 | P3: 公式分数
A4: 【第一部分：先行指标（Leading Indicators）——提前1-2个季度预示景气变化】 | O4: 先行 | P4: =ROUND(SUMPRODUCT(F5:F11,G5:G11)/SUM(F5:F11),1) -> 7.7
A5: 1-多晶硅料价格 | B5: 硅业分会 | C5: 42 | D5: 元/kg | E5: 下行 | F5: 0.1103 | G5: 8 | H5: <40=10分,40-50=8分,50-60=6分,60-70=4分,>70=2分 | I5: 22% | J5: 硅料价格触底，全产业链成本改善 | K5: 周度 | L5: 0.15 | M5: 目标组权重 50%；按同组相对重要性归一化。 | N5: 改为5年滚动分位(P20/P40/P60/P80)+3个月动量；须与库存、价差或利润交叉确认。 | O5: 同步 | P5: =ROUND(SUMPRODUCT(F13:F18,G13:G18)/SUM(F13:F18),1) -> 7.5
A6: 2-硅片价格变化 | B6: PV InfoLink | C6: 1.55 | D6: 元/片 | E6: 下行 | F6: 0.0735 | G6: 6 | H6: <1.5=10分,1.5-2.0=8分,2.0-2.5=6分,2.5-3.0=4分,>3.0=2分 | I6: 25% | J6: 硅片价格低位，利润压缩 | K6: 周度 | L6: 0.1 | M6: 目标组权重 50%；按同组相对重要性归一化。 | N6: 改为5年滚动分位(P20/P40/P60/P80)+3个月动量；须与库存、价差或利润交叉确认。 | O6: 滞后 | P6: =ROUND(SUMPRODUCT(F20:F23,G20:G23)/SUM(F20:F23),1) -> 4.4
A7: 3-光伏组件价格 | B7: PV InfoLink | C7: 0.82 | D7: 元/W | E7: 下行 | F7: 0.0882 | G7: 8 | H7: <0.8=10分,0.8-0.9=8分,0.9-1.0=6分,1.0-1.1=4分,>1.1=2分 | I7: 22% | J7: 组件价格触底，出口竞争力强 | K7: 周度 | L7: 0.12 | M7: 目标组权重 50%；按同组相对重要性归一化。 | N7: 改为5年滚动分位(P20/P40/P60/P80)+3个月动量；须与库存、价差或利润交叉确认。
A8: 4-多晶硅产能投放计划 | B8: 硅业分会 | C8: 12 | D8: 万吨 | E8: 放缓 | F8: 0.0588 | G8: 8 | H8: <10=10分,10-20=8分,20-30=6分,30-40=4分,>40=2分 | I8: 35% | J8: 产能投放放缓，供给压力减轻 | K8: 季度 | L8: 0.08 | M8: 目标组权重 50%；按同组相对重要性归一化。 | N8: 采用5年滚动分位+同比/环比双阈值；数据滞后超过一个频率周期时自动降权。
A9: 5-光伏玻璃价格 | B9: 卓创资讯 | C9: 18.5 | D9: 元/平米 | E9: 下行 | F9: 0.0588 | G9: 8 | H9: <20=10分,20-25=8分,25-30=6分,30-35=4分,>35=2分 | I9: 28% | J9: 玻璃价格低位，辅材成本改善 | K9: 周度 | L9: 0.08 | M9: 目标组权重 50%；按同组相对重要性归一化。 | N9: 改为5年滚动分位(P20/P40/P60/P80)+3个月动量；须与库存、价差或利润交叉确认。
A10: 6-EVA胶膜价格 | B10: 卓创资讯 | C10: 9.2 | D10: 元/平米 | E10: 下行 | F10: 0.0515 | G10: 8 | H10: <10=10分,10-12=8分,12-14=6分,14-16=4分,>16=2分 | I10: 30% | J10: 胶膜价格回落，组件成本下降 | K10: 周度 | L10: 0.07 | M10: 目标组权重 50%；按同组相对重要性归一化。 | N10: 改为5年滚动分位(P20/P40/P60/P80)+3个月动量；须与库存、价差或利润交叉确认。
A11: 7-光伏企业排产计划 | B11: PV InfoLink | C11: +12 | D11: %MoM | E11: 上行 | F11: 0.0588 | G11: 8 | H11: >15%=10分,5-15%=8分,0-5%=6分,-10-0%=4分,<-10%=2分 | I11: 62% | J11: 排产回升，5-6月旺季来临 | K11: 月度 | L11: 0.08 | M11: 目标组权重 50%；按同组相对重要性归一化。 | N11: 采用5年滚动分位+同比/环比双阈值；数据滞后超过一个频率周期时自动降权。
A12: 【第二部分：同步指标（Coincident Indicators）——与当前景气同步变动】
A13: 8-光伏新增装机量 | B13: 国家能源局 | C13: 65 | D13: GW(累计) | E13: 上行 | F13: 0.0905 | G13: 6 | H13: >100年化=10分,80-100=8分,60-80=6分,40-60=4分,<40=2分 | I13: 55% | J13: 装机量稳健，分布式+集中式双驱动 | K13: 月度 | L13: 0.15 | M13: 目标组权重 35%；按同组相对重要性归一化。 | N13: 采用季调同比+3个月环比；单月值用3个月移动均值过滤。
A14: 9-组件出货量增速 | B14: PV InfoLink | C14: +28 | D14: %YoY | E14: 上行 | F14: 0.0603 | G14: 8 | H14: >30%=10分,20-30%=8分,10-20%=6分,0-10%=4分,<0%=2分 | I14: 68% | J14: 组件出货高增，海外需求旺盛 | K14: 月度 | L14: 0.1 | M14: 目标组权重 35%；按同组相对重要性归一化。 | N14: 采用季调同比+3个月环比；单月值用3个月移动均值过滤。
A15: 10-电池片产量增速 | B15: PV InfoLink | C15: +22 | D15: %YoY | E15: 上行 | F15: 0.0483 | G15: 8 | H15: >25%=10分,15-25%=8分,5-15%=6分,0-5%=4分,<0%=2分 | I15: 65% | J15: 电池片产量增长，TOPCon放量 | K15: 月度 | L15: 0.08 | M15: 目标组权重 35%；按同组相对重要性归一化。 | N15: 采用季调同比+3个月环比；单月值用3个月移动均值过滤。
A16: 11-光伏出口金额增速 | B16: 海关总署 | C16: +18 | D16: %YoY | E16: 上行 | F16: 0.0603 | G16: 8 | H16: >20%=10分,10-20%=8分,0-10%=6分,-10-0%=4分,<-10%=2分 | I16: 65% | J16: 光伏出口强劲，欧洲/新兴市场 | K16: 月度 | L16: 0.1 | M16: 目标组权重 35%；按同组相对重要性归一化。 | N16: 采用5年滚动分位+同比/环比双阈值；数据滞后超过一个频率周期时自动降权。
A17: 12-分布式光伏装机占比 | B17: 国家能源局 | C17: 62 | D17: % | E17: 上行 | F17: 0.0422 | G17: 8 | H17: >60%=10分,50-60%=8分,40-50%=6分,30-40%=4分,<30%=2分 | I17: 72% | J17: 分布式占比提升，户用/工商业爆发 | K17: 月度 | L17: 0.07 | M17: 目标组权重 35%；按同组相对重要性归一化。 | N17: 采用季调同比+3个月环比；单月值用3个月移动均值过滤。
A18: 13-光伏逆变器出货量 | B18: Wood Mackenzie | C18: +32 | D18: %YoY | E18: 上行 | F18: 0.0483 | G18: 8 | H18: >30%=10分,20-30%=8分,10-20%=6分,0-10%=4分,<0%=2分 | I18: 70% | J18: 逆变器出货高增，储能逆变器贡献 | K18: 季度 | L18: 0.08 | M18: 目标组权重 35%；按同组相对重要性归一化。 | N18: 采用季调同比+3个月环比；单月值用3个月移动均值过滤。
A19: 【第三部分：滞后指标（Lagging Indicators）——滞后1-2个季度反映景气变化】
A20: 14-光伏企业季度毛利率 | B20: 上市公司财报 | C20: 14.5 | D20: % | E20: 下行 | F20: 0.0455 | G20: 4 | H20: >20%=10分,15-20%=8分,10-15%=6分,5-10%=4分,<5%=2分 | I20: 32% | J20: Q1毛利率低迷，价格竞争惨烈 | K20: 季度 | L20: 0.1 | M20: 目标组权重 15%；按同组相对重要性归一化。 | N20: 改为5年滚动分位(P20/P40/P60/P80)+3个月动量；须与库存、价差或利润交叉确认。
A21: 15-光伏企业季度净利润 | B21: 上市公司财报 | C21: 25 | D21: 亿元 | E21: 下行 | F21: 0.0364 | G21: 4 | H21: >80亿=10分,40-80亿=8分,0-40亿=6分,-40-0亿=4分,<-40亿=2分 | I21: 28% | J21: Q1利润大幅下滑，多数企业亏损 | K21: 季度 | L21: 0.08 | M21: 目标组权重 15%；按同组相对重要性归一化。 | N21: 采用TTM/滚动4季同比+历史分位；剔除一次性损益，IRR按项目现金流复核。
A22: 16-光伏行业产能利用率 | B22: PV InfoLink | C22: 68 | D22: % | E22: 下行 | F22: 0.0364 | G22: 4 | H22: >80%=10分,70-80%=8分,60-70%=6分,50-60%=4分,<50%=2分 | I22: 42% | J22: 产能利用率偏低，产能过剩严重 | K22: 季度 | L22: 0.08 | M22: 目标组权重 15%；按同组相对重要性归一化。 | N22: 采用TTM/滚动4季同比+历史分位；剔除一次性损益，IRR按项目现金流复核。
A23: 17-光伏行业资产负债率 | B23: 上市公司财报 | C23: 62 | D23: % | E23: 上行 | F23: 0.0318 | G23: 6 | H23: <55%=10分,55-60%=8分,60-65%=6分,65-70%=4分,>70%=2分 | I23: 58% | J23: 负债率上升，资金链承压 | K23: 季度 | L23: 0.07 | M23: 目标组权重 15%；按同组相对重要性归一化。 | N23: 采用同比、环比、历史分位三维评分；按去库/改善方向计分。
A24: 行业综合景气度加权得分 | G24: =ROUND(SUMPRODUCT(F5:F23,G5:G23),1) -> 7.1 | H24: 综合分=Σ(建议权重×单项评分)，建议权重和=100%。

Sheet 风电
A1: 行业景气度量化跟踪体系（参数优化版）— 风电
A2: 默认阶段框架：政策资本开支/交付｜先行/同步/滞后=45%/35%/20%。政策与规划只作确认项，必须由招标、交付、回款和利润验证。｜核心验证：招标、交付与盈利/回款；必选：招标、核准、海风进度
A3: 指标名称 | B3: 数据来源 | C3: 最新数值 | D3: 单位 | E3: 趋势 | F3: 权重 | G3: 评分 (1-10) | H3: 评分阈值说明 | I3: 历史分位 | J3: 对景气度影响 | K3: 跟踪频率 | L3: 原权重 | M3: 参数优化建议 | N3: 评分口径（更新时采用） | O3: 阶段分项 | P3: 公式分数
A4: 【第一部分：先行指标（Leading Indicators）——提前1-2个季度预示景气变化】 | O4: 先行 | P4: =ROUND(SUMPRODUCT(F5:F11,G5:G11)/SUM(F5:F11),1) -> 9.1
A5: 1-风电招标量 | B5: 金风科技/中国风能协会 | C5: 85 | D5: GW | E5: 高增 | F5: 0.0964 | G5: 10 | H5: >80=10分,60-80=8分,40-60=6分,20-40=4分,<20=2分 | I5: 82% | J5: 风电招标创新高，装机预期强劲 | K5: 季度 | L5: 0.15 | M5: 目标组权重 45%；按同组相对重要性归一化。 | N5: 滚动3M/4Q同比；以交付、收入或现金流确认，政策/规划单项权重≤8%。 | O5: 同步 | P5: =ROUND(SUMPRODUCT(F13:F18,G13:G18)/SUM(F13:F18),1) -> 7.2
A6: 2-风机中标均价 | B6: 金风科技 | C6: 1520 | D6: 元/kW | E6: 下行 | F6: 0.0771 | G6: 10 | H6: <1500=10分,1500-1800=8分,1800-2100=6分,2100-2400=4分,>2400=2分 | I6: 32% | J6: 风机价格触底，成本竞争力强 | K6: 月度 | L6: 0.12 | M6: 目标组权重 45%；按同组相对重要性归一化。 | N6: 改为5年滚动分位(P20/P40/P60/P80)+3个月动量；须与库存、价差或利润交叉确认。 | O6: 滞后 | P6: =ROUND(SUMPRODUCT(F20:F23,G20:G23)/SUM(F20:F23),1) -> 6.6
A7: 3-中厚板/钢铁价格 | B7: 上海钢联 | C7: -8.5 | D7: %YoY | E7: 下行 | F7: 0.0643 | G7: 8 | H7: <-10%=10分,-10-0%=8分,0-5%=6分,5-10%=4分,>10%=2分 | I7: 38% | J7: 钢材价格回落，塔筒/桩基成本改善 | K7: 周度 | L7: 0.1 | M7: 目标组权重 45%；按同组相对重要性归一化。 | N7: 改为5年滚动分位(P20/P40/P60/P80)+3个月动量；须与库存、价差或利润交叉确认。
A8: 4-海上风电规划容量 | B8: 国家能源局/各省发改委 | C8: 55 | D8: GW | E8: 高增 | F8: 0.0643 | G8: 10 | H8: >50=10分,40-50=8分,30-40=6分,20-30=4分,<20=2分 | I8: 85% | J8: 海上风电规划加码，沿海省份竞配 | K8: 年度 | L8: 0.1 | M8: 目标组权重 45%；按同组相对重要性归一化。 | N8: 滚动3M/4Q同比；以交付、收入或现金流确认，政策/规划单项权重≤8%。
A9: 5-风电项目核准量 | B9: 国家能源局 | C9: 45 | D9: GW | E9: 高增 | F9: 0.0514 | G9: 8 | H9: >40=10分,30-40=8分,20-30=6分,10-20=4分,<10=2分 | I9: 75% | J9: 项目核准放量，开工前置 | K9: 季度 | L9: 0.08 | M9: 目标组权重 45%；按同组相对重要性归一化。 | N9: 滚动3M/4Q同比；以交付、收入或现金流确认，政策/规划单项权重≤8%。
A10: 6-叶片/塔筒订单增速 | B10: 上市公司公告 | C10: +35 | D10: %YoY | E10: 上行 | F10: 0.0514 | G10: 8 | H10: >30%=10分,15-30%=8分,5-15%=6分,0-5%=4分,<0%=2分 | I10: 72% | J10: 零部件订单高增，供应链景气 | K10: 季度 | L10: 0.08 | M10: 目标组权重 45%；按同组相对重要性归一化。 | N10: 滚动3M/4Q同比；以交付、收入或现金流确认，政策/规划单项权重≤8%。
A11: 7-风电整机企业排产计划 | B11: 产业调研 | C11: +15 | D11: %MoM | E11: 上行 | F11: 0.045 | G11: 8 | H11: >15%=10分,5-15%=8分,0-5%=6分,-10-0%=4分,<-10%=2分 | I11: 68% | J11: 排产高增，交付旺季来临 | K11: 月度 | L11: 0.07 | M11: 目标组权重 45%；按同组相对重要性归一化。 | N11: 采用5年滚动分位+同比/环比双阈值；数据滞后超过一个频率周期时自动降权。
A12: 【第二部分：同步指标（Coincident Indicators）——与当前景气同步变动】
A13: 8-风电新增装机量 | B13: 国家能源局 | C13: 28 | D13: GW(累计) | E13: 上行 | F13: 0.0905 | G13: 6 | H13: >60年化=10分,50-60=8分,40-50=6分,30-40=4分,<30=2分 | I13: 52% | J13: 装机量平稳，海上风电加速 | K13: 月度 | L13: 0.15 | M13: 目标组权重 35%；按同组相对重要性归一化。 | N13: 采用季调同比+3个月环比；单月值用3个月移动均值过滤。
A14: 9-风机产量增速 | B14: 中国风能协会 | C14: +22 | D14: %YoY | E14: 上行 | F14: 0.0603 | G14: 8 | H14: >25%=10分,15-25%=8分,5-15%=6分,0-5%=4分,<0%=2分 | I14: 65% | J14: 风机产量增长，大型化趋势 | K14: 季度 | L14: 0.1 | M14: 目标组权重 35%；按同组相对重要性归一化。 | N14: 采用季调同比+3个月环比；单月值用3个月移动均值过滤。
A15: 10-风电发电量增速 | B15: 国家能源局 | C15: +18 | D15: %YoY | E15: 上行 | F15: 0.0603 | G15: 8 | H15: >20%=10分,15-20%=8分,10-15%=6分,5-10%=4分,<5%=2分 | I15: 68% | J15: 发电量高增，装机+利用小时双驱动 | K15: 月度 | L15: 0.1 | M15: 目标组权重 35%；按同组相对重要性归一化。 | N15: 采用5年滚动分位+同比/环比双阈值；数据滞后超过一个频率周期时自动降权。
A16: 11-风电利用率 | B16: 国家能源局 | C16: 96.5 | D16: % | E16: 上行 | F16: 0.0483 | G16: 8 | H16: >97%=10分,95-97%=8分,93-95%=6分,90-93%=4分,<90%=2分 | I16: 65% | J16: 利用率高，消纳改善 | K16: 月度 | L16: 0.08 | M16: 目标组权重 35%；按同组相对重要性归一化。 | N16: 采用TTM/滚动4季同比+历史分位；剔除一次性损益，IRR按项目现金流复核。
A17: 12-海上风电装机量 | B17: 国家能源局 | C17: 8.5 | D17: GW(累计) | E17: 上行 | F17: 0.0483 | G17: 6 | H17: >15年化=10分,10-15=8分,7-10=6分,4-7=4分,<4=2分 | I17: 55% | J17: 海上风电装机加速 | K17: 月度 | L17: 0.08 | M17: 目标组权重 35%；按同组相对重要性归一化。 | N17: 采用季调同比+3个月环比；单月值用3个月移动均值过滤。
A18: 13-风电出口金额增速 | B18: 海关总署 | C18: +25 | D18: %YoY | E18: 上行 | F18: 0.0422 | G18: 8 | H18: >30%=10分,20-30%=8分,10-20%=6分,0-10%=4分,<0%=2分 | I18: 68% | J18: 风电出口强劲，风机/零部件出海 | K18: 月度 | L18: 0.07 | M18: 目标组权重 35%；按同组相对重要性归一化。 | N18: 采用5年滚动分位+同比/环比双阈值；数据滞后超过一个频率周期时自动降权。
A19: 【第三部分：滞后指标（Lagging Indicators）——滞后1-2个季度反映景气变化】
A20: 14-风电企业季度毛利率 | B20: 上市公司财报 | C20: 19 | D20: % | E20: 上行 | F20: 0.0606 | G20: 8 | H20: >20%=10分,15-20%=8分,10-15%=6分,5-10%=4分,<5%=2分 | I20: 55% | J20: Q1毛利率改善，价格竞争趋缓 | K20: 季度 | L20: 0.1 | M20: 目标组权重 20%；按同组相对重要性归一化。 | N20: 改为5年滚动分位(P20/P40/P60/P80)+3个月动量；须与库存、价差或利润交叉确认。
A21: 15-风电企业季度净利润 | B21: 上市公司财报 | C21: 35 | D21: 亿元 | E21: 上行 | F21: 0.0485 | G21: 6 | H21: >50亿=10分,20-50亿=8分,0-20亿=6分,-20-0亿=4分,<-20亿=2分 | I21: 52% | J21: Q1利润改善，零部件企业贡献 | K21: 季度 | L21: 0.08 | M21: 目标组权重 20%；按同组相对重要性归一化。 | N21: 采用TTM/滚动4季同比+历史分位；剔除一次性损益，IRR按项目现金流复核。
A22: 16-风电行业应收账款周转 | B22: 上市公司财报 | C22: 125 | D22: 天 | E22: 下行 | F22: 0.0485 | G22: 6 | H22: <120天=10分,120-150天=8分,150-180天=6分,180-210天=4分,>210天=2分 | I22: 52% | J22: 应收账款周转放缓，回款周期延长 | K22: 季度 | L22: 0.08 | M22: 目标组权重 20%；按同组相对重要性归一化。 | N22: 采用同比、环比、历史分位三维评分；按去库/改善方向计分。
A23: 17-风电行业资产负债率 | B23: 上市公司财报 | C23: 62 | D23: % | E23: 下行 | F23: 0.0424 | G23: 6 | H23: <65%=10分,65-70%=8分,70-75%=6分,75-80%=4分,>80%=2分 | I23: 48% | J23: 负债率可控，财务结构稳健 | K23: 季度 | L23: 0.07 | M23: 目标组权重 20%；按同组相对重要性归一化。 | N23: 采用同比、环比、历史分位三维评分；按去库/改善方向计分。
A24: 行业综合景气度加权得分 | G24: =ROUND(SUMPRODUCT(F5:F23,G5:G23),1) -> 7.9 | H24: 综合分=Σ(建议权重×单项评分)，建议权重和=100%。

Sheet 储能
A1: 行业景气度量化跟踪体系（参数优化版）— 储能
A2: 默认阶段框架：政策资本开支/交付｜先行/同步/滞后=45%/35%/20%。政策与规划只作确认项，必须由招标、交付、回款和利润验证。｜核心验证：项目IRR、招标与并网利用；必选：峰谷价差、IRR、招标、海外订单
A3: 指标名称 | B3: 数据来源 | C3: 最新数值 | D3: 单位 | E3: 趋势 | F3: 权重 | G3: 评分 (1-10) | H3: 评分阈值说明 | I3: 历史分位 | J3: 对景气度影响 | K3: 跟踪频率 | L3: 原权重 | M3: 参数优化建议 | N3: 评分口径（更新时采用） | O3: 阶段分项 | P3: 公式分数
A4: 【第一部分：先行指标（Leading Indicators）——提前1-2个季度预示景气变化】 | O4: 先行 | P4: =ROUND(SUMPRODUCT(F5:F11,G5:G11)/SUM(F5:F11),1) -> 9.2
A5: 1-储能系统招标量 | B5: CNESA/中关村储能联盟 | C5: 68 | D5: GWh | E5: 高增 | F5: 0.0925 | G5: 10 | H5: >60=10分,45-60=8分,30-45=6分,15-30=4分,<15=2分 | I5: 82% | J5: 储能招标创新高，工商业+大储双爆发 | K5: 季度 | L5: 0.15 | M5: 目标组权重 45%；按同组相对重要性归一化。 | N5: 滚动3M/4Q同比；以交付、收入或现金流确认，政策/规划单项权重≤8%。 | O5: 同步 | P5: =ROUND(SUMPRODUCT(F13:F18,G13:G18)/SUM(F13:F18),1) -> 7.1
A6: 2-储能系统中标均价 | B6: CNESA | C6: 0.48 | D6: 元/Wh | E6: 下行 | F6: 0.074 | G6: 10 | H6: <0.5=10分,0.5-0.6=8分,0.6-0.7=6分,0.7-0.8=4分,>0.8=2分 | I6: 22% | J6: 系统价格触底，经济性凸显 | K6: 月度 | L6: 0.12 | M6: 目标组权重 45%；按同组相对重要性归一化。 | N6: 改为5年滚动分位(P20/P40/P60/P80)+3个月动量；须与库存、价差或利润交叉确认。 | O6: 滞后 | P6: =ROUND(SUMPRODUCT(F20:F23,G20:G23)/SUM(F20:F23),1) -> 7.1
A7: 3-锂电池价格 | B7: SMM | C7: 0.52 | D7: 元/Wh | E7: 下行 | F7: 0.0616 | G7: 8 | H7: <0.5=10分,0.5-0.6=8分,0.6-0.7=6分,0.7-0.8=4分,>0.8=2分 | I7: 28% | J7: 电池价格低位，储能成本下降 | K7: 周度 | L7: 0.1 | M7: 目标组权重 45%；按同组相对重要性归一化。 | N7: 改为5年滚动分位(P20/P40/P60/P80)+3个月动量；须与库存、价差或利润交叉确认。
A8: 4-新型储能规划容量 | B8: 国家能源局 | C8: 55 | D8: GW | E8: 高增 | F8: 0.0616 | G8: 10 | H8: >50=10分,40-50=8分,30-40=6分,20-30=4分,<20=2分 | I8: 82% | J8: 储能规划加码，政策目标明确 | K8: 年度 | L8: 0.1 | M8: 目标组权重 45%；按同组相对重要性归一化。 | N8: 滚动3M/4Q同比；以交付、收入或现金流确认，政策/规划单项权重≤8%。
A9: 5-储能政策发布数量 | B9: 国家能源局/发改委 | C9: 22 | D9: 项/年 | E9: 高增 | F9: 0.0493 | G9: 10 | H9: >20=10分,15-20=8分,10-15=6分,5-10=4分,<5=2分 | I9: 78% | J9: 政策密集出台，储能地位提升 | K9: 年度 | L9: 0.08 | M9: 目标组权重 45%；按同组相对重要性归一化。 | N9: 滚动3M/4Q同比；以交付、收入或现金流确认，政策/规划单项权重≤8%。
A10: 6-工商业储能IRR | B10: 产业调研 | C10: 14.5 | D10: % | E10: 上行 | F10: 0.0616 | G10: 8 | H10: >15%=10分,12-15%=8分,9-12%=6分,6-9%=4分,<6%=2分 | I10: 68% | J10: 工商业IRR改善，投资吸引力增强 | K10: 季度 | L10: 0.1 | M10: 目标组权重 45%；按同组相对重要性归一化。 | N10: 采用TTM/滚动4季同比+历史分位；剔除一次性损益，IRR按项目现金流复核。
A11: 7-储能PCS订单增速 | B11: 阳光电源/上能电气 | C11: +55 | D11: %YoY | E11: 上行 | F11: 0.0493 | G11: 8 | H11: >50%=10分,30-50%=8分,15-30%=6分,0-15%=4分,<0%=2分 | I11: 78% | J11: PCS订单爆发，大储+工商业双驱 | K11: 季度 | L11: 0.08 | M11: 目标组权重 45%；按同组相对重要性归一化。 | N11: 滚动3M/4Q同比；以交付、收入或现金流确认，政策/规划单项权重≤8%。
A12: 【第二部分：同步指标（Coincident Indicators）——与当前景气同步变动】
A13: 8-储能新增装机量 | B13: CNESA | C13: 18 | D13: GWh(累计) | E13: 上行 | F13: 0.0905 | G13: 6 | H13: >50年化=10分,40-50=8分,30-40=6分,20-30=4分,<20=2分 | I13: 55% | J13: 装机量高增，但基数仍小 | K13: 季度 | L13: 0.15 | M13: 目标组权重 35%；按同组相对重要性归一化。 | N13: 采用季调同比+3个月环比；单月值用3个月移动均值过滤。
A14: 9-储能项目并网量 | B14: 国家能源局 | C14: 15 | D14: GWh(累计) | E14: 上行 | F14: 0.0603 | G14: 6 | H14: >40年化=10分,30-40=8分,20-30=6分,10-20=4分,<10=2分 | I14: 52% | J14: 并网量增长，项目落地加速 | K14: 季度 | L14: 0.1 | M14: 目标组权重 35%；按同组相对重要性归一化。 | N14: 采用5年滚动分位+同比/环比双阈值；数据滞后超过一个频率周期时自动降权。
A15: 10-工商业储能渗透率 | B15: 产业调研 | C15: 8.5 | D15: % | E15: 上行 | F15: 0.0603 | G15: 6 | H15: >10%=10分,7-10%=8分,4-7%=6分,2-4%=4分,<2%=2分 | I15: 58% | J15: 工商业渗透率提升，峰谷价差驱动 | K15: 季度 | L15: 0.1 | M15: 目标组权重 35%；按同组相对重要性归一化。 | N15: 采用5年滚动分位+同比/环比双阈值；数据滞后超过一个频率周期时自动降权。
A16: 11-储能出口金额增速 | B16: 海关总署 | C16: +55 | D16: %YoY | E16: 上行 | F16: 0.0483 | G16: 10 | H16: >50%=10分,30-50%=8分,15-30%=6分,0-15%=4分,<0%=2分 | I16: 82% | J16: 储能出口爆发，欧美大储订单 | K16: 月度 | L16: 0.08 | M16: 目标组权重 35%；按同组相对重要性归一化。 | N16: 采用5年滚动分位+同比/环比双阈值；数据滞后超过一个频率周期时自动降权。
A17: 12-电源侧储能配储比例 | B17: 国家能源局 | C17: 13.5 | D17: % | E17: 上行 | F17: 0.0483 | G17: 8 | H17: >15%=10分,12-15%=8分,10-12%=6分,8-10%=4分,<8%=2分 | I17: 62% | J17: 配储比例提升，新能源强制配储 | K17: 年度 | L17: 0.08 | M17: 目标组权重 35%；按同组相对重要性归一化。 | N17: 采用5年滚动分位+同比/环比双阈值；数据滞后超过一个频率周期时自动降权。
A18: 13-储能EPC中标量 | B18: CNESA | C18: 32 | D18: GWh | E18: 上行 | F18: 0.0422 | G18: 8 | H18: >30=10分,20-30=8分,10-20=6分,5-10=4分,<5=2分 | I18: 72% | J18: EPC中标放量，项目建设提速 | K18: 季度 | L18: 0.07 | M18: 目标组权重 35%；按同组相对重要性归一化。 | N18: 采用5年滚动分位+同比/环比双阈值；数据滞后超过一个频率周期时自动降权。
A19: 【第三部分：滞后指标（Lagging Indicators）——滞后1-2个季度反映景气变化】
A20: 14-储能企业季度毛利率 | B20: 上市公司财报 | C20: 22 | D20: % | E20: 上行 | F20: 0.0606 | G20: 8 | H20: >25%=10分,20-25%=8分,15-20%=6分,10-15%=4分,<10%=2分 | I20: 58% | J20: Q1毛利率改善，系统集成能力提升 | K20: 季度 | L20: 0.1 | M20: 目标组权重 20%；按同组相对重要性归一化。 | N20: 改为5年滚动分位(P20/P40/P60/P80)+3个月动量；须与库存、价差或利润交叉确认。
A21: 15-储能企业季度净利润 | B21: 上市公司财报 | C21: 18 | D21: 亿元 | E21: 上行 | F21: 0.0485 | G21: 6 | H21: >30亿=10分,15-30亿=8分,0-15亿=6分,-15-0亿=4分,<-15亿=2分 | I21: 52% | J21: Q1利润改善，系统集成商贡献 | K21: 季度 | L21: 0.08 | M21: 目标组权重 20%；按同组相对重要性归一化。 | N21: 采用TTM/滚动4季同比+历史分位；剔除一次性损益，IRR按项目现金流复核。
A22: 16-储能项目IRR实现值 | B22: 产业调研 | C22: 10.5 | D22: % | E22: 上行 | F22: 0.0485 | G22: 8 | H22: >12%=10分,9-12%=8分,6-9%=6分,3-6%=4分,<3%=2分 | I22: 62% | J22: 项目IRR改善，盈利模式清晰 | K22: 年度 | L22: 0.08 | M22: 目标组权重 20%；按同组相对重要性归一化。 | N22: 采用TTM/滚动4季同比+历史分位；剔除一次性损益，IRR按项目现金流复核。
A23: 17-储能行业产能利用率 | B23: CNESA | C23: 72 | D23: % | E23: 下行 | F23: 0.0424 | G23: 6 | H23: >75%=10分,65-75%=8分,55-65%=6分,45-55%=4分,<45%=2分 | I23: 48% | J23: 产能利用率偏低，产能快速扩张 | K23: 季度 | L23: 0.07 | M23: 目标组权重 20%；按同组相对重要性归一化。 | N23: 采用TTM/滚动4季同比+历史分位；剔除一次性损益，IRR按项目现金流复核。
A24: 行业综合景气度加权得分 | G24: =ROUND(SUMPRODUCT(F5:F23,G5:G23),1) -> 8 | H24: 综合分=Σ(建议权重×单项评分)，建议权重和=100%。

Sheet CXO
A1: 行业景气度量化跟踪体系（参数优化版）— CXO
A2: 默认阶段框架：早期产业化/兑现｜先行/同步/滞后=55%/30%/15%。量产、订单、交付优先；热度与规划指标不得主导评分。｜核心验证：全球研发资金、订单与产能利用；必选：融资、IND、订单、地缘风险
A3: 指标名称 | B3: 数据来源 | C3: 最新数值 | D3: 单位 | E3: 趋势 | F3: 权重 | G3: 评分 (1-10) | H3: 评分阈值说明 | I3: 历史分位 | J3: 对景气度影响 | K3: 跟踪频率 | L3: 原权重 | M3: 参数优化建议 | N3: 评分口径（更新时采用） | O3: 阶段分项 | P3: 公式分数
A4: 【先行指标（Leading Indicators）——提前1-2个季度预示景气变化】 | O4: 先行 | P4: =ROUND(SUMPRODUCT(F5:F11,G5:G11)/SUM(F5:F11),1) -> 7.8
A5: 1-全球生物医药融资额 | B5: PitchBook | C5: +18 | D5: %YoY | E5: 上行 | F5: 0.1086 | G5: 8 | H5: >20%=10分,10-20%=8分,0-10%=6分,-10-0%=4分,<-10%=2分 | I5: 62% | J5: 融资回暖，创新药研发资金充裕，CXO订单源头改善 | K5: 季度 | L5: 0.15 | M5: 目标组权重 55%；按同组相对重要性归一化。 | N5: 滚动3M/4Q同比；以交付、收入或现金流确认，政策/规划单项权重≤8%。 | O5: 同步 | P5: =ROUND(SUMPRODUCT(F13:F18,G13:G18)/SUM(F13:F18),1) -> 7.4
A6: 2-FDA新药批准数量 | B6: FDA | C6: 28 | D6: 个/年 | E6: 上行 | F6: 0.0724 | G6: 8 | H6: >30=10分,25-30=8分,20-25=6分,15-20=4分,<15=2分 | I6: 58% | J6: FDA批准活跃，全球新药上市加速，后端CDMO需求增加 | K6: 月度 | L6: 0.1 | M6: 目标组权重 55%；按同组相对重要性归一化。 | N6: 滚动3M/4Q同比；以交付、收入或现金流确认，政策/规划单项权重≤8%。 | O6: 滞后 | P6: =ROUND(SUMPRODUCT(F20:F23,G20:G23)/SUM(F20:F23),1) -> 7.1
A7: 3-CXO企业订单增速 | B7: 药明康德/康龙化成/凯莱英 | C7: +22 | D7: %YoY | E7: 上行 | F7: 0.1086 | G7: 8 | H7: >25%=10分,15-25%=8分,5-15%=6分,0-5%=4分,<0%=2分 | I7: 68% | J7: 订单增速回升，全球外包转移+国内创新药需求双驱 | K7: 季度 | L7: 0.15 | M7: 目标组权重 55%；按同组相对重要性归一化。 | N7: 滚动3M/4Q同比；以交付、收入或现金流确认，政策/规划单项权重≤8%。
A8: 4-客户研发管线数量 | B8: Pharmaprojects | C8: +12 | D8: %YoY | E8: 上行 | F8: 0.0724 | G8: 8 | H8: >15%=10分,10-15%=8分,5-10%=6分,0-5%=4分,<0%=2分 | I8: 62% | J8: 客户管线扩张，前端CRO需求旺盛 | K8: 年度 | L8: 0.1 | M8: 目标组权重 55%；按同组相对重要性归一化。 | N8: 滚动3M/4Q同比；以交付、收入或现金流确认，政策/规划单项权重≤8%。
A9: 5-创新药IND数量 | B9: CDE | C9: 185 | D9: 个/月 | E9: 上行 | F9: 0.0724 | G9: 8 | H9: >200=10分,150-200=8分,100-150=6分,50-100=4分,<50=2分 | I9: 72% | J9: 国内IND活跃，早期研发外包需求强劲 | K9: 月度 | L9: 0.1 | M9: 目标组权重 55%；按同组相对重要性归一化。 | N9: 采用5年滚动分位+同比/环比双阈值；数据滞后超过一个频率周期时自动降权。
A10: 6-大分子/ADC药物研发热度 | B10: 相关统计 | C10: 高 | E10: 上行 | F10: 0.0579 | G10: 8 | H10: 极高=10分,高=8分,中=6分,低=4分,极低=2分 | I10: 75% | J10: ADC/双抗热度高涨，大分子CDMO产能紧缺 | K10: 季度 | L10: 0.08 | M10: 目标组权重 55%；按同组相对重要性归一化。 | N10: 采用5年滚动分位+同比/环比双阈值；数据滞后超过一个频率周期时自动降权。
A11: 7-地缘政治风险指数 | B11: 相关智库 | C11: 65 | D11: 点 | E11: 回落 | F11: 0.0579 | G11: 6 | H11: <40=10分,40-60=8分,60-80=6分,80-100=4分,>100=2分 | I11: 55% | J11: 地缘风险边际回落，但美国生物安全法案仍存不确定性 | K11: 月度 | L11: 0.08 | M11: 目标组权重 55%；按同组相对重要性归一化。 | N11: 采用5年滚动分位+同比/环比双阈值；数据滞后超过一个频率周期时自动降权。
A12: 【同步指标（Coincident Indicators）——与当前景气同步变动】
A13: 8-CXO企业收入增速 | B13: 上市公司财报 | C13: +16.5 | D13: %YoY | E13: 上行 | F13: 0.075 | G13: 8 | H13: >20%=10分,10-20%=8分,5-10%=6分,0-5%=4分,<0%=2分 | I13: 65% | J13: 收入增速回升，化学/生物业务双增长 | K13: 季度 | L13: 0.15 | M13: 目标组权重 30%；按同组相对重要性归一化。 | N13: 采用季调同比+3个月环比；单月值用3个月移动均值过滤。
A14: 9-CDMO产能利用率 | B14: 产业调研 | C14: 78 | D14: % | E14: 上行 | F14: 0.05 | G14: 6 | H14: >85%=10分,75-85%=8分,65-75%=6分,55-65%=4分,<55%=2分 | I14: 58% | J14: 产能利用率回升，小分子CDMO回暖明显 | K14: 季度 | L14: 0.1 | M14: 目标组权重 30%；按同组相对重要性归一化。 | N14: 采用TTM/滚动4季同比+历史分位；剔除一次性损益，IRR按项目现金流复核。
A15: 10-实验室服务收入增速 | B15: 药明康德/康龙化成 | C15: +18 | D15: %YoY | E15: 上行 | F15: 0.05 | G15: 8 | H15: >20%=10分,10-20%=8分,5-10%=6分,0-5%=4分,<0%=2分 | I15: 68% | J15: 实验室服务高增，药物发现阶段需求旺盛 | K15: 季度 | L15: 0.1 | M15: 目标组权重 30%；按同组相对重要性归一化。 | N15: 采用季调同比+3个月环比；单月值用3个月移动均值过滤。
A16: 11-临床CRO在研项目数 | B16: 泰格医药/诺思格 | C16: +15 | D16: %YoY | E16: 上行 | F16: 0.04 | G16: 8 | H16: >20%=10分,10-20%=8分,5-10%=6分,0-5%=4分,<0%=2分 | I16: 62% | J16: 临床项目增长，国内创新药临床需求增加 | K16: 季度 | L16: 0.08 | M16: 目标组权重 30%；按同组相对重要性归一化。 | N16: 采用5年滚动分位+同比/环比双阈值；数据滞后超过一个频率周期时自动降权。
A17: 12-CXO企业合同负债 | B17: 上市公司财报 | C17: +28 | D17: %YoY | E17: 上行 | F17: 0.05 | G17: 8 | H17: >30%=10分,15-30%=8分,5-15%=6分,0-5%=4分,<0%=2分 | I17: 68% | J17: 合同负债高增，在手订单充裕，收入前瞻性好 | K17: 季度 | L17: 0.1 | M17: 目标组权重 30%；按同组相对重要性归一化。 | N17: 滚动3M/4Q同比；以交付、收入或现金流确认，政策/规划单项权重≤8%。
A18: 13-CXO企业海外收入占比 | B18: 上市公司财报 | C18: 78 | D18: % | E18: 企稳 | F18: 0.035 | G18: 6 | H18: >80%=10分,70-80%=8分,60-70%=6分,50-60%=4分,<50%=2分 | I18: 65% | J18: 海外收入占比高，全球化布局成熟 | K18: 季度 | L18: 0.07 | M18: 目标组权重 30%；按同组相对重要性归一化。 | N18: 采用季调同比+3个月环比；单月值用3个月移动均值过滤。
A19: 【滞后指标（Lagging Indicators）——滞后1-2个季度反映景气变化】
A20: 14-CXO企业季度毛利率 | B20: 上市公司财报 | C20: 38.5 | D20: % | E20: 上行 | F20: 0.0429 | G20: 8 | H20: >40%=10分,35-40%=8分,30-35%=6分,25-30%=4分,<25%=2分 | I20: 58% | J20: Q1毛利率改善，产能利用率提升+价格企稳 | K20: 季度 | L20: 0.1 | M20: 目标组权重 15%；按同组相对重要性归一化。 | N20: 改为5年滚动分位(P20/P40/P60/P80)+3个月动量；须与库存、价差或利润交叉确认。
A21: 15-CXO企业净利润增速 | B21: 上市公司财报 | C21: +22 | D21: %YoY | E21: 上行 | F21: 0.0429 | G21: 8 | H21: >25%=10分,15-25%=8分,5-15%=6分,0-5%=4分,<0%=2分 | I21: 65% | J21: Q1净利增速回升，规模效应显现 | K21: 季度 | L21: 0.1 | M21: 目标组权重 15%；按同组相对重要性归一化。 | N21: 采用TTM/滚动4季同比+历史分位；剔除一次性损益，IRR按项目现金流复核。
A22: 16-CXO行业人均产出 | B22: 上市公司财报 | C22: 65 | D22: 万元 | E22: 上行 | F22: 0.0343 | G22: 6 | H22: >80=10分,60-80=8分,45-60=6分,30-45=4分,<30=2分 | I22: 55% | J22: 人均产出提升，运营效率改善 | K22: 年度 | L22: 0.08 | M22: 目标组权重 15%；按同组相对重要性归一化。 | N22: 采用5年滚动分位+同比/环比双阈值；数据滞后超过一个频率周期时自动降权。
A23: 17-CXO产能扩张进度 | B23: 上市公司公告 | C23: +15 | D23: %YoY | E23: 放缓 | F23: 0.03 | G23: 6 | H23: >25%=10分,15-25%=8分,5-15%=6分,0-5%=4分,<0%=2分 | I23: 52% | J23: 产能扩张放缓，资本开支趋于理性 | K23: 年度 | L23: 0.07 | M23: 目标组权重 15%；按同组相对重要性归一化。 | N23: 采用5年滚动分位+同比/环比双阈值；数据滞后超过一个频率周期时自动降权。
A24: 行业综合景气度加权得分 | G24: =ROUND(SUMPRODUCT(F5:F23,G5:G23),1) -> 7.6 | H24: 综合分=Σ(建议权重×单项评分)，建议权重和=100%。

Sheet 创新药
A1: 行业景气度量化跟踪体系（参数优化版）— 创新药
A2: 默认阶段框架：早期产业化/兑现｜先行/同步/滞后=55%/30%/15%。量产、订单、交付优先；热度与规划指标不得主导评分。｜核心验证：研发兑现、商业化与支付；必选：BD、临床、获批、医保/准入
A3: 指标名称 | B3: 数据来源 | C3: 最新数值 | D3: 单位 | E3: 趋势 | F3: 权重 | G3: 评分 (1-10) | H3: 评分阈值说明 | I3: 历史分位 | J3: 对景气度影响 | K3: 跟踪频率 | L3: 原权重 | M3: 参数优化建议 | N3: 评分口径（更新时采用） | O3: 阶段分项 | P3: 公式分数
A4: 【先行指标（Leading Indicators）——提前1-2个季度预示景气变化】 | O4: 先行 | P4: =ROUND(SUMPRODUCT(F5:F11,G5:G11)/SUM(F5:F11),1) -> 8
A5: 1-全球生物医药融资额 | B5: PitchBook | C5: +18 | D5: %YoY | E5: 上行 | F5: 0.1058 | G5: 8 | H5: >20%=10分,10-20%=8分,0-10%=6分,-10-0%=4分,<-10%=2分 | I5: 62% | J5: 融资回暖，Biotech资金充裕，早期研发外包及自研投入增加 | K5: 季度 | L5: 0.15 | M5: 目标组权重 55%；按同组相对重要性归一化。 | N5: 滚动3M/4Q同比；以交付、收入或现金流确认，政策/规划单项权重≤8%。 | O5: 同步 | P5: =ROUND(SUMPRODUCT(F13:F18,G13:G18)/SUM(F13:F18),1) -> 8
A6: 2-创新药IND数量 | B6: CDE | C6: 185 | D6: 个/月 | E6: 上行 | F6: 0.1058 | G6: 8 | H6: >200=10分,150-200=8分,100-150=6分,50-100=4分,<50=2分 | I6: 72% | J6: IND申报活跃，研发管线丰富，预示3-5年后上市品种 | K6: 月度 | L6: 0.15 | M6: 目标组权重 55%；按同组相对重要性归一化。 | N6: 采用5年滚动分位+同比/环比双阈值；数据滞后超过一个频率周期时自动降权。 | O6: 滞后 | P6: =ROUND(SUMPRODUCT(F20:F24,G20:G24)/SUM(F20:F24),1) -> 8.1
A7: 3-NDA/BLA申报数量 | B7: CDE | C7: 42 | D7: 个/月 | E7: 上行 | F7: 0.0705 | G7: 8 | H7: >50=10分,40-50=8分,30-40=6分,20-30=4分,<20=2分 | I7: 65% | J7: 上市申请增加，商业化在即，收入前瞻性好 | K7: 月度 | L7: 0.1 | M7: 目标组权重 55%；按同组相对重要性归一化。 | N7: 采用5年滚动分位+同比/环比双阈值；数据滞后超过一个频率周期时自动降权。
A8: 4-临床管线数量 | B8: Pharmaprojects/Insight | C8: +15 | D8: %YoY | E8: 上行 | F8: 0.0705 | G8: 8 | H8: >20%=10分,10-20%=8分,5-10%=6分,0-5%=4分,<0%=2分 | I8: 62% | J8: 管线扩张，临床阶段项目增加，CRO/CDMO需求拉动 | K8: 年度 | L8: 0.1 | M8: 目标组权重 55%；按同组相对重要性归一化。 | N8: 滚动3M/4Q同比；以交付、收入或现金流确认，政策/规划单项权重≤8%。
A9: 5-创新药BD交易金额 | B9: 医药魔方 | C9: +35 | D9: %YoY | E9: 上行 | F9: 0.0846 | G9: 8 | H9: >30%=10分,20-30%=8分,10-20%=6分,0-10%=4分,<0%=2分 | I9: 75% | J9: License-out高增，国产创新药国际化加速，首付款改善现金流 | K9: 季度 | L9: 0.12 | M9: 目标组权重 55%；按同组相对重要性归一化。 | N9: 采用5年滚动分位+同比/环比双阈值；数据滞后超过一个频率周期时自动降权。
A10: 6-医保谈判降价预期 | B10: 国家医保局 | C10: 45 | D10: % | E10: 温和 | F10: 0.0564 | G10: 8 | H10: <40%=10分,40-50%=8分,50-60%=6分,60-70%=4分,>70%=2分 | I10: 55% | J10: 降价幅度可控，创新药定价环境改善，利于峰值销售预期 | K10: 年度 | L10: 0.08 | M10: 目标组权重 55%；按同组相对重要性归一化。 | N10: 采用5年滚动分位+同比/环比双阈值；数据滞后超过一个频率周期时自动降权。
A11: 7-创新药研发支出增速 | B11: 上市公司财报 | C11: +22 | D11: %YoY | E11: 上行 | F11: 0.0564 | G11: 8 | H11: >25%=10分,15-25%=8分,5-15%=6分,0-5%=4分,<0%=2分 | I11: 68% | J11: 研发投入高增，管线厚度增加，长期成长确定性提升 | K11: 季度 | L11: 0.08 | M11: 目标组权重 55%；按同组相对重要性归一化。 | N11: 采用5年滚动分位+同比/环比双阈值；数据滞后超过一个频率周期时自动降权。
A12: 【同步指标（Coincident Indicators）——与当前景气同步变动】
A13: 8-创新药获批数量 | B13: NMPA | C13: 28 | D13: 个/年 | E13: 上行 | F13: 0.0726 | G13: 8 | H13: >30=10分,25-30=8分,20-25=6分,15-20=4分,<15=2分 | I13: 68% | J13: 获批数量高增，国产创新药进入收获期 | K13: 月度 | L13: 0.15 | M13: 目标组权重 30%；按同组相对重要性归一化。 | N13: 采用5年滚动分位+同比/环比双阈值；数据滞后超过一个频率周期时自动降权。
A14: 9-创新药销售额增速 | B14: PDB/样本医院 | C14: +25 | D14: %YoY | E14: 上行 | F14: 0.0581 | G14: 8 | H14: >30%=10分,20-30%=8分,10-20%=6分,0-10%=4分,<0%=2分 | I14: 72% | J14: 院内销售高增，新药放量+适应症拓展 | K14: 季度 | L14: 0.12 | M14: 目标组权重 30%；按同组相对重要性归一化。 | N14: 采用5年滚动分位+同比/环比双阈值；数据滞后超过一个频率周期时自动降权。
A15: 10-医院准入数量 | B15: 产业调研 | C15: +18 | D15: %YoY | E15: 上行 | F15: 0.0484 | G15: 8 | H15: >20%=10分,10-20%=8分,5-10%=6分,0-5%=4分,<0%=2分 | I15: 65% | J15: 医院准入加快，医保+商保双通道推动放量 | K15: 季度 | L15: 0.1 | M15: 目标组权重 30%；按同组相对重要性归一化。 | N15: 采用5年滚动分位+同比/环比双阈值；数据滞后超过一个频率周期时自动降权。
A16: 11-创新药处方量增速 | B16: IQVIA | C16: +22 | D16: %YoY | E16: 上行 | F16: 0.0484 | G16: 8 | H16: >25%=10分,15-25%=8分,5-15%=6分,0-5%=4分,<0%=2分 | I16: 68% | J16: 处方量高增，医生/患者接受度提升 | K16: 季度 | L16: 0.1 | M16: 目标组权重 30%；按同组相对重要性归一化。 | N16: 采用5年滚动分位+同比/环比双阈值；数据滞后超过一个频率周期时自动降权。
A17: 12-创新药出口金额 | B17: 海关总署 | C17: +45 | D17: %YoY | E17: 上行 | F17: 0.0387 | G17: 10 | H17: >40%=10分,30-40%=8分,20-30%=6分,10-20%=4分,<10%=2分 | I17: 78% | J17: 出口爆发，License-out+自主出海双轮驱动 | K17: 月度 | L17: 0.08 | M17: 目标组权重 30%；按同组相对重要性归一化。 | N17: 采用5年滚动分位+同比/环比双阈值；数据滞后超过一个频率周期时自动降权。
A18: 13-生物类似药上市数量 | B18: NMPA | C18: 8 | D18: 个/年 | E18: 上行 | F18: 0.0339 | G18: 6 | H18: >10=10分,7-10=8分,4-7=6分,2-4=4分,<2=2分 | I18: 55% | J18: 生物类似药上市，市场竞争加剧但可及性提升 | K18: 年度 | L18: 0.07 | M18: 目标组权重 30%；按同组相对重要性归一化。 | N18: 采用5年滚动分位+同比/环比双阈值；数据滞后超过一个频率周期时自动降权。
A19: 【滞后指标（Lagging Indicators）——滞后1-2个季度反映景气变化】
A20: 14-创新药企业毛利率 | B20: 上市公司财报 | C20: 82 | D20: % | E20: 上行 | F20: 0.0349 | G20: 10 | H20: >80%=10分,70-80%=8分,60-70%=6分,50-60%=4分,<50%=2分 | I20: 85% | J20: 毛利率极高，创新药专利壁垒+定价权强 | K20: 季度 | L20: 0.1 | M20: 目标组权重 15%；按同组相对重要性归一化。 | N20: 改为5年滚动分位(P20/P40/P60/P80)+3个月动量；须与库存、价差或利润交叉确认。
A21: 15-创新药企业净利润 | B21: 上市公司财报 | C21: +35 | D21: %YoY | E21: 上行 | F21: 0.0349 | G21: 8 | H21: >30%=10分,15-30%=8分,0-15%=6分,-15-0%=4分,<-15%=2分 | I21: 72% | J21: Q1净利润高增，重磅品种放量+费用率优化 | K21: 季度 | L21: 0.1 | M21: 目标组权重 15%；按同组相对重要性归一化。 | N21: 采用TTM/滚动4季同比+历史分位；剔除一次性损益，IRR按项目现金流复核。
A22: 16-创新药研发费用率 | B22: 上市公司财报 | C22: 28 | D22: % | E22: 上行 | F22: 0.0279 | G22: 6 | H22: >30%=10分,25-30%=8分,20-25%=6分,15-20%=4分,<15%=2分 | I22: 65% | J22: 研发费用率维持高位，管线投入大 | K22: 季度 | L22: 0.08 | M22: 目标组权重 15%；按同组相对重要性归一化。 | N22: 采用5年滚动分位+同比/环比双阈值；数据滞后超过一个频率周期时自动降权。
A23: 17-创新药销售费用率 | B23: 上市公司财报 | C23: 38 | D23: % | E23: 下行 | F23: 0.0244 | G23: 8 | H23: <35%=10分,35-45%=8分,45-55%=6分,55-65%=4分,>65%=2分 | I23: 58% | J23: 销售费用率下降，学术推广效率提升 | K23: 季度 | L23: 0.07 | M23: 目标组权重 15%；按同组相对重要性归一化。 | N23: 采用5年滚动分位+同比/环比双阈值；数据滞后超过一个频率周期时自动降权。
A24: 18-创新药经营性现金流 | B24: 上市公司财报 | C24: +28 | D24: %YoY | E24: 上行 | F24: 0.0279 | G24: 8 | H24: >30%=10分,15-30%=8分,0-15%=6分,-15-0%=4分,<-15%=2分 | I24: 68% | J24: 现金流改善，BD首付款+销售回款增加 | K24: 季度 | L24: 0.08 | M24: 目标组权重 15%；按同组相对重要性归一化。 | N24: 采用TTM/滚动4季同比+历史分位；剔除一次性损益，IRR按项目现金流复核。
A25: 行业综合景气度加权得分 | G25: =ROUND(SUMPRODUCT(F5:F24,G5:G24),1) -> 8 | H25: 综合分=Σ(建议权重×单项评分)，建议权重和=100%。
